Workbook

Sheet 高净值
A1: 账户规划 | B1: 匹配策略 | C1: 工具-BLOCK | D1: 参考基准 | E1: 入池或模块筛选标准 | F1: 工具示例
A2: 增值 | B2: 对标大势 | C2: 1.精品私募 2.公募池（涵盖11个板块33只基金-主动*10，被动*23） 3.投顾组合（e.g.奇点1号、2号） | D2: 科创创业50等权 （932381.CSI） | E2: 1、风格明确的高仓/满仓运作的工具化产品 2、受益于全球AI供应链景气（AI基建）或受益于国产替代景气（半导体材料、设备、芯片等） 3、符合国家“十五五”战略发展方向 4、采用景气度趋势投资等策略跟踪产业方向 5、私募管理人风格鲜明且稳定，业绩前1/5 | F2: 1.全球人工智能指数、龙旗科技创新 2.同大众版工具库
B3: 对标市场 | C3: 1.精品私募 2.宽基指基或指增基金 | D3: 中证800 （000906.sh） | E3: 1.指数-跟踪误差低、规模头部前1/5 2.指增-α稳定且始终处于同类前1/3 | F3: 1.掘金宝系列、龙翔、龙腾、麒麟（宝）系列 2.同大众版工具库
A6: 生息 | B6: 债券生息 | C6: 1.精品私募 2.短期及中长期债券公募指基 | D6: 中债新综合指数 （CBA00101.CB） | E6: 1.管理人、规模、流动性 2.良好的风险治理架构 | F6: 1.合晟同晖3号、岚湖、利位优势轮动等 2.同大众版工具库
B11: 波动生息 | C11: 1.金兔、青鸾系列 2.投顾组合（e.g.梧桐） | D11: LC+4% | E11: 结构化策略 | F11: 金兔系列、青鸾
B12: 低波多资产 | C12: 1.魔方系列 2.投顾组合（e.g.百灵） | D12: 中证MARP （930929.CSI） | E12: 策略稳定、业绩可追溯 | F12: 魔方系列
B13: 低波多策略 | C13: CTA及中性套利等多策略 | D13: LC+4% | E13: 策略稳定、业绩可追溯 | F13: 千象、聚金宝、伯乐5号、锐联多元化、博润银泰稳健等
A14: 保障 | B14: 保身家 | C14: 寿险、杠杆寿 | D14: -- | E14: -- | F14: 杠杆寿系列

Sheet 超高净
A1: 账户规划 | B1: 匹配策略 | C1: 工具-BLOCK | D1: 参考基准 | E1: 入池或模块筛选标准 | F1: 工具示例
A2: 增值 | B2: 对标大势 | C2: 1.精品私募 2.公募池（涵盖11个板块33只基金-主动*10，被动*23） 3.投顾组合（e.g.奇点1号、2号） 4、私募股权基金 | D2: 科创创业50等权 （932381.CSI） | E2: 1、风格明确的高仓/满仓运作的工具化产品 2、受益于全球AI供应链景气（AI基建）或受益于国产替代景气（半导体材料、设备、芯片等） 3、符合国家“十五五”战略发展方向 4、采用景气度趋势投资等策略跟踪产业方向 5、私募管理人风格鲜明且稳定，业绩前1/5 | F2: 1.高景气策略（私募）、全球人工智能指数、龙旗科技创新 2.同大众版工具库
B3: 对标市场 | C3: 1.精品私募 2.宽基指基或指增基金 | D3: 中证800 （000906.SH） | E3: 1.指数-跟踪误差低、规模头部前1/5 2.指增-α稳定且始终处于同类前1/3 | F3: 1.掘金宝系列、龙翔、龙腾、麒麟（宝）系列 2.同大众版工具库
A6: 生息 | B6: 债券生息 | C6: 1.精品私募 2.短期及中长期债券公募指基 | D6: 中债新综合指数 （CBA00101.CB） | E6: 1.管理人、规模、流动性 2.良好的风险治理架构 | F6: 1.合晟同晖3号、岚湖、利位优势轮动等 2.同大众版工具库
B11: 波动生息 | C11: 1.金兔、青鸾系列 2.投顾组合（e.g.梧桐） | D11: LC+4% | E11: 结构化策略 | F11: 金兔系列、青鸾
B12: 低波多资产 | C12: 1.魔方系列 2.投顾组合（e.g.百灵） | D12: 中证MARP （930929.CSI） | E12: 策略稳定、业绩可追溯 | F12: 魔方系列
B13: 低波多策略 | C13: CTA及中性套利等多策略 | D13: LC+4% | E13: 策略稳定、业绩可追溯 | F13: 千象、聚金宝、伯乐5号、锐联多元化、博润银泰稳健等
B14: 长期生息 | C14: 实物资产、储蓄分红 | D14: ？ | E14: ？ | F14: -
A15: 保障 | B15: 保身家 | C15: 寿险、杠杆寿 | D15: -- | E15: -- | F15: 杠杆寿系列

Sheet 大众
A1: 账户规划 | B1: 匹配策略 | C1: 工具-BLOCK | D1: 参考基准 | E1: 入池或模块筛选标准 | F1: 工具示例
A2: 增值 | B2: 对标大势 | C2: 1. 公募池（涵盖11个方向33只基金-主动*10，被动*23） 2. 投顾组合（e.g.奇点1号、2号？） | D2: 科创创业50等权 （932381.CSI） | E2: 1、风格明确的高仓/满仓运作的工具化产品 2、受益于全球AI供应链景气（AI基建）或受益于国产替代景气（半导体材料、设备、芯片等） 3、符合国家“十五五”战略发展方向 4、采用景气度趋势投资等策略跟踪产业方向 | F2: 1.见产业趋势池-公募 2.自主构建“奇点”投顾组合系列
B3: 对标市场 | C3: 1.宽基指基或指增基金 2.投顾组合（e.g.瑞鹤） | D3: 中证800 （000906.SH） | E3: 1.指数-跟踪误差低、规模头部前1/5 2.指增-α稳定且始终处于同类前1/3 | F3: 国泰海通中证500指数增强A（014155.OF）
F4: 汇添富中证1000指数增强A（017953.OF）
F6: 瑞鹤指增宝（中证1000增强）
A7: 生息 | B7: 债券生息 | C7: 1.短期及中长期债券公募指基 2、投顾组合（e.g.嘉蝠） | D7: 中债新综合指数 （CBA00101.CB） | E7: 1.管理人、规模、流动性 2.α稳定 | F7: 综合债-易方达中债新综指(LOF)A（161119.OF）
F8: 长债利率-广发中债7-10年国开债指数A（003376.OF）
F9: 长债信用-易方达优选投资级信用指数发起式A（018996.OF）
F10: 中短债-嘉实中短债债券A（006797.OF）
F11: 投顾组合-嘉蝠固收优选
B12: 波动生息 | C12: 投顾组合（e.g.梧桐） | D12: LC+4% | E12: 策略稳定、业绩可追溯 | F12: 梧桐系列
B13: 低波多资产 | C13: 投顾组合（e.g.百灵） | D13: 中证MARP （930929.CSI） | E13: 策略稳定、业绩可追溯 | F13: 百灵
A14: 保障 | B14: 黄金 | C14: 指数基金 | D14: 上海金 | E14: 1.规模、流动性 | F14: 国泰黄金ETF联接A（000218.OF） 华安黄金ETF联接A（000216.OF）

Sheet 增值序列
B1: 50%奇点1号+50%奇点2号 | G1: 931187.CSI | H1: 300-500-1000-2000指增等权
A2: 日期 | B2: 奇点组合 | C2: 奇点1号 | D2: 奇点2号 | E2: 科创创业50等权 | F2: 中证800 | G2: 中证科技100 | H2: 指增组合 | I2: 增值组合
A3: 43832 | B3: 1.0255811 | C3: 1.0238067 | D3: 1.0273555 | E3: 1.022877 | F3: 1.0147986 | G3: =[1]!thsiFinD("ths_int_chg_ratio_index",G$1,$A$3,$A3,101)/100+1 -> 1.0262842 | H3: 1.0173101 | I3: =D3*0.5+H3*0.5 -> 1.0223328 | J3: =I3/I2-1 -> #VALUE! | K3: =MAX(I$3:I3) -> 1.0223328 | L3: =I3/K3-1 -> 0
A4: 43833 | B4: 1.0299986 | C4: 1.0262594 | D4: 1.0337378 | E4: 1.0237908 | F4: 1.0140972 | G4: =[1]!thsiFinD("ths_int_chg_ratio_index",G$1,$A$3,$A4,101)/100+1 -> 1.0279941 | H4: 1.0202139 | I4: =D4*0.5+H4*0.5 -> 1.0269759 | J4: =I4/I3-1 -> 0.0045416487 | K4: =MAX(I$3:I4) -> 1.0269759 | L4: =I4/K4-1 -> 0
A5: 43836 | B5: 1.0380842 | C5: 1.0318116 | D5: 1.0443567 | E5: 1.0321693 | F5: 1.0136224 | G5: =[1]!thsiFinD("ths_int_chg_ratio_index",G$1,$A$3,$A5,101)/100+1 -> 1.028522 | H5: 1.0263972 | I5: =D5*0.5+H5*0.5 -> 1.0353769 | J5: =I5/I4-1 -> 0.0081804002 | K5: =MAX(I$3:I5) -> 1.0353769 | L5: =I5/K5-1 -> 0
A6: 43837 | B6: 1.0444645 | C6: 1.0400458 | D6: 1.0488831 | E6: 1.0429945 | F6: 1.0223099 | G6: =[1]!thsiFinD("ths_int_chg_ratio_index",G$1,$A$3,$A6,101)/100+1 -> 1.0379423 | H6: 1.0393231 | I6: =D6*0.5+H6*0.5 -> 1.0441031 | J6: =I6/I5-1 -> 0.0084280108 | K6: =MAX(I$3:I6) -> 1.0441031 | L6: =I6/K6-1 -> 0
A7: 43838 | B7: 1.0299565 | C7: 1.0269667 | D7: 1.0329462 | E7: 1.0372105 | F7: 1.0099639 | G7: =[1]!thsiFinD("ths_int_chg_ratio_index",G$1,$A$3,$A7,101)/100+1 -> 1.029766 | H7: 1.0261808 | I7: =D7*0.5+H7*0.5 -> 1.0295635 | J7: =I7/I6-1 -> -0.013925434 | K7: =MAX(I$3:I7) -> 1.0441031 | L7: =I7/K7-1 -> -0.013925434
A8: 43839 | B8: 1.0578962 | C8: 1.0559455 | D8: 1.0598469 | E8: 1.0643465 | F8: 1.0229774 | G8: =[1]!thsiFinD("ths_int_chg_ratio_index",G$1,$A$3,$A8,101)/100+1 -> 1.0521272 | H8: 1.0416767 | I8: =D8*0.5+H8*0.5 -> 1.0507618 | J8: =I8/I7-1 -> 0.020589586 | K8: =MAX(I$3:I8) -> 1.0507618 | L8: =I8/K8-1 -> 0
A9: 43840 | B9: 1.0629979 | C9: 1.0585585 | D9: 1.0674373 | E9: 1.0626663 | F9: 1.0219762 | G9: =[1]!thsiFinD("ths_int_chg_ratio_index",G$1,$A$3,$A9,101)/100+1 -> 1.055762 | H9: 1.0406964 | I9: =D9*0.5+H9*0.5 -> 1.0540669 | J9: =I9/I8-1 -> 0.0031454061 | K9: =MAX(I$3:I9) -> 1.0540669 | L9: =I9/K9-1 -> 0
A10: 43843 | B10: 1.093894 | C10: 1.0909374 | D10: 1.0968505 | E10: 1.092189 | F10: 1.0331502 | G10: =[1]!thsiFinD("ths_int_chg_ratio_index",G$1,$A$3,$A10,101)/100+1 -> 1.0708176 | H10: 1.0533907 | I10: =D10*0.5+H10*0.5 -> 1.0751206 | J10: =I10/I9-1 -> 0.019973835 | K10: =MAX(I$3:I10) -> 1.0751206 | L10: =I10/K10-1 -> 0
A11: 43844 | B11: 1.0917522 | C11: 1.0894067 | D11: 1.0940977 | E11: 1.0935226 | F11: 1.0297456 | G11: =[1]!thsiFinD("ths_int_chg_ratio_index",G$1,$A$3,$A11,101)/100+1 -> 1.0645131 | H11: 1.0518627 | I11: =D11*0.5+H11*0.5 -> 1.0729802 | J11: =I11/I10-1 -> -0.0019908755 | K11: =MAX(I$3:I11) -> 1.0751206 | L11: =I11/K11-1 -> -0.0019908755
A12: 43845 | B12: 1.0981376 | C12: 1.096209 | D12: 1.1000663 | E12: 1.0960574 | F12: 1.0248815 | G12: =[1]!thsiFinD("ths_int_chg_ratio_index",G$1,$A$3,$A12,101)/100+1 -> 1.0682675 | H12: 1.0491022 | I12: =D12*0.5+H12*0.5 -> 1.0745843 | J12: =I12/I11-1 -> 0.0014949614 | K12: =MAX(I$3:I12) -> 1.0751206 | L12: =I12/K12-1 -> -0.00049889037
A13: 43846 | B13: 1.1074447 | C13: 1.1110572 | D13: 1.1038321 | E13: 1.1141374 | F13: 1.0214824 | G13: =[1]!thsiFinD("ths_int_chg_ratio_index",G$1,$A$3,$A13,101)/100+1 -> 1.0674689 | H13: 1.0476066 | I13: =D13*0.5+H13*0.5 -> 1.0757194 | J13: =I13/I12-1 -> 0.0010563363 | K13: =MAX(I$3:I13) -> 1.0757194 | L13: =I13/K13-1 -> 0
A14: 43847 | B14: 1.119527 | C14: 1.1336678 | D14: 1.1053862 | E14: 1.151934 | F14: 1.0217692 | G14: =[1]!thsiFinD("ths_int_chg_ratio_index",G$1,$A$3,$A14,101)/100+1 -> 1.0708384 | H14: 1.0448327 | I14: =D14*0.5+H14*0.5 -> 1.0751094 | J14: =I14/I13-1 -> -0.00056702124 | K14: =MAX(I$3:I14) -> 1.0757194 | L14: =I14/K14-1 -> -0.00056702124
... A1534: 46142 | B1534: 3.8381333 | C1534: 2.6500447 | D1534: 5.0262218 | E1534: 1.5769944 | F1534: 1.2658054 | G1534: =[1]!thsiFinD("ths_int_chg_ratio_index",G$1,$A$3,$A1534,101)/100+1 -> 2.0603068 | H1534: 2.0825817 | I1534: =D1534*0.5+H1534*0.5 -> 3.5544017 | J1534: =I1534/I1533-1 -> 0.0024991528 | K1534: =MAX(I$3:I1534) -> 3.6092552 | L1534: =I1534/K1534-1 -> -0.015198002
J1536: =STDEV(J4:J1534)*250^0.5 -> 0.24782811 | L1536: =MIN(L3:L1534) -> -0.39015008
H1537: 43830 | I1537: 1
H1538: 44195 | I1538: =VLOOKUP($H1538,$A$3:$L$1534,9,0) -> 1.4335467 | J1538: =I1538/I1537-1 -> 0.43354675
H1539: 44561 | I1539: =VLOOKUP($H1539,$A$3:$L$1534,9,0) -> 1.7865133 | J1539: =I1539/I1538-1 -> 0.24621908
H1540: 44925 | I1540: =VLOOKUP($H1540,$A$3:$L$1534,9,0) -> 1.3999675 | J1540: =I1540/I1539-1 -> -0.21636882
H1541: 45289 | I1541: =VLOOKUP($H1541,$A$3:$L$1534,9,0) -> 1.3931329 | J1541: =I1541/I1540-1 -> -0.0048819712
H1542: 45657 | I1542: =VLOOKUP($H1542,$A$3:$L$1534,9,0) -> 1.6760462 | J1542: =I1542/I1541-1 -> 0.20307703
H1543: 46022 | I1543: =VLOOKUP($H1543,$A$3:$L$1534,9,0) -> 2.871303 | J1543: =I1543/I1542-1 -> 0.71314067
H1544: 46142 | I1544: =VLOOKUP($H1544,$A$3:$L$1534,9,0) -> 3.5544017 | J1544: =I1544/I1543-1 -> 0.23790549
J1545: =I1544-1 -> 2.5544017

Sheet 增值

Sheet 增值-产业趋势
A1: 代码 | B1: 931160.CSI | C1: 931743.CSI | D1: 000688.SH | E1: 399673.SZ | F1: 000940.OF | G1: 001513.OF | H1: 001480.OF | I1: 001323.OF | M1: 932381.CSI | N1: 000906.SH | O1: 15 | P1: 16 | Q1: 17 | R1: 18 | S1: 19
A2: =[1]!HX_AutoDate(1,"2020-01-1","2026-09-18",-1,-1,0,0,0,0,0,"SSE",1629,0) -> 日期 | B2: 中证全指通信设备 | C2: 中证半导体材料设备 | D2: 科创50 | E2: 创业板50 | F2: 富国曹晋 | G2: 易方达郑希 | H2: 财通金梓才 | I2: 东吴刘元海 | J2: 奇点组合 | K2: 奇点1号 | L2: 奇点2号 | M2: 科创创业50等权 | N2: 中证800 | O2: 奇点组合 | P2: 奇点1号 | Q2: 奇点2号 | R2: 科创创业50等权 | S2: 中证800
A3: 43832 | B3: 0.25 | C3: 0.25 | D3: 0.25 | E3: 0.25 | F3: 0.25 | G3: 0.25 | H3: 0.25 | I3: 0.25 | J3: 50%奇点1号+50%奇点2号 | K3: =SUMPRODUCT(B3:E3,B$3:E$3)/100 -> 0.0025 | L3: =SUMPRODUCT(F3:I3,F$3:I$3)/100 -> 0.0025 | O3: 50%奇点1号+50%奇点2号 | Q3: =L3+1 -> 1.0025 | R3: =M3+1 -> 1
A4: 43833 | B4: =[1]!thsiFinD("ths_int_chg_ratio_index",B$1,$A$4,$A4,101) -> 0.50890893 | C4: =[1]!thsiFinD("ths_int_chg_ratio_index",C$1,$A$4,$A4,101) -> -0.092007055 | D4: =[1]!thsiFinD("ths_int_chg_ratio_index",D$1,$A$4,$A4,101) -> 0.46664615 | E4: =[1]!thsiFinD("ths_int_chg_ratio_index",E$1,$A$4,$A4,101) -> 0.080616317 | F4: =[1]!thsiFinD("ths_adjustment_nvg_ratio_fund",F$1,$A$4,$A4,101) -> 0.6752609 | G4: =[1]!thsiFinD("ths_adjustment_nvg_ratio_fund",G$1,$A$4,$A4,101) -> 0.5107832 | H4: =[1]!thsiFinD("ths_adjustment_nvg_ratio_fund",H$1,$A$4,$A4,101) -> 1 | I4: =[1]!thsiFinD("ths_adjustment_nvg_ratio_fund",I$1,$A$4,$A4,101) -> 0.29296875 | J4: =50%*K4+50%*L4 -> 0.0043039715 | K4: =SUMPRODUCT(B4:E4,B$3:E$3)/100 -> 0.0024104109 | L4: =SUMPRODUCT(F4:I4,F$3:I$3)/100 -> 0.0061975321 | M4: =[1]!thsiFinD("ths_int_chg_ratio_index",M$1,$A$4,$A4,101)/100 -> 0.00089336255 | N4: =[1]!thsiFinD("ths_int_chg_ratio_index",N$1,$A$4,$A4,101)/100 -> -0.00069124917 | O4: =J4+1 -> 1.004304 | P4: =K4+1 -> 1.0024104 | Q4: =L4+1 -> 1.0061975 | R4: =M4+1 -> 1.0008934 | S4: =N4+1 -> 0.99930875
A5: 43836 | B5: =[1]!thsiFinD("ths_int_chg_ratio_index",B$1,$A$4,$A5,101) -> 1.196003 | C5: =[1]!thsiFinD("ths_int_chg_ratio_index",C$1,$A$4,$A5,101) -> 0.094581477 | D5: =[1]!thsiFinD("ths_int_chg_ratio_index",D$1,$A$4,$A5,101) -> 0.74077931 | E5: =[1]!thsiFinD("ths_int_chg_ratio_index",E$1,$A$4,$A5,101) -> 1.1102243 | F5: =[1]!thsiFinD("ths_adjustment_nvg_ratio_fund",F$1,$A$4,$A5,101) -> 1.2891344 | G5: =[1]!thsiFinD("ths_adjustment_nvg_ratio_fund",G$1,$A$4,$A5,101) -> 2.4971623 | H5: =[1]!thsiFinD("ths_adjustment_nvg_ratio_fund",H$1,$A$4,$A5,101) -> 1.8461538 | I5: =[1]!thsiFinD("ths_adjustment_nvg_ratio_fund",I$1,$A$4,$A5,101) -> 0.9765625 | J5: =50%*K5+50%*L5 -> 0.012188251 | K5: =SUMPRODUCT(B5:E5,B$3:E$3)/100 -> 0.0078539702 | L5: =SUMPRODUCT(F5:I5,F$3:I$3)/100 -> 0.016522533 | M5: =[1]!thsiFinD("ths_int_chg_ratio_index",M$1,$A$4,$A5,101)/100 -> 0.0090844745 | N5: =[1]!thsiFinD("ths_int_chg_ratio_index",N$1,$A$4,$A5,101)/100 -> -0.0011590682 | O5: =J5+1 -> 1.0121883 | P5: =K5+1 -> 1.007854 | Q5: =L5+1 -> 1.0165225 | R5: =M5+1 -> 1.0090845 | S5: =N5+1 -> 0.99884093 | T5: =O5/O4-1 -> 0.0078504917 | U5: =P5/P4-1 -> 0.0054304697 | V5: =Q5/Q4-1 -> 0.010261405 | W5: =R5/R4-1 -> 0.0081838008 | X5: =S5/S4-1 -> -0.00046814265 | Y5: =MAX(O$4:O5) -> 1.0121883 | Z5: =MAX(P$4:P5) -> 1.007854 | AA5: =MAX(Q$4:Q5) -> 1.0165225 | AB5: =MAX(R$4:R5) -> 1.0090845 | AC5: =MAX(S$4:S5) -> 0.99930875 | AD5: =O5/Y5-1 -> 0 | AE5: =P5/Z5-1 -> 0 | AF5: =Q5/AA5-1 -> 0 | AG5: =R5/AB5-1 -> 0 | AH5: =S5/AC5-1 -> -0.00046814265
A6: 43837 | B6: =[1]!thsiFinD("ths_int_chg_ratio_index",B$1,$A$4,$A6,101) -> 1.7819438 | C6: =[1]!thsiFinD("ths_int_chg_ratio_index",C$1,$A$4,$A6,101) -> 0.076288139 | D6: =[1]!thsiFinD("ths_int_chg_ratio_index",D$1,$A$4,$A6,101) -> 2.2908075 | E6: =[1]!thsiFinD("ths_int_chg_ratio_index",E$1,$A$4,$A6,101) -> 2.2261475 | F6: =[1]!thsiFinD("ths_adjustment_nvg_ratio_fund",F$1,$A$4,$A6,101) -> 1.7188459 | G6: =[1]!thsiFinD("ths_adjustment_nvg_ratio_fund",G$1,$A$4,$A6,101) -> 2.6674234 | H6: =[1]!thsiFinD("ths_adjustment_nvg_ratio_fund",H$1,$A$4,$A6,101) -> 2.2307692 | I6: =[1]!thsiFinD("ths_adjustment_nvg_ratio_fund",I$1,$A$4,$A6,101) -> 1.7578125 | J6: =50%*K6+50%*L6 -> 0.018437547 | K6: =SUMPRODUCT(B6:E6,B$3:E$3)/100 -> 0.015937967 | L6: =SUMPRODUCT(F6:I6,F$3:I$3)/100 -> 0.020937128 | M6: =[1]!thsiFinD("ths_int_chg_ratio_index",M$1,$A$4,$A6,101)/100 -> 0.019667565 | N6: =[1]!thsiFinD("ths_int_chg_ratio_index",N$1,$A$4,$A6,101)/100 -> 0.0074017532 | O6: =J6+1 -> 1.0184375 | P6: =K6+1 -> 1.015938 | Q6: =L6+1 -> 1.0209371 | R6: =M6+1 -> 1.0196676 | S6: =N6+1 -> 1.0074018 | T6: =O6/O5-1 -> 0.0061740451 | U6: =P6/P5-1 -> 0.0080210004 | V6: =Q6/Q5-1 -> 0.0043428401 | W6: =R6/R5-1 -> 0.010487814 | X6: =S6/S5-1 -> 0.0085707555 | Y6: =MAX(O$4:O6) -> 1.0184375 | Z6: =MAX(P$4:P6) -> 1.015938 | AA6: =MAX(Q$4:Q6) -> 1.0209371 | AB6: =MAX(R$4:R6) -> 1.0196676 | AC6: =MAX(S$4:S6) -> 1.0074018 | AD6: =O6/Y6-1 -> 0 | AE6: =P6/Z6-1 -> 0 | AF6: =Q6/AA6-1 -> 0 | AG6: =R6/AB6-1 -> 0 | AH6: =S6/AC6-1 -> 0
A7: 43838 | B7: =[1]!thsiFinD("ths_int_chg_ratio_index",B$1,$A$4,$A7,101) -> -0.31280878 | C7: =[1]!thsiFinD("ths_int_chg_ratio_index",C$1,$A$4,$A7,101) -> -2.221551 | D7: =[1]!thsiFinD("ths_int_chg_ratio_index",D$1,$A$4,$A7,101) -> 3.0828458 | E7: =[1]!thsiFinD("ths_int_chg_ratio_index",E$1,$A$4,$A7,101) -> 0.73537017 | F7: =[1]!thsiFinD("ths_adjustment_nvg_ratio_fund",F$1,$A$4,$A7,101) -> 0.85942296 | G7: =[1]!thsiFinD("ths_adjustment_nvg_ratio_fund",G$1,$A$4,$A7,101) -> 1.4755959 | H7: =[1]!thsiFinD("ths_adjustment_nvg_ratio_fund",H$1,$A$4,$A7,101) -> -0.53846154 | I7: =[1]!thsiFinD("ths_adjustment_nvg_ratio_fund",I$1,$A$4,$A7,101) -> 0.390625 | J7: =50%*K7+50%*L7 -> 0.0043387981 | K7: =SUMPRODUCT(B7:E7,B$3:E$3)/100 -> 0.0032096404 | L7: =SUMPRODUCT(F7:I7,F$3:I$3)/100 -> 0.0054679558 | M7: =[1]!thsiFinD("ths_int_chg_ratio_index",M$1,$A$4,$A7,101)/100 -> 0.014012926 | N7: =[1]!thsiFinD("ths_int_chg_ratio_index",N$1,$A$4,$A7,101)/100 -> -0.0047642137 | O7: =J7+1 -> 1.0043388 | P7: =K7+1 -> 1.0032096 | Q7: =L7+1 -> 1.005468 | R7: =M7+1 -> 1.0140129 | S7: =N7+1 -> 0.99523579 | T7: =O7/O6-1 -> -0.013843509 | U7: =P7/P6-1 -> -0.012528646 | V7: =Q7/Q6-1 -> -0.015151934 | W7: =R7/R6-1 -> -0.0055455709 | X7: =S7/S6-1 -> -0.012076579 | Y7: =MAX(O$4:O7) -> 1.0184375 | Z7: =MAX(P$4:P7) -> 1.015938 | AA7: =MAX(Q$4:Q7) -> 1.0209371 | AB7: =MAX(R$4:R7) -> 1.0196676 | AC7: =MAX(S$4:S7) -> 1.0074018 | AD7: =O7/Y7-1 -> -0.013843509 | AE7: =P7/Z7-1 -> -0.012528646 | AF7: =Q7/AA7-1 -> -0.015151934 | AG7: =R7/AB7-1 -> -0.0055455709 | AH7: =S7/AC7-1 -> -0.012076579
A8: 43839 | B8: =[1]!thsiFinD("ths_int_chg_ratio_index",B$1,$A$4,$A8,101) -> 2.9441021 | C8: =[1]!thsiFinD("ths_int_chg_ratio_index",C$1,$A$4,$A8,101) -> 0.12210496 | D8: =[1]!thsiFinD("ths_int_chg_ratio_index",D$1,$A$4,$A8,101) -> 5.745509 | E8: =[1]!thsiFinD("ths_int_chg_ratio_index",E$1,$A$4,$A8,101) -> 3.8041247 | F8: =[1]!thsiFinD("ths_adjustment_nvg_ratio_fund",F$1,$A$4,$A8,101) -> 3.4376918 | G8: =[1]!thsiFinD("ths_adjustment_nvg_ratio_fund",G$1,$A$4,$A8,101) -> 3.6322361 | H8: =[1]!thsiFinD("ths_adjustment_nvg_ratio_fund",H$1,$A$4,$A8,101) -> 3.2307692 | I8: =[1]!thsiFinD("ths_adjustment_nvg_ratio_fund",I$1,$A$4,$A8,101) -> 2.34375 | J8: =50%*K8+50%*L8 -> 0.03157536 | K8: =SUMPRODUCT(B8:E8,B$3:E$3)/100 -> 0.031539602 | L8: =SUMPRODUCT(F8:I8,F$3:I$3)/100 -> 0.031611118 | M8: =[1]!thsiFinD("ths_int_chg_ratio_index",M$1,$A$4,$A8,101)/100 -> 0.04054202 | N8: =[1]!thsiFinD("ths_int_chg_ratio_index",N$1,$A$4,$A8,101)/100 -> 0.0080594913 | O8: =J8+1 -> 1.0315754 | P8: =K8+1 -> 1.0315396 | Q8: =L8+1 -> 1.0316111 | R8: =M8+1 -> 1.040542 | S8: =N8+1 -> 1.0080595 | T8: =O8/O7-1 -> 0.027118898 | U8: =P8/P7-1 -> 0.028239324 | V8: =Q8/Q7-1 -> 0.02600099 | W8: =R8/R7-1 -> 0.026162481 | X8: =S8/S7-1 -> 0.012885092 | Y8: =MAX(O$4:O8) -> 1.0315754 | Z8: =MAX(P$4:P8) -> 1.0315396 | AA8: =MAX(Q$4:Q8) -> 1.0316111 | AB8: =MAX(R$4:R8) -> 1.040542 | AC8: =MAX(S$4:S8) -> 1.0080595 | AD8: =O8/Y8-1 -> 0 | AE8: =P8/Z8-1 -> 0 | AF8: =Q8/AA8-1 -> 0 | AG8: =R8/AB8-1 -> 0 | AH8: =S8/AC8-1 -> 0
A9: 43840 | B9: =[1]!thsiFinD("ths_int_chg_ratio_index",B$1,$A$4,$A9,101) -> 3.1634807 | C9: =[1]!thsiFinD("ths_int_chg_ratio_index",C$1,$A$4,$A9,101) -> 1.417167 | D9: =[1]!thsiFinD("ths_int_chg_ratio_index",D$1,$A$4,$A9,101) -> 5.5617533 | E9: =[1]!thsiFinD("ths_int_chg_ratio_index",E$1,$A$4,$A9,101) -> 3.472864 | F9: =[1]!thsiFinD("ths_adjustment_nvg_ratio_fund",F$1,$A$4,$A9,101) -> 3.7446286 | G9: =[1]!thsiFinD("ths_adjustment_nvg_ratio_fund",G$1,$A$4,$A9,101) -> 4.0862656 | H9: =[1]!thsiFinD("ths_adjustment_nvg_ratio_fund",H$1,$A$4,$A9,101) -> 4.9230769 | I9: =[1]!thsiFinD("ths_adjustment_nvg_ratio_fund",I$1,$A$4,$A9,101) -> 2.8320312 | J9: =50%*K9+50%*L9 -> 0.036501584 | K9: =SUMPRODUCT(B9:E9,B$3:E$3)/100 -> 0.034038162 | L9: =SUMPRODUCT(F9:I9,F$3:I$3)/100 -> 0.038965006 | M9: =[1]!thsiFinD("ths_int_chg_ratio_index",M$1,$A$4,$A9,101)/100 -> 0.038899398 | N9: =[1]!thsiFinD("ths_int_chg_ratio_index",N$1,$A$4,$A9,101)/100 -> 0.0070728611 | O9: =J9+1 -> 1.0365016 | P9: =K9+1 -> 1.0340382 | Q9: =L9+1 -> 1.038965 | R9: =M9+1 -> 1.0388994 | S9: =N9+1 -> 1.0070729 | T9: =O9/O8-1 -> 0.0047754381 | U9: =P9/P8-1 -> 0.0024221663 | V9: =Q9/Q8-1 -> 0.0071285467 | W9: =R9/R8-1 -> -0.0015786212 | X9: =S9/S8-1 -> -0.00097874203 | Y9: =MAX(O$4:O9) -> 1.0365016 | Z9: =MAX(P$4:P9) -> 1.0340382 | AA9: =MAX(Q$4:Q9) -> 1.038965 | AB9: =MAX(R$4:R9) -> 1.040542 | AC9: =MAX(S$4:S9) -> 1.0080595 | AD9: =O9/Y9-1 -> 0 | AE9: =P9/Z9-1 -> 0 | AF9: =Q9/AA9-1 -> 0 | AG9: =R9/AB9-1 -> -0.0015786212 | AH9: =S9/AC9-1 -> -0.00097874203 | AT9: 2020/1/1-2026/4/30 | AU9: 奇点组合 | AV9: 奇点1号（指数） | AW9: 奇点2号（主动） | AX9: 科创创业50等权指数 | AY9: 中证800 | AZ9: 指增
A10: 43843 | B10: =[1]!thsiFinD("ths_int_chg_ratio_index",B$1,$A$4,$A10,101) -> 5.4744392 | C10: =[1]!thsiFinD("ths_int_chg_ratio_index",C$1,$A$4,$A10,101) -> 7.1878804 | D10: =[1]!thsiFinD("ths_int_chg_ratio_index",D$1,$A$4,$A10,101) -> 8.4458884 | E10: =[1]!thsiFinD("ths_int_chg_ratio_index",E$1,$A$4,$A10,101) -> 5.1033537 | F10: =[1]!thsiFinD("ths_adjustment_nvg_ratio_fund",F$1,$A$4,$A10,101) -> 6.3842848 | G10: =[1]!thsiFinD("ths_adjustment_nvg_ratio_fund",G$1,$A$4,$A10,101) -> 6.8671964 | H10: =[1]!thsiFinD("ths_adjustment_nvg_ratio_fund",H$1,$A$4,$A10,101) -> 9.0769231 | I10: =[1]!thsiFinD("ths_adjustment_nvg_ratio_fund",I$1,$A$4,$A10,101) -> 4.6875 | J10: =50%*K10+50%*L10 -> 0.066534332 | K10: =SUMPRODUCT(B10:E10,B$3:E$3)/100 -> 0.065528904 | L10: =SUMPRODUCT(F10:I10,F$3:I$3)/100 -> 0.067539761 | M10: =[1]!thsiFinD("ths_int_chg_ratio_index",M$1,$A$4,$A10,101)/100 -> 0.067761813 | N10: =[1]!thsiFinD("ths_int_chg_ratio_index",N$1,$A$4,$A10,101)/100 -> 0.018083906 | O10: =J10+1 -> 1.0665343 | P10: =K10+1 -> 1.0655289 | Q10: =L10+1 -> 1.0675398 | R10: =M10+1 -> 1.0677618 | S10: =N10+1 -> 1.0180839 | T10: =O10/O9-1 -> 0.028975111 | U10: =P10/P9-1 -> 0.030454139 | V10: =Q10/Q9-1 -> 0.027503096 | W10: =R10/R9-1 -> 0.027781722 | X10: =S10/S9-1 -> 0.010933712 | Y10: =MAX(O$4:O10) -> 1.0665343 | Z10: =MAX(P$4:P10) -> 1.0655289 | AA10: =MAX(Q$4:Q10) -> 1.0675398 | AB10: =MAX(R$4:R10) -> 1.0677618 | AC10: =MAX(S$4:S10) -> 1.0180839 | AD10: =O10/Y10-1 -> 0 | AE10: =P10/Z10-1 -> 0 | AF10: =Q10/AA10-1 -> 0 | AG10: =R10/AB10-1 -> 0 | AH10: =S10/AC10-1 -> 0 | AT10: 累计收益率 | AU10: =J1535 -> 2.8269589 | AV10: =K1552 -> 2.0271764 | AW10: =L1552 -> 4.8380314 | AX10: =M1552 -> 0.74842107 | AY10: =N1552 -> 0.26348381 | AZ10: ='增值-指数增强'!AE7 -> 1.0825817 | BA10: =增值序列!J1545 -> 2.5544017
A11: 43844 | B11: =[1]!thsiFinD("ths_int_chg_ratio_index",B$1,$A$4,$A11,101) -> 4.0253222 | C11: =[1]!thsiFinD("ths_int_chg_ratio_index",C$1,$A$4,$A11,101) -> 7.3459877 | D11: =[1]!thsiFinD("ths_int_chg_ratio_index",D$1,$A$4,$A11,101) -> 9.6676118 | E11: =[1]!thsiFinD("ths_int_chg_ratio_index",E$1,$A$4,$A11,101) -> 4.5674686 | F11: =[1]!thsiFinD("ths_adjustment_nvg_ratio_fund",F$1,$A$4,$A11,101) -> 6.0773481 | G11: =[1]!thsiFinD("ths_adjustment_nvg_ratio_fund",G$1,$A$4,$A11,101) -> 7.2077185 | H11: =[1]!thsiFinD("ths_adjustment_nvg_ratio_fund",H$1,$A$4,$A11,101) -> 8.0769231 | I11: =[1]!thsiFinD("ths_adjustment_nvg_ratio_fund",I$1,$A$4,$A11,101) -> 4.5898438 | J11: =50%*K11+50%*L11 -> 0.06444778 | K11: =SUMPRODUCT(B11:E11,B$3:E$3)/100 -> 0.064015976 | L11: =SUMPRODUCT(F11:I11,F$3:I$3)/100 -> 0.064879583 | M11: =[1]!thsiFinD("ths_int_chg_ratio_index",M$1,$A$4,$A11,101)/100 -> 0.069065587 | N11: =[1]!thsiFinD("ths_int_chg_ratio_index",N$1,$A$4,$A11,101)/100 -> 0.014728953 | O11: =J11+1 -> 1.0644478 | P11: =K11+1 -> 1.064016 | Q11: =L11+1 -> 1.0648796 | R11: =M11+1 -> 1.0690656 | S11: =N11+1 -> 1.014729 | T11: =O11/O10-1 -> -0.0019563859 | U11: =P11/P10-1 -> -0.0014198848 | V11: =Q11/Q10-1 -> -0.0024918765 | W11: =R11/R10-1 -> 0.0012210341 | X11: =S11/S10-1 -> -0.0032953596 | Y11: =MAX(O$4:O11) -> 1.0665343 | Z11: =MAX(P$4:P11) -> 1.0655289 | AA11: =MAX(Q$4:Q11) -> 1.0675398 | AB11: =MAX(R$4:R11) -> 1.0690656 | AC11: =MAX(S$4:S11) -> 1.0180839 | AD11: =O11/Y11-1 -> -0.0019563859 | AE11: =P11/Z11-1 -> -0.0014198848 | AF11: =Q11/AA11-1 -> -0.0024918765 | AG11: =R11/AB11-1 -> 0 | AH11: =S11/AC11-1 -> -0.0032953596 | AT11: 最大回撤 | AU11: =MIN(AD5:AD1535) -> -0.45012326 | AV11: =MIN(AE5:AE1535) -> -0.54459836 | AW11: =MIN(AF5:AF1535) -> -0.39614942 | AX11: =MIN(AG5:AG1535) -> -0.62688287 | AY11: =MIN(AH5:AH1535) -> -0.42957366 | AZ11: ='增值-指数增强'!AE8 -> -0.39461055 | BA11: =增值序列!L1536 -> -0.39015008
A12: 43845 | B12: =[1]!thsiFinD("ths_int_chg_ratio_index",B$1,$A$4,$A12,101) -> 4.4349226 | C12: =[1]!thsiFinD("ths_int_chg_ratio_index",C$1,$A$4,$A12,101) -> 9.8769044 | D12: =[1]!thsiFinD("ths_int_chg_ratio_index",D$1,$A$4,$A12,101) -> 9.3203804 | E12: =[1]!thsiFinD("ths_int_chg_ratio_index",E$1,$A$4,$A12,101) -> 4.59446 | F12: =[1]!thsiFinD("ths_adjustment_nvg_ratio_fund",F$1,$A$4,$A12,101) -> 7.3050952 | G12: =[1]!thsiFinD("ths_adjustment_nvg_ratio_fund",G$1,$A$4,$A12,101) -> 7.3779796 | H12: =[1]!thsiFinD("ths_adjustment_nvg_ratio_fund",H$1,$A$4,$A12,101) -> 8.6153846 | I12: =[1]!thsiFinD("ths_adjustment_nvg_ratio_fund",I$1,$A$4,$A12,101) -> 4.9804688 | J12: =50%*K12+50%*L12 -> 0.070631994 | K12: =SUMPRODUCT(B12:E12,B$3:E$3)/100 -> 0.070566668 | L12: =SUMPRODUCT(F12:I12,F$3:I$3)/100 -> 0.07069732 | M12: =[1]!thsiFinD("ths_int_chg_ratio_index",M$1,$A$4,$A12,101)/100 -> 0.071543695 | N12: =[1]!thsiFinD("ths_int_chg_ratio_index",N$1,$A$4,$A12,101)/100 -> 0.0099358575 | O12: =J12+1 -> 1.070632 | P12: =K12+1 -> 1.0705667 | Q12: =L12+1 -> 1.0706973 | R12: =M12+1 -> 1.0715437 | S12: =N12+1 -> 1.0099359 | T12: =O12/O11-1 -> 0.0058097868 | U12: =P12/P11-1 -> 0.0061565735 | V12: =Q12/Q11-1 -> 0.0054632813 | W12: =R12/R11-1 -> 0.0023180134 | X12: =S12/S11-1 -> -0.0047235229 | Y12: =MAX(O$4:O12) -> 1.070632 | Z12: =MAX(P$4:P12) -> 1.0705667 | AA12: =MAX(Q$4:Q12) -> 1.0706973 | AB12: =MAX(R$4:R12) -> 1.0715437 | AC12: =MAX(S$4:S12) -> 1.0180839 | AD12: =O12/Y12-1 -> 0 | AE12: =P12/Z12-1 -> 0 | AF12: =Q12/AA12-1 -> 0 | AG12: =R12/AB12-1 -> 0 | AH12: =S12/AC12-1 -> -0.0080033168 | AN12: 43830 | AO12: 1 | AP12: 1 | AQ12: 1 | AR12: 1 | AS12: 1 | AT12: 年化波动率 | AU12: =STDEV(T5:T1535)*250^0.5 -> 0.29534112 | AV12: =STDEV(U5:U1535)*250^0.5 -> 0.31017148 | AW12: =STDEV(V5:V1535)*250^0.5 -> 0.29742333 | AX12: =STDEV(W5:W1535)*250^0.5 -> 0.29226288 | AY12: =STDEV(X5:X1535)*250^0.5 -> 0.18947229 | AZ12: ='增值-指数增强'!AE9 -> 0.20526196 | BA12: =增值序列!J1536 -> 0.24782811
A13: 43846 | B13: =[1]!thsiFinD("ths_int_chg_ratio_index",B$1,$A$4,$A13,101) -> 4.1806114 | C13: =[1]!thsiFinD("ths_int_chg_ratio_index",C$1,$A$4,$A13,101) -> 11.73663 | D13: =[1]!thsiFinD("ths_int_chg_ratio_index",D$1,$A$4,$A13,101) -> 13.197638 | E13: =[1]!thsiFinD("ths_int_chg_ratio_index",E$1,$A$4,$A13,101) -> 4.9016698 | F13: =[1]!thsiFinD("ths_adjustment_nvg_ratio_fund",F$1,$A$4,$A13,101) -> 8.7170043 | G13: =[1]!thsiFinD("ths_adjustment_nvg_ratio_fund",G$1,$A$4,$A13,101) -> 7.2077185 | H13: =[1]!thsiFinD("ths_adjustment_nvg_ratio_fund",H$1,$A$4,$A13,101) -> 8.4615385 | I13: =[1]!thsiFinD("ths_adjustment_nvg_ratio_fund",I$1,$A$4,$A13,101) -> 5.3710938 | J13: =50%*K13+50%*L13 -> 0.07971738 | K13: =SUMPRODUCT(B13:E13,B$3:E$3)/100 -> 0.085041373 | L13: =SUMPRODUCT(F13:I13,F$3:I$3)/100 -> 0.074393388 | M13: =[1]!thsiFinD("ths_int_chg_ratio_index",M$1,$A$4,$A13,101)/100 -> 0.089219329 | N13: =[1]!thsiFinD("ths_int_chg_ratio_index",N$1,$A$4,$A13,101)/100 -> 0.0065862713 | O13: =J13+1 -> 1.0797174 | P13: =K13+1 -> 1.0850414 | Q13: =L13+1 -> 1.0743934 | R13: =M13+1 -> 1.0892193 | S13: =N13+1 -> 1.0065863 | T13: =O13/O12-1 -> 0.0084860028 | U13: =P13/P12-1 -> 0.013520601 | V13: =Q13/Q12-1 -> 0.0034520188 | W13: =R13/R12-1 -> 0.016495486 | X13: =S13/S12-1 -> -0.0033166326 | Y13: =MAX(O$4:O13) -> 1.0797174 | Z13: =MAX(P$4:P13) -> 1.0850414 | AA13: =MAX(Q$4:Q13) -> 1.0743934 | AB13: =MAX(R$4:R13) -> 1.0892193 | AC13: =MAX(S$4:S13) -> 1.0180839 | AD13: =O13/Y13-1 -> 0 | AE13: =P13/Z13-1 -> 0 | AF13: =Q13/AA13-1 -> 0 | AG13: =R13/AB13-1 -> 0 | AH13: =S13/AC13-1 -> -0.011293405 | AN13: 44195 | AO13: =VLOOKUP($AN13,$A$3:$S$1552,O$1,0) -> 1.4638865 | AP13: =VLOOKUP($AN13,$A$3:$S$1552,P$1,0) -> 1.3927331 | AQ13: =VLOOKUP($AN13,$A$3:$S$1552,Q$1,0) -> 1.5350399 | AR13: =VLOOKUP($AN13,$A$3:$S$1552,R$1,0) -> 1.6069209 | AS13: =VLOOKUP($AN13,$A$3:$S$1552,S$1,0) -> 1.2172569 | AT13: 2020年 | AU13: =AO13/AO12-1 -> 0.46388651 | AV13: =AP13/AP12-1 -> 0.39273307 | AW13: =AQ13/AQ12-1 -> 0.53503995 | AX13: =AR13/AR12-1 -> 0.60692087 | AY13: =AS13/AS12-1 -> 0.2172569 | AZ13: ='增值-指数增强'!AE10 -> 0.29090822 | BA13: =增值序列!J1538 -> 0.43354675
A14: 43847 | B14: =[1]!thsiFinD("ths_int_chg_ratio_index",B$1,$A$4,$A14,101) -> 4.5133835 | C14: =[1]!thsiFinD("ths_int_chg_ratio_index",C$1,$A$4,$A14,101) -> 11.95677 | D14: =[1]!thsiFinD("ths_int_chg_ratio_index",D$1,$A$4,$A14,101) -> 21.470567 | E14: =[1]!thsiFinD("ths_int_chg_ratio_index",E$1,$A$4,$A14,101) -> 4.9410997 | F14: =[1]!thsiFinD("ths_adjustment_nvg_ratio_fund",F$1,$A$4,$A14,101) -> 9.699202 | G14: =[1]!thsiFinD("ths_adjustment_nvg_ratio_fund",G$1,$A$4,$A14,101) -> 7.3212259 | H14: =[1]!thsiFinD("ths_adjustment_nvg_ratio_fund",H$1,$A$4,$A14,101) -> 8.0769231 | I14: =[1]!thsiFinD("ths_adjustment_nvg_ratio_fund",I$1,$A$4,$A14,101) -> 5.2734375 | J14: =50%*K14+50%*L14 -> 0.091565761 | K14: =SUMPRODUCT(B14:E14,B$3:E$3)/100 -> 0.10720455 | L14: =SUMPRODUCT(F14:I14,F$3:I$3)/100 -> 0.075926971 | M14: =[1]!thsiFinD("ths_int_chg_ratio_index",M$1,$A$4,$A14,101)/100 -> 0.1261706 | N14: =[1]!thsiFinD("ths_int_chg_ratio_index",N$1,$A$4,$A14,101)/100 -> 0.0068688928 | O14: =J14+1 -> 1.0915658 | P14: =K14+1 -> 1.1072046 | Q14: =L14+1 -> 1.075927 | R14: =M14+1 -> 1.1261706 | S14: =N14+1 -> 1.0068689 | T14: =O14/O13-1 -> 0.010973595 | U14: =P14/P13-1 -> 0.020426113 | V14: =Q14/Q13-1 -> 0.0014273948 | W14: =R14/R13-1 -> 0.033924541 | X14: =S14/S13-1 -> 0.00028077224 | Y14: =MAX(O$4:O14) -> 1.0915658 | Z14: =MAX(P$4:P14) -> 1.1072046 | AA14: =MAX(Q$4:Q14) -> 1.075927 | AB14: =MAX(R$4:R14) -> 1.1261706 | AC14: =MAX(S$4:S14) -> 1.0180839 | AD14: =O14/Y14-1 -> 0 | AE14: =P14/Z14-1 -> 0 | AF14: =Q14/AA14-1 -> 0 | AG14: =R14/AB14-1 -> 0 | AH14: =S14/AC14-1 -> -0.011015804 | AN14: 44561 | AO14: =VLOOKUP($AN14,$A$3:$S$1552,O$1,0) -> 1.8179474 | AP14: =VLOOKUP($AN14,$A$3:$S$1552,P$1,0) -> 1.6474115 | AQ14: =VLOOKUP($AN14,$A$3:$S$1552,Q$1,0) -> 1.9884833 | AR14: =VLOOKUP($AN14,$A$3:$S$1552,R$1,0) -> 1.5796178 | AS14: =VLOOKUP($AN14,$A$3:$S$1552,S$1,0) -> 1.2301716 | AT14: 2021年 | AU14: =AO14/AO13-1 -> 0.24186361 | AV14: =AP14/AP13-1 -> 0.18286235 | AW14: =AQ14/AQ13-1 -> 0.29539513 | AX14: =AR14/AR13-1 -> -0.016990935 | AY14: =AS14/AS13-1 -> 0.010609659 | AZ14: ='增值-指数增强'!AE11 -> 0.18648292 | BA14: =增值序列!J1539 -> 0.24621908
A15: 43850 | B15: =[1]!thsiFinD("ths_int_chg_ratio_index",B$1,$A$4,$A15,101) -> 7.6461889 | C15: =[1]!thsiFinD("ths_int_chg_ratio_index",C$1,$A$4,$A15,101) -> 17.862162 | D15: =[1]!thsiFinD("ths_int_chg_ratio_index",D$1,$A$4,$A15,101) -> 21.651558 | E15: =[1]!thsiFinD("ths_int_chg_ratio_index",E$1,$A$4,$A15,101) -> 7.9663259 | F15: =[1]!thsiFinD("ths_adjustment_nvg_ratio_fund",F$1,$A$4,$A15,101) -> 12.277471 | G15: =[1]!thsiFinD("ths_adjustment_nvg_ratio_fund",G$1,$A$4,$A15,101) -> 10.385925 | H15: =[1]!thsiFinD("ths_adjustment_nvg_ratio_fund",H$1,$A$4,$A15,101) -> 12.846154 | I15: =[1]!thsiFinD("ths_adjustment_nvg_ratio_fund",I$1,$A$4,$A15,101) -> 7.7148438 | J15: =50%*K15+50%*L15 -> 0.12293828 | K15: =SUMPRODUCT(B15:E15,B$3:E$3)/100 -> 0.13781559 | L15: =SUMPRODUCT(F15:I15,F$3:I$3)/100 -> 0.10806098 | M15: =[1]!thsiFinD("ths_int_chg_ratio_index",M$1,$A$4,$A15,101)/100 -> 0.15158528 | N15: =[1]!thsiFinD("ths_int_chg_ratio_index",N$1,$A$4,$A15,101)/100 -> 0.01599346 | O15: =J15+1 -> 1.1229383 | P15: =K15+1 -> 1.1378156 | Q15: =L15+1 -> 1.108061 | R15: =M15+1 -> 1.1515853 | S15: =N15+1 -> 1.0159935 | T15: =O15/O14-1 -> 0.028740846 | U15: =P15/P14-1 -> 0.027647135 | V15: =Q15/Q14-1 -> 0.029866351 | W15: =R15/R14-1 -> 0.022567352 | X15: =S15/S14-1 -> 0.0090623192 | Y15: =MAX(O$4:O15) -> 1.1229383 | Z15: =MAX(P$4:P15) -> 1.1378156 | AA15: =MAX(Q$4:Q15) -> 1.108061 | AB15: =MAX(R$4:R15) -> 1.1515853 | AC15: =MAX(S$4:S15) -> 1.0180839 | AD15: =O15/Y15-1 -> 0 | AE15: =P15/Z15-1 -> 0 | AF15: =Q15/AA15-1 -> 0 | AG15: =R15/AB15-1 -> 0 | AH15: =S15/AC15-1 -> -0.0020533135 | AN15: 44925 | AO15: =VLOOKUP($AN15,$A$3:$S$1552,O$1,0) -> 1.333535 | AP15: =VLOOKUP($AN15,$A$3:$S$1552,P$1,0) -> 1.1447699 | AQ15: =VLOOKUP($AN15,$A$3:$S$1552,Q$1,0) -> 1.5223002 | AR15: =VLOOKUP($AN15,$A$3:$S$1552,R$1,0) -> 1.1313812 | AS15: =VLOOKUP($AN15,$A$3:$S$1552,S$1,0) -> 0.96794721 | AT15: 2022年 | AU15: =AO15/AO14-1 -> -0.26646114 | AV15: =AP15/AP14-1 -> -0.30510994 | AW15: =AQ15/AQ14-1 -> -0.23444153 | AX15: =AR15/AR14-1 -> -0.28376269 | AY15: =AS15/AS14-1 -> -0.21316081 | AZ15: ='增值-指数增强'!AE12 -> -0.19298452 | BA15: =增值序列!J1540 -> -0.21636882
A16: 43851 | B16: =[1]!thsiFinD("ths_int_chg_ratio_index",B$1,$A$4,$A16,101) -> 6.3666199 | C16: =[1]!thsiFinD("ths_int_chg_ratio_index",C$1,$A$4,$A16,101) -> 18.120939 | D16: =[1]!thsiFinD("ths_int_chg_ratio_index",D$1,$A$4,$A16,101) -> 17.190034 | E16: =[1]!thsiFinD("ths_int_chg_ratio_index",E$1,$A$4,$A16,101) -> 6.9387866 | F16: =[1]!thsiFinD("ths_adjustment_nvg_ratio_fund",F$1,$A$4,$A16,101) -> 10.804174 | G16: =[1]!thsiFinD("ths_adjustment_nvg_ratio_fund",G$1,$A$4,$A16,101) -> 9.9886493 | H16: =[1]!thsiFinD("ths_adjustment_nvg_ratio_fund",H$1,$A$4,$A16,101) -> 14 | I16: =[1]!thsiFinD("ths_adjustment_nvg_ratio_fund",I$1,$A$4,$A16,101) -> 6.9335938 | J16: =50%*K16+50%*L16 -> 0.1129285 | K16: =SUMPRODUCT(B16:E16,B$3:E$3)/100 -> 0.12154095 | L16: =SUMPRODUCT(F16:I16,F$3:I$3)/100 -> 0.10431604 | M16: =[1]!thsiFinD("ths_int_chg_ratio_index",M$1,$A$4,$A16,101)/100 -> 0.13440042 | N16: =[1]!thsiFinD("ths_int_chg_ratio_index",N$1,$A$4,$A16,101)/100 -> 5.0600554e-05 | O16: =J16+1 -> 1.1129285 | P16: =K16+1 -> 1.121541 | Q16: =L16+1 -> 1.104316 | R16: =M16+1 -> 1.1344004 | S16: =N16+1 -> 1.0000506 | T16: =O16/O15-1 -> -0.0089139251 | U16: =P16/P15-1 -> -0.014303403 | V16: =Q16/Q15-1 -> -0.0033797241 | W16: =R16/R15-1 -> -0.014922787 | X16: =S16/S15-1 -> -0.015691892 | Y16: =MAX(O$4:O16) -> 1.1229383 | Z16: =MAX(P$4:P16) -> 1.1378156 | AA16: =MAX(Q$4:Q16) -> 1.108061 | AB16: =MAX(R$4:R16) -> 1.1515853 | AC16: =MAX(S$4:S16) -> 1.0180839 | AD16: =O16/Y16-1 -> -0.0089139251 | AE16: =P16/Z16-1 -> -0.014303403 | AF16: =Q16/AA16-1 -> -0.0033797241 | AG16: =R16/AB16-1 -> -0.014922787 | AH16: =S16/AC16-1 -> -0.017712985 | AN16: 45289 | AO16: =VLOOKUP($AN16,$A$3:$S$1552,O$1,0) -> 1.2927999 | AP16: =VLOOKUP($AN16,$A$3:$S$1552,P$1,0) -> 1.0514057 | AQ16: =VLOOKUP($AN16,$A$3:$S$1552,Q$1,0) -> 1.534194 | AR16: =VLOOKUP($AN16,$A$3:$S$1552,R$1,0) -> 0.9365391 | AS16: =VLOOKUP($AN16,$A$3:$S$1552,S$1,0) -> 0.86754 | AT16: 2023年 | AU16: =AO16/AO15-1 -> -0.030546776 | AV16: =AP16/AP15-1 -> -0.081557186 | AW16: =AQ16/AQ15-1 -> 0.0078130568 | AX16: =AR16/AR15-1 -> -0.17221614 | AY16: =AS16/AS15-1 -> -0.10373211 | AZ16: ='增值-指数增强'!AE13 -> -0.018795985 | BA16: =增值序列!J1541 -> -0.0048819712
A17: 43852 | B17: =[1]!thsiFinD("ths_int_chg_ratio_index",B$1,$A$4,$A17,101) -> 8.2738664 | C17: =[1]!thsiFinD("ths_int_chg_ratio_index",C$1,$A$4,$A17,101) -> 25.122288 | D17: =[1]!thsiFinD("ths_int_chg_ratio_index",D$1,$A$4,$A17,101) -> 22.045312 | E17: =[1]!thsiFinD("ths_int_chg_ratio_index",E$1,$A$4,$A17,101) -> 9.4073621 | F17: =[1]!thsiFinD("ths_adjustment_nvg_ratio_fund",F$1,$A$4,$A17,101) -> 13.627993 | G17: =[1]!thsiFinD("ths_adjustment_nvg_ratio_fund",G$1,$A$4,$A17,101) -> 13.337117 | H17: =[1]!thsiFinD("ths_adjustment_nvg_ratio_fund",H$1,$A$4,$A17,101) -> 18.153846 | I17: =[1]!thsiFinD("ths_adjustment_nvg_ratio_fund",I$1,$A$4,$A17,101) -> 9.375 | J17: =50%*K17+50%*L17 -> 0.14917848 | K17: =SUMPRODUCT(B17:E17,B$3:E$3)/100 -> 0.16212207 | L17: =SUMPRODUCT(F17:I17,F$3:I$3)/100 -> 0.13623489 | M17: =[1]!thsiFinD("ths_int_chg_ratio_index",M$1,$A$4,$A17,101)/100 -> 0.16302224 | N17: =[1]!thsiFinD("ths_int_chg_ratio_index",N$1,$A$4,$A17,101)/100 -> 0.0055747899 | O17: =J17+1 -> 1.1491785 | P17: =K17+1 -> 1.1621221 | Q17: =L17+1 -> 1.1362349 | R17: =M17+1 -> 1.1630222 | S17: =N17+1 -> 1.0055748 | T17: =O17/O16-1 -> 0.032571709 | U17: =P17/P16-1 -> 0.036183361 | V17: =Q17/Q16-1 -> 0.028903724 | W17: =R17/R16-1 -> 0.02523079 | X17: =S17/S16-1 -> 0.0055239099 | Y17: =MAX(O$4:O17) -> 1.1491785 | Z17: =MAX(P$4:P17) -> 1.1621221 | AA17: =MAX(Q$4:Q17) -> 1.1362349 | AB17: =MAX(R$4:R17) -> 1.1630222 | AC17: =MAX(S$4:S17) -> 1.0180839 | AD17: =O17/Y17-1 -> 0 | AE17: =P17/Z17-1 -> 0 | AF17: =Q17/AA17-1 -> 0 | AG17: =R17/AB17-1 -> 0 | AH17: =S17/AC17-1 -> -0.01228692 | AN17: 45657 | AO17: =VLOOKUP($AN17,$A$3:$S$1552,O$1,0) -> 1.6085686 | AP17: =VLOOKUP($AN17,$A$3:$S$1552,P$1,0) -> 1.2441342 | AQ17: =VLOOKUP($AN17,$A$3:$S$1552,Q$1,0) -> 1.973003 | AR17: =VLOOKUP($AN17,$A$3:$S$1552,R$1,0) -> 0.98554792 | AS17: =VLOOKUP($AN17,$A$3:$S$1552,S$1,0) -> 0.97340431 | AT17: 2024年 | AU17: =AO17/AO16-1 -> 0.24425181 | AV17: =AP17/AP16-1 -> 0.18330555 | AW17: =AQ17/AQ16-1 -> 0.28601918 | AX17: =AR17/AR16-1 -> 0.052329716 | AY17: =AS17/AS16-1 -> 0.12202815 | AZ17: ='增值-指数增强'!AE14 -> 0.094822329 | BA17: =增值序列!J1542 -> 0.20307703
A18: 43853 | B18: =[1]!thsiFinD("ths_int_chg_ratio_index",B$1,$A$4,$A18,101) -> 3.2796959 | C18: =[1]!thsiFinD("ths_int_chg_ratio_index",C$1,$A$4,$A18,101) -> 20.53023 | D18: =[1]!thsiFinD("ths_int_chg_ratio_index",D$1,$A$4,$A18,101) -> 17.885125 | E18: =[1]!thsiFinD("ths_int_chg_ratio_index",E$1,$A$4,$A18,101) -> 5.8190382 | F18: =[1]!thsiFinD("ths_adjustment_nvg_ratio_fund",F$1,$A$4,$A18,101) -> 10.006139 | G18: =[1]!thsiFinD("ths_adjustment_nvg_ratio_fund",G$1,$A$4,$A18,101) -> 11.180477 | H18: =[1]!thsiFinD("ths_adjustment_nvg_ratio_fund",H$1,$A$4,$A18,101) -> 14.076923 | I18: =[1]!thsiFinD("ths_adjustment_nvg_ratio_fund",I$1,$A$4,$A18,101) -> 6.4453125 | J18: =50%*K18+50%*L18 -> 0.11152867 | K18: =SUMPRODUCT(B18:E18,B$3:E$3)/100 -> 0.11878522 | L18: =SUMPRODUCT(F18:I18,F$3:I$3)/100 -> 0.10427213 | M18: =[1]!thsiFinD("ths_int_chg_ratio_index",M$1,$A$4,$A18,101)/100 -> 0.12630209 | N18: =[1]!thsiFinD("ths_int_chg_ratio_index",N$1,$A$4,$A18,101)/100 -> -0.026695258 | O18: =J18+1 -> 1.1115287 | P18: =K18+1 -> 1.1187852 | Q18: =L18+1 -> 1.1042721 | R18: =M18+1 -> 1.1263021 | S18: =N18+1 -> 0.97330474 | T18: =O18/O17-1 -> -0.032762366 | U18: =P18/P17-1 -> -0.037291133 | V18: =Q18/Q17-1 -> -0.028130417 | W18: =R18/R17-1 -> -0.031573045 | X18: =S18/S17-1 -> -0.032091147 | Y18: =MAX(O$4:O18) -> 1.1491785 | Z18: =MAX(P$4:P18) -> 1.1621221 | AA18: =MAX(Q$4:Q18) -> 1.1362349 | AB18: =MAX(R$4:R18) -> 1.1630222 | AC18: =MAX(S$4:S18) -> 1.0180839 | AD18: =O18/Y18-1 -> -0.032762366 | AE18: =P18/Z18-1 -> -0.037291133 | AF18: =Q18/AA18-1 -> -0.028130417 | AG18: =R18/AB18-1 -> -0.031573045 | AH18: =S18/AC18-1 -> -0.043983766 | AN18: 46022 | AO18: =VLOOKUP($AN18,$A$3:$S$1552,O$1,0) -> 2.9406503 | AP18: =VLOOKUP($AN18,$A$3:$S$1552,P$1,0) -> 2.0864853 | AQ18: =VLOOKUP($AN18,$A$3:$S$1552,Q$1,0) -> 3.7948152 | AR18: =VLOOKUP($AN18,$A$3:$S$1552,R$1,0) -> 1.3915357 | AS18: =VLOOKUP($AN18,$A$3:$S$1552,S$1,0) -> 1.1767276 | AT18: 2025年 | AU18: =AO18/AO17-1 -> 0.82811622 | AV18: =AP18/AP17-1 -> 0.67705812 | AW18: =AQ18/AQ17-1 -> 0.92337028 | AX18: =AR18/AR17-1 -> 0.41194122 | AY18: =AS18/AS17-1 -> 0.20887859 | AZ18: ='增值-指数增强'!AE15 -> 0.39265658 | BA18: =增值序列!J1543 -> 0.71314067
A19: 43864 | B19: =[1]!thsiFinD("ths_int_chg_ratio_index",B$1,$A$4,$A19,101) -> -6.2892155 | C19: =[1]!thsiFinD("ths_int_chg_ratio_index",C$1,$A$4,$A19,101) -> 8.475285 | D19: =[1]!thsiFinD("ths_int_chg_ratio_index",D$1,$A$4,$A19,101) -> 1.0617487 | E19: =[1]!thsiFinD("ths_int_chg_ratio_index",E$1,$A$4,$A19,101) -> -1.0038267 | F19: =[1]!thsiFinD("ths_adjustment_nvg_ratio_fund",F$1,$A$4,$A19,101) -> 2.0257827 | G19: =[1]!thsiFinD("ths_adjustment_nvg_ratio_fund",G$1,$A$4,$A19,101) -> 4.3132804 | H19: =[1]!thsiFinD("ths_adjustment_nvg_ratio_fund",H$1,$A$4,$A19,101) -> 4.8461538 | I19: =[1]!thsiFinD("ths_adjustment_nvg_ratio_fund",I$1,$A$4,$A19,101) -> -1.3671875 | J19: =50%*K19+50%*L19 -> 0.015077526 | K19: =SUMPRODUCT(B19:E19,B$3:E$3)/100 -> 0.0056099789 | L19: =SUMPRODUCT(F19:I19,F$3:I$3)/100 -> 0.024545073 | M19: =[1]!thsiFinD("ths_int_chg_ratio_index",M$1,$A$4,$A19,101)/100 -> 0.011739241 | N19: =[1]!thsiFinD("ths_int_chg_ratio_index",N$1,$A$4,$A19,101)/100 -> -0.10531309 | O19: =J19+1 -> 1.0150775 | P19: =K19+1 -> 1.00561 | Q19: =L19+1 -> 1.0245451 | R19: =M19+1 -> 1.0117392 | S19: =N19+1 -> 0.89468691 | T19: =O19/O18-1 -> -0.086773424 | U19: =P19/P18-1 -> -0.10115904 | V19: =Q19/Q18-1 -> -0.072198738 | W19: =R19/R18-1 -> -0.10171591 | X19: =S19/S18-1 -> -0.080774116 | Y19: =MAX(O$4:O19) -> 1.1491785 | Z19: =MAX(P$4:P19) -> 1.1621221 | AA19: =MAX(Q$4:Q19) -> 1.1362349 | AB19: =MAX(R$4:R19) -> 1.1630222 | AC19: =MAX(S$4:S19) -> 1.0180839 | AD19: =O19/Y19-1 -> -0.11669289 | AE19: =P19/Z19-1 -> -0.13467784 | AF19: =Q19/AA19-1 -> -0.098298175 | AG19: =R19/AB19-1 -> -0.13007748 | AH19: =S19/AC19-1 -> -0.12120513 | AN19: 46142 | AO19: =VLOOKUP($AN19,$A$3:$S$1552,O$1,0) -> 3.741689 | AP19: =VLOOKUP($AN19,$A$3:$S$1552,P$1,0) -> 2.5866241 | AQ19: =VLOOKUP($AN19,$A$3:$S$1552,Q$1,0) -> 4.8967538 | AR19: =VLOOKUP($AN19,$A$3:$S$1552,R$1,0) -> 1.5417244 | AS19: =VLOOKUP($AN19,$A$3:$S$1552,S$1,0) -> 1.2473463 | AT19: 2026年YTD | AU19: =AO19/AO18-1 -> 0.27240189 | AV19: =AP19/AP18-1 -> 0.23970397 | AW19: =AQ19/AQ18-1 -> 0.29038003 | AX19: =AR19/AR18-1 -> 0.10793013 | AY19: =AS19/AS18-1 -> 0.060012787 | AZ19: ='增值-指数增强'!AE16 -> 0.12620206 | BA19: =增值序列!J1544 -> 0.23790549
A20: 43865 | B20: =[1]!thsiFinD("ths_int_chg_ratio_index",B$1,$A$4,$A20,101) -> -6.1434311 | C20: =[1]!thsiFinD("ths_int_chg_ratio_index",C$1,$A$4,$A20,101) -> 13.924437 | D20: =[1]!thsiFinD("ths_int_chg_ratio_index",D$1,$A$4,$A20,101) -> 13.09259 | E20: =[1]!thsiFinD("ths_int_chg_ratio_index",E$1,$A$4,$A20,101) -> 4.2740635 | F20: =[1]!thsiFinD("ths_adjustment_nvg_ratio_fund",F$1,$A$4,$A20,101) -> 6.8753837 | G20: =[1]!thsiFinD("ths_adjustment_nvg_ratio_fund",G$1,$A$4,$A20,101) -> 9.7616345 | H20: =[1]!thsiFinD("ths_adjustment_nvg_ratio_fund",H$1,$A$4,$A20,101) -> 7.5384615 | I20: =[1]!thsiFinD("ths_adjustment_nvg_ratio_fund",I$1,$A$4,$A20,101) -> 2.34375 | J20: =50%*K20+50%*L20 -> 0.064583611 | K20: =SUMPRODUCT(B20:E20,B$3:E$3)/100 -> 0.062869148 | L20: =SUMPRODUCT(F20:I20,F$3:I$3)/100 -> 0.066298074 | M20: =[1]!thsiFinD("ths_int_chg_ratio_index",M$1,$A$4,$A20,101)/100 -> 0.077379001 | N20: =[1]!thsiFinD("ths_int_chg_ratio_index",N$1,$A$4,$A20,101)/100 -> -0.083669939 | O20: =J20+1 -> 1.0645836 | P20: =K20+1 -> 1.0628691 | Q20: =L20+1 -> 1.0662981 | R20: =M20+1 -> 1.077379 | S20: =N20+1 -> 0.91633006 | T20: =O20/O19-1 -> 0.048770743 | U20: =P20/P19-1 -> 0.056939738 | V20: =Q20/Q19-1 -> 0.040752722 | W20: =R20/R19-1 -> 0.064878139 | X20: =S20/S19-1 -> 0.024190752 | Y20: =MAX(O$4:O20) -> 1.1491785 | Z20: =MAX(P$4:P20) -> 1.1621221 | AA20: =MAX(Q$4:Q20) -> 1.1362349 | AB20: =MAX(R$4:R20) -> 1.1630222 | AC20: =MAX(S$4:S20) -> 1.0180839 | AD20: =O20/Y20-1 -> -0.073613342 | AE20: =P20/Z20-1 -> -0.085406624 | AF20: =Q20/AA20-1 -> -0.061551371 | AG20: =R20/AB20-1 -> -0.073638523 | AH20: =S20/AC20-1 -> -0.099946423
A21: 43866 | B21: =[1]!thsiFinD("ths_int_chg_ratio_index",B$1,$A$4,$A21,101) -> -4.3421664 | C21: =[1]!thsiFinD("ths_int_chg_ratio_index",C$1,$A$4,$A21,101) -> 15.184925 | D21: =[1]!thsiFinD("ths_int_chg_ratio_index",D$1,$A$4,$A21,101) -> 18.033263 | E21: =[1]!thsiFinD("ths_int_chg_ratio_index",E$1,$A$4,$A21,101) -> 7.889151 | F21: =[1]!thsiFinD("ths_adjustment_nvg_ratio_fund",F$1,$A$4,$A21,101) -> 8.9011664 | G21: =[1]!thsiFinD("ths_adjustment_nvg_ratio_fund",G$1,$A$4,$A21,101) -> 11.577753 | H21: =[1]!thsiFinD("ths_adjustment_nvg_ratio_fund",H$1,$A$4,$A21,101) -> 8.5384615 | I21: =[1]!thsiFinD("ths_adjustment_nvg_ratio_fund",I$1,$A$4,$A21,101) -> 3.7109375 | J21: =50%*K21+50%*L21 -> 0.086866862 | K21: =SUMPRODUCT(B21:E21,B$3:E$3)/100 -> 0.09191293 | L21: =SUMPRODUCT(F21:I21,F$3:I$3)/100 -> 0.081820795 | M21: =[1]!thsiFinD("ths_int_chg_ratio_index",M$1,$A$4,$A21,101)/100 -> 0.10735035 | N21: =[1]!thsiFinD("ths_int_chg_ratio_index",N$1,$A$4,$A21,101)/100 -> -0.070136997 | O21: =J21+1 -> 1.0868669 | P21: =K21+1 -> 1.0919129 | Q21: =L21+1 -> 1.0818208 | R21: =M21+1 -> 1.1073503 | S21: =N21+1 -> 0.929863 | T21: =O21/O20-1 -> 0.020931424 | U21: =P21/P20-1 -> 0.02732583 | V21: =Q21/Q20-1 -> 0.014557581 | W21: =R21/R20-1 -> 0.027818758 | X21: =S21/S20-1 -> 0.014768633 | Y21: =MAX(O$4:O21) -> 1.1491785 | Z21: =MAX(P$4:P21) -> 1.1621221 | AA21: =MAX(Q$4:Q21) -> 1.1362349 | AB21: =MAX(R$4:R21) -> 1.1630222 | AC21: =MAX(S$4:S21) -> 1.0180839 | AD21: =O21/Y21-1 -> -0.05422275 | AE21: =P21/Z21-1 -> -0.060414601 | AF21: =Q21/AA21-1 -> -0.047889829 | AG21: =R21/AB21-1 -> -0.047868297 | AH21: =S21/AC21-1 -> -0.086653862
A22: 43867 | B22: =[1]!thsiFinD("ths_int_chg_ratio_index",B$1,$A$4,$A22,101) -> -2.2096132 | C22: =[1]!thsiFinD("ths_int_chg_ratio_index",C$1,$A$4,$A22,101) -> 20.147353 | D22: =[1]!thsiFinD("ths_int_chg_ratio_index",D$1,$A$4,$A22,101) -> 21.479737 | E22: =[1]!thsiFinD("ths_int_chg_ratio_index",E$1,$A$4,$A22,101) -> 11.949749 | F22: =[1]!thsiFinD("ths_adjustment_nvg_ratio_fund",F$1,$A$4,$A22,101) -> 12.952732 | G22: =[1]!thsiFinD("ths_adjustment_nvg_ratio_fund",G$1,$A$4,$A22,101) -> 14.982974 | H22: =[1]!thsiFinD("ths_adjustment_nvg_ratio_fund",H$1,$A$4,$A22,101) -> 11.153846 | I22: =[1]!thsiFinD("ths_adjustment_nvg_ratio_fund",I$1,$A$4,$A22,101) -> 6.9335938 | J22: =50%*K22+50%*L22 -> 0.12173796 | K22: =SUMPRODUCT(B22:E22,B$3:E$3)/100 -> 0.12841806 | L22: =SUMPRODUCT(F22:I22,F$3:I$3)/100 -> 0.11505786 | M22: =[1]!thsiFinD("ths_int_chg_ratio_index",M$1,$A$4,$A22,101)/100 -> 0.14059159 | N22: =[1]!thsiFinD("ths_int_chg_ratio_index",N$1,$A$4,$A22,101)/100 -> -0.050005646 | O22: =J22+1 -> 1.121738 | P22: =K22+1 -> 1.1284181 | Q22: =L22+1 -> 1.1150579 | R22: =M22+1 -> 1.1405916 | S22: =N22+1 -> 0.94999435 | T22: =O22/O21-1 -> 0.032084059 | U22: =P22/P21-1 -> 0.033432275 | V22: =Q22/Q21-1 -> 0.030723267 | W22: =R22/R21-1 -> 0.03001872 | X22: =S22/S21-1 -> 0.021649803 | Y22: =MAX(O$4:O22) -> 1.1491785 | Z22: =MAX(P$4:P22) -> 1.1621221 | AA22: =MAX(Q$4:Q22) -> 1.1362349 | AB22: =MAX(R$4:R22) -> 1.1630222 | AC22: =MAX(S$4:S22) -> 1.0180839 | AD22: =O22/Y22-1 -> -0.023878377 | AE22: =P22/Z22-1 -> -0.029002124 | AF22: =Q22/AA22-1 -> -0.018637894 | AG22: =R22/AB22-1 -> -0.019286522 | AH22: =S22/AC22-1 -> -0.066880098
A23: 43868 | B23: =[1]!thsiFinD("ths_int_chg_ratio_index",B$1,$A$4,$A23,101) -> -0.59832687 | C23: =[1]!thsiFinD("ths_int_chg_ratio_index",C$1,$A$4,$A23,101) -> 24.86601 | D23: =[1]!thsiFinD("ths_int_chg_ratio_index",D$1,$A$4,$A23,101) -> 28.246228 | E23: =[1]!thsiFinD("ths_int_chg_ratio_index",E$1,$A$4,$A23,101) -> 11.420057 | F23: =[1]!thsiFinD("ths_adjustment_nvg_ratio_fund",F$1,$A$4,$A23,101) -> 16.329036 | G23: =[1]!thsiFinD("ths_adjustment_nvg_ratio_fund",G$1,$A$4,$A23,101) -> 16.00454 | H23: =[1]!thsiFinD("ths_adjustment_nvg_ratio_fund",H$1,$A$4,$A23,101) -> 13.076923 | I23: =[1]!thsiFinD("ths_adjustment_nvg_ratio_fund",I$1,$A$4,$A23,101) -> 7.9101562 | J23: =50%*K23+50%*L23 -> 0.14656828 | K23: =SUMPRODUCT(B23:E23,B$3:E$3)/100 -> 0.15983492 | L23: =SUMPRODUCT(F23:I23,F$3:I$3)/100 -> 0.13330164 | M23: =[1]!thsiFinD("ths_int_chg_ratio_index",M$1,$A$4,$A23,101)/100 -> 0.16378509 | N23: =[1]!thsiFinD("ths_int_chg_ratio_index",N$1,$A$4,$A23,101)/100 -> -0.048025453 | O23: =J23+1 -> 1.1465683 | P23: =K23+1 -> 1.1598349 | Q23: =L23+1 -> 1.1333016 | R23: =M23+1 -> 1.1637851 | S23: =N23+1 -> 0.95197455 | T23: =O23/O22-1 -> 0.022135578 | U23: =P23/P22-1 -> 0.027841507 | V23: =Q23/Q22-1 -> 0.016361282 | W23: =R23/R22-1 -> 0.020334625 | X23: =S23/S22-1 -> 0.002084426 | Y23: =MAX(O$4:O23) -> 1.1491785 | Z23: =MAX(P$4:P23) -> 1.1621221 | AA23: =MAX(Q$4:Q23) -> 1.1362349 | AB23: =MAX(R$4:R23) -> 1.1637851 | AC23: =MAX(S$4:S23) -> 1.0180839 | AD23: =O23/Y23-1 -> -0.0022713609 | AE23: =P23/Z23-1 -> -0.0019680794 | AF23: =Q23/AA23-1 -> -0.0025815522 | AG23: =R23/AB23-1 -> 0 | AH23: =S23/AC23-1 -> -0.064935079 | AT23: 产业趋势指数组合：从十五五规划支柱产业出发，以创业板50和科创板50为底仓，叠加两条投资线，一是参与全球AI产业链的企业，比如算力基建设施，比如光、存、电等；二是自主创新产业链，包括先进制程国产化、匹配国产大模型的AI基建。
A24: 43871 | B24: =[1]!thsiFinD("ths_int_chg_ratio_index",B$1,$A$4,$A24,101) -> 0.14816717 | C24: =[1]!thsiFinD("ths_int_chg_ratio_index",C$1,$A$4,$A24,101) -> 22.628644 | D24: =[1]!thsiFinD("ths_int_chg_ratio_index",D$1,$A$4,$A24,101) -> 29.667535 | E24: =[1]!thsiFinD("ths_int_chg_ratio_index",E$1,$A$4,$A24,101) -> 13.335072 | F24: =[1]!thsiFinD("ths_adjustment_nvg_ratio_fund",F$1,$A$4,$A24,101) -> 16.635973 | G24: =[1]!thsiFinD("ths_adjustment_nvg_ratio_fund",G$1,$A$4,$A24,101) -> 16.45857 | H24: =[1]!thsiFinD("ths_adjustment_nvg_ratio_fund",H$1,$A$4,$A24,101) -> 12.153846 | I24: =[1]!thsiFinD("ths_adjustment_nvg_ratio_fund",I$1,$A$4,$A24,101) -> 8.0078125 | J24: =50%*K24+50%*L24 -> 0.14879452 | K24: =SUMPRODUCT(B24:E24,B$3:E$3)/100 -> 0.16444855 | L24: =SUMPRODUCT(F24:I24,F$3:I$3)/100 -> 0.1331405 | M24: =[1]!thsiFinD("ths_int_chg_ratio_index",M$1,$A$4,$A24,101)/100 -> 0.18013466 | N24: =[1]!thsiFinD("ths_int_chg_ratio_index",N$1,$A$4,$A24,101)/100 -> -0.042336588 | O24: =J24+1 -> 1.1487945 | P24: =K24+1 -> 1.1644485 | Q24: =L24+1 -> 1.1331405 | R24: =M24+1 -> 1.1801347 | S24: =N24+1 -> 0.95766341 | T24: =O24/O23-1 -> 0.0019416581 | U24: =P24/P23-1 -> 0.0039778274 | V24: =Q24/Q23-1 -> -0.00014218278 | W24: =R24/R23-1 -> 0.014048617 | X24: =S24/S23-1 -> 0.0059758591 | Y24: =MAX(O$4:O24) -> 1.1491785 | Z24: =MAX(P$4:P24) -> 1.1644485 | AA24: =MAX(Q$4:Q24) -> 1.1362349 | AB24: =MAX(R$4:R24) -> 1.1801347 | AC24: =MAX(S$4:S24) -> 1.0180839 | AD24: =O24/Y24-1 -> -0.00033411298 | AE24: =P24/Z24-1 -> 0 | AF24: =Q24/AA24-1 -> -0.0027233679 | AG24: =R24/AB24-1 -> 0 | AH24: =S24/AC24-1 -> -0.059347263 | AT24: 代码 | AU24: 简称 | AV24: 配比
A25: 43872 | B25: =[1]!thsiFinD("ths_int_chg_ratio_index",B$1,$A$4,$A25,101) -> 0.058441244 | C25: =[1]!thsiFinD("ths_int_chg_ratio_index",C$1,$A$4,$A25,101) -> 23.050168 | D25: =[1]!thsiFinD("ths_int_chg_ratio_index",D$1,$A$4,$A25,101) -> 25.874566 | E25: =[1]!thsiFinD("ths_int_chg_ratio_index",E$1,$A$4,$A25,101) -> 12.387388 | F25: =[1]!thsiFinD("ths_adjustment_nvg_ratio_fund",F$1,$A$4,$A25,101) -> 16.206262 | G25: =[1]!thsiFinD("ths_adjustment_nvg_ratio_fund",G$1,$A$4,$A25,101) -> 16.855846 | H25: =[1]!thsiFinD("ths_adjustment_nvg_ratio_fund",H$1,$A$4,$A25,101) -> 14.692308 | I25: =[1]!thsiFinD("ths_adjustment_nvg_ratio_fund",I$1,$A$4,$A25,101) -> 8.7890625 | J25: =50%*K25+50%*L25 -> 0.14739255 | K25: =SUMPRODUCT(B25:E25,B$3:E$3)/100 -> 0.15342641 | L25: =SUMPRODUCT(F25:I25,F$3:I$3)/100 -> 0.14135869 | M25: =[1]!thsiFinD("ths_int_chg_ratio_index",M$1,$A$4,$A25,101)/100 -> 0.17187844 | N25: =[1]!thsiFinD("ths_int_chg_ratio_index",N$1,$A$4,$A25,101)/100 -> -0.036859152 | O25: =J25+1 -> 1.1473926 | P25: =K25+1 -> 1.1534264 | Q25: =L25+1 -> 1.1413587 | R25: =M25+1 -> 1.1718784 | S25: =N25+1 -> 0.96314085 | T25: =O25/O24-1 -> -0.0012203874 | U25: =P25/P24-1 -> -0.0094655436 | V25: =Q25/Q24-1 -> 0.0072525778 | W25: =R25/R24-1 -> -0.0069960003 | X25: =S25/S24-1 -> 0.0057195827 | Y25: =MAX(O$4:O25) -> 1.1491785 | Z25: =MAX(P$4:P25) -> 1.1644485 | AA25: =MAX(Q$4:Q25) -> 1.1413587 | AB25: =MAX(R$4:R25) -> 1.1801347 | AC25: =MAX(S$4:S25) -> 1.0180839 | AD25: =O25/Y25-1 -> -0.0015540927 | AE25: =P25/Z25-1 -> -0.0094655436 | AF25: =Q25/AA25-1 -> 0 | AG25: =R25/AB25-1 -> -0.0069960003 | AH25: =S25/AC25-1 -> -0.053967122 | AT25: 931160.CSI | AU25: 中证全指通信设备 | AV25: 0.25
A26: 43873 | B26: =[1]!thsiFinD("ths_int_chg_ratio_index",B$1,$A$4,$A26,101) -> 1.5574833 | C26: =[1]!thsiFinD("ths_int_chg_ratio_index",C$1,$A$4,$A26,101) -> 26.949843 | D26: =[1]!thsiFinD("ths_int_chg_ratio_index",D$1,$A$4,$A26,101) -> 32.261543 | E26: =[1]!thsiFinD("ths_int_chg_ratio_index",E$1,$A$4,$A26,101) -> 15.83974 | F26: =[1]!thsiFinD("ths_adjustment_nvg_ratio_fund",F$1,$A$4,$A26,101) -> 19.459791 | G26: =[1]!thsiFinD("ths_adjustment_nvg_ratio_fund",G$1,$A$4,$A26,101) -> 19.06924 | H26: =[1]!thsiFinD("ths_adjustment_nvg_ratio_fund",H$1,$A$4,$A26,101) -> 16.461538 | I26: =[1]!thsiFinD("ths_adjustment_nvg_ratio_fund",I$1,$A$4,$A26,101) -> 11.328125 | J26: =50%*K26+50%*L26 -> 0.17865913 | K26: =SUMPRODUCT(B26:E26,B$3:E$3)/100 -> 0.19152152 | L26: =SUMPRODUCT(F26:I26,F$3:I$3)/100 -> 0.16579674 | M26: =[1]!thsiFinD("ths_int_chg_ratio_index",M$1,$A$4,$A26,101)/100 -> 0.20788589 | N26: =[1]!thsiFinD("ths_int_chg_ratio_index",N$1,$A$4,$A26,101)/100 -> -0.026609627 | O26: =J26+1 -> 1.1786591 | P26: =K26+1 -> 1.1915215 | Q26: =L26+1 -> 1.1657967 | R26: =M26+1 -> 1.2078859 | S26: =N26+1 -> 0.97339037 | T26: =O26/O25-1 -> 0.027250115 | U26: =P26/P25-1 -> 0.033027781 | V26: =Q26/Q25-1 -> 0.02141136 | W26: =R26/R25-1 -> 0.030726274 | X26: =S26/S25-1 -> 0.010641772 | Y26: =MAX(O$4:O26) -> 1.1786591 | Z26: =MAX(P$4:P26) -> 1.1915215 | AA26: =MAX(Q$4:Q26) -> 1.1657967 | AB26: =MAX(R$4:R26) -> 1.2078859 | AC26: =MAX(S$4:S26) -> 1.0180839 | AD26: =O26/Y26-1 -> 0 | AE26: =P26/Z26-1 -> 0 | AF26: =Q26/AA26-1 -> 0 | AG26: =R26/AB26-1 -> 0 | AH26: =S26/AC26-1 -> -0.043899655 | AT26: 931743.CSI | AU26: 中证半导体材料设备 | AV26: 0.25
A27: 43874 | B27: =[1]!thsiFinD("ths_int_chg_ratio_index",B$1,$A$4,$A27,101) -> 0.58720758 | C27: =[1]!thsiFinD("ths_int_chg_ratio_index",C$1,$A$4,$A27,101) -> 29.866387 | D27: =[1]!thsiFinD("ths_int_chg_ratio_index",D$1,$A$4,$A27,101) -> 33.439068 | E27: =[1]!thsiFinD("ths_int_chg_ratio_index",E$1,$A$4,$A27,101) -> 14.764099 | F27: =[1]!thsiFinD("ths_adjustment_nvg_ratio_fund",F$1,$A$4,$A27,101) -> 19.214242 | G27: =[1]!thsiFinD("ths_adjustment_nvg_ratio_fund",G$1,$A$4,$A27,101) -> 18.444949 | H27: =[1]!thsiFinD("ths_adjustment_nvg_ratio_fund",H$1,$A$4,$A27,101) -> 16.769231 | I27: =[1]!thsiFinD("ths_adjustment_nvg_ratio_fund",I$1,$A$4,$A27,101) -> 11.132812 | J27: =50%*K27+50%*L27 -> 0.18027249 | K27: =SUMPRODUCT(B27:E27,B$3:E$3)/100 -> 0.1966419 | L27: =SUMPRODUCT(F27:I27,F$3:I$3)/100 -> 0.16390309 | M27: =[1]!thsiFinD("ths_int_chg_ratio_index",M$1,$A$4,$A27,101)/100 -> 0.20224524 | N27: =[1]!thsiFinD("ths_int_chg_ratio_index",N$1,$A$4,$A27,101)/100 -> -0.033199215 | O27: =J27+1 -> 1.1802725 | P27: =K27+1 -> 1.1966419 | Q27: =L27+1 -> 1.1639031 | R27: =M27+1 -> 1.2022452 | S27: =N27+1 -> 0.96680079 | T27: =O27/O26-1 -> 0.0013688143 | U27: =P27/P26-1 -> 0.0042973471 | V27: =Q27/Q26-1 -> -0.0016243402 | W27: =R27/R26-1 -> -0.0046698605 | X27: =S27/S26-1 -> -0.0067697278 | Y27: =MAX(O$4:O27) -> 1.1802725 | Z27: =MAX(P$4:P27) -> 1.1966419 | AA27: =MAX(Q$4:Q27) -> 1.1657967 | AB27: =MAX(R$4:R27) -> 1.2078859 | AC27: =MAX(S$4:S27) -> 1.0180839 | AD27: =O27/Y27-1 -> 0 | AE27: =P27/Z27-1 -> 0 | AF27: =Q27/AA27-1 -> -0.0016243402 | AG27: =R27/AB27-1 -> -0.0046698605 | AH27: =S27/AC27-1 -> -0.050372194 | AT27: 000688.SH | AU27: 科创50 | AV27: 0.25
A28: 43875 | B28: =[1]!thsiFinD("ths_int_chg_ratio_index",B$1,$A$4,$A28,101) -> 0.75497716 | C28: =[1]!thsiFinD("ths_int_chg_ratio_index",C$1,$A$4,$A28,101) -> 31.954376 | D28: =[1]!thsiFinD("ths_int_chg_ratio_index",D$1,$A$4,$A28,101) -> 30.155295 | E28: =[1]!thsiFinD("ths_int_chg_ratio_index",E$1,$A$4,$A28,101) -> 14.795638 | F28: =[1]!thsiFinD("ths_adjustment_nvg_ratio_fund",F$1,$A$4,$A28,101) -> 19.275629 | G28: =[1]!thsiFinD("ths_adjustment_nvg_ratio_fund",G$1,$A$4,$A28,101) -> 17.934166 | H28: =[1]!thsiFinD("ths_adjustment_nvg_ratio_fund",H$1,$A$4,$A28,101) -> 17.846154 | I28: =[1]!thsiFinD("ths_adjustment_nvg_ratio_fund",I$1,$A$4,$A28,101) -> 12.011719 | J28: =50%*K28+50%*L28 -> 0.18090994 | K28: =SUMPRODUCT(B28:E28,B$3:E$3)/100 -> 0.19415071 | L28: =SUMPRODUCT(F28:I28,F$3:I$3)/100 -> 0.16766917 | M28: =[1]!thsiFinD("ths_int_chg_ratio_index",M$1,$A$4,$A28,101)/100 -> 0.19138978 | N28: =[1]!thsiFinD("ths_int_chg_ratio_index",N$1,$A$4,$A28,101)/100 -> -0.027744949 | O28: =J28+1 -> 1.1809099 | P28: =K28+1 -> 1.1941507 | Q28: =L28+1 -> 1.1676692 | R28: =M28+1 -> 1.1913898 | S28: =N28+1 -> 0.97225505 | T28: =O28/O27-1 -> 0.00054008453 | U28: =P28/P27-1 -> -0.0020818174 | V28: =Q28/Q27-1 -> 0.0032357365 | W28: =R28/R27-1 -> -0.0090293222 | X28: =S28/S27-1 -> 0.0056415606 | Y28: =MAX(O$4:O28) -> 1.1809099 | Z28: =MAX(P$4:P28) -> 1.1966419 | AA28: =MAX(Q$4:Q28) -> 1.1676692 | AB28: =MAX(R$4:R28) -> 1.2078859 | AC28: =MAX(S$4:S28) -> 1.0180839 | AD28: =O28/Y28-1 -> 0 | AE28: =P28/Z28-1 -> -0.0020818174 | AF28: =Q28/AA28-1 -> 0 | AG28: =R28/AB28-1 -> -0.013657017 | AH28: =S28/AC28-1 -> -0.045014811 | AT28: 399673.SZ | AU28: 创业板50 | AV28: 0.25
A29: 43878 | B29: =[1]!thsiFinD("ths_int_chg_ratio_index",B$1,$A$4,$A29,101) -> 6.0261065 | C29: =[1]!thsiFinD("ths_int_chg_ratio_index",C$1,$A$4,$A29,101) -> 36.550928 | D29: =[1]!thsiFinD("ths_int_chg_ratio_index",D$1,$A$4,$A29,101) -> 35.483132 | E29: =[1]!thsiFinD("ths_int_chg_ratio_index",E$1,$A$4,$A29,101) -> 19.046607 | F29: =[1]!thsiFinD("ths_adjustment_nvg_ratio_fund",F$1,$A$4,$A29,101) -> 22.95887 | G29: =[1]!thsiFinD("ths_adjustment_nvg_ratio_fund",G$1,$A$4,$A29,101) -> 21.906924 | H29: =[1]!thsiFinD("ths_adjustment_nvg_ratio_fund",H$1,$A$4,$A29,101) -> 23.307692 | I29: =[1]!thsiFinD("ths_adjustment_nvg_ratio_fund",I$1,$A$4,$A29,101) -> 15.234375 | J29: =50%*K29+50%*L29 -> 0.22564329 | K29: =SUMPRODUCT(B29:E29,B$3:E$3)/100 -> 0.24276693 | L29: =SUMPRODUCT(F29:I29,F$3:I$3)/100 -> 0.20851965 | M29: =[1]!thsiFinD("ths_int_chg_ratio_index",M$1,$A$4,$A29,101)/100 -> 0.23987156 | N29: =[1]!thsiFinD("ths_int_chg_ratio_index",N$1,$A$4,$A29,101)/100 -> -0.0035773233 | O29: =J29+1 -> 1.2256433 | P29: =K29+1 -> 1.2427669 | Q29: =L29+1 -> 1.2085197 | R29: =M29+1 -> 1.2398716 | S29: =N29+1 -> 0.99642268 | T29: =O29/O28-1 -> 0.03788041 | U29: =P29/P28-1 -> 0.040711963 | V29: =Q29/Q28-1 -> 0.03498464 | W29: =R29/R28-1 -> 0.040693468 | X29: =S29/S28-1 -> 0.02485729 | Y29: =MAX(O$4:O29) -> 1.2256433 | Z29: =MAX(P$4:P29) -> 1.2427669 | AA29: =MAX(Q$4:Q29) -> 1.2085197 | AB29: =MAX(R$4:R29) -> 1.2398716 | AC29: =MAX(S$4:S29) -> 1.0180839 | AD29: =O29/Y29-1 -> 0 | AE29: =P29/Z29-1 -> 0 | AF29: =Q29/AA29-1 -> 0 | AG29: =R29/AB29-1 -> 0 | AH29: =S29/AC29-1 -> -0.021276467
A30: 43879 | B30: =[1]!thsiFinD("ths_int_chg_ratio_index",B$1,$A$4,$A30,101) -> 7.5453205 | C30: =[1]!thsiFinD("ths_int_chg_ratio_index",C$1,$A$4,$A30,101) -> 44.353375 | D30: =[1]!thsiFinD("ths_int_chg_ratio_index",D$1,$A$4,$A30,101) -> 37.231734 | E30: =[1]!thsiFinD("ths_int_chg_ratio_index",E$1,$A$4,$A30,101) -> 20.324023 | F30: =[1]!thsiFinD("ths_adjustment_nvg_ratio_fund",F$1,$A$4,$A30,101) -> 25.475752 | G30: =[1]!thsiFinD("ths_adjustment_nvg_ratio_fund",G$1,$A$4,$A30,101) -> 23.212259 | H30: =[1]!thsiFinD("ths_adjustment_nvg_ratio_fund",H$1,$A$4,$A30,101) -> 24.769231 | I30: =[1]!thsiFinD("ths_adjustment_nvg_ratio_fund",I$1,$A$4,$A30,101) -> 15.917969 | J30: =50%*K30+50%*L30 -> 0.24853708 | K30: =SUMPRODUCT(B30:E30,B$3:E$3)/100 -> 0.27363613 | L30: =SUMPRODUCT(F30:I30,F$3:I$3)/100 -> 0.22343803 | M30: =[1]!thsiFinD("ths_int_chg_ratio_index",M$1,$A$4,$A30,101)/100 -> 0.25632828 | N30: =[1]!thsiFinD("ths_int_chg_ratio_index",N$1,$A$4,$A30,101)/100 -> -0.0042758505 | O30: =J30+1 -> 1.2485371 | P30: =K30+1 -> 1.2736361 | Q30: =L30+1 -> 1.223438 | R30: =M30+1 -> 1.2563283 | S30: =N30+1 -> 0.99572415 | T30: =O30/O29-1 -> 0.018678994 | U30: =P30/P29-1 -> 0.024839087 | V30: =Q30/Q29-1 -> 0.012344335 | W30: =R30/R29-1 -> 0.013272923 | X30: =S30/S29-1 -> -0.000701035 | Y30: =MAX(O$4:O30) -> 1.2485371 | Z30: =MAX(P$4:P30) -> 1.2736361 | AA30: =MAX(Q$4:Q30) -> 1.223438 | AB30: =MAX(R$4:R30) -> 1.2563283 | AC30: =MAX(S$4:S30) -> 1.0180839 | AD30: =O30/Y30-1 -> 0 | AE30: =P30/Z30-1 -> 0 | AF30: =Q30/AA30-1 -> 0 | AG30: =R30/AB30-1 -> 0 | AH30: =S30/AC30-1 -> -0.021962587 | AT30: 产业趋势主动组合：精选2020年以来在不同产业发挥阶段对产业趋势均有捕获的基金经理，且框架稳定，长期超额出色
A31: 43880 | B31: =[1]!thsiFinD("ths_int_chg_ratio_index",B$1,$A$4,$A31,101) -> 7.2612944 | C31: =[1]!thsiFinD("ths_int_chg_ratio_index",C$1,$A$4,$A31,101) -> 45.586493 | D31: =[1]!thsiFinD("ths_int_chg_ratio_index",D$1,$A$4,$A31,101) -> 34.687887 | E31: =[1]!thsiFinD("ths_int_chg_ratio_index",E$1,$A$4,$A31,101) -> 17.635613 | F31: =[1]!thsiFinD("ths_adjustment_nvg_ratio_fund",F$1,$A$4,$A31,101) -> 24.923266 | G31: =[1]!thsiFinD("ths_adjustment_nvg_ratio_fund",G$1,$A$4,$A31,101) -> 20.601589 | H31: =[1]!thsiFinD("ths_adjustment_nvg_ratio_fund",H$1,$A$4,$A31,101) -> 22.846154 | I31: =[1]!thsiFinD("ths_adjustment_nvg_ratio_fund",I$1,$A$4,$A31,101) -> 13.378906 | J31: =50%*K31+50%*L31 -> 0.2336515 | K31: =SUMPRODUCT(B31:E31,B$3:E$3)/100 -> 0.26292822 | L31: =SUMPRODUCT(F31:I31,F$3:I$3)/100 -> 0.20437479 | M31: =[1]!thsiFinD("ths_int_chg_ratio_index",M$1,$A$4,$A31,101)/100 -> 0.23521724 | N31: =[1]!thsiFinD("ths_int_chg_ratio_index",N$1,$A$4,$A31,101)/100 -> -0.0079725468 | O31: =J31+1 -> 1.2336515 | P31: =K31+1 -> 1.2629282 | Q31: =L31+1 -> 1.2043748 | R31: =M31+1 -> 1.2352172 | S31: =N31+1 -> 0.99202745 | T31: =O31/O30-1 -> -0.011922413 | U31: =P31/P30-1 -> -0.0084073558 | V31: =Q31/Q30-1 -> -0.015581695 | W31: =R31/R30-1 -> -0.016803763 | X31: =S31/S30-1 -> -0.0037125708 | Y31: =MAX(O$4:O31) -> 1.2485371 | Z31: =MAX(P$4:P31) -> 1.2736361 | AA31: =MAX(Q$4:Q31) -> 1.223438 | AB31: =MAX(R$4:R31) -> 1.2563283 | AC31: =MAX(S$4:S31) -> 1.0180839 | AD31: =O31/Y31-1 -> -0.011922413 | AE31: =P31/Z31-1 -> -0.0084073558 | AF31: =Q31/AA31-1 -> -0.015581695 | AG31: =R31/AB31-1 -> -0.016803763 | AH31: =S31/AC31-1 -> -0.02559362 | AT31: 代码 | AU31: 基金经理 | AV31: 配比
A32: 43881 | B32: =[1]!thsiFinD("ths_int_chg_ratio_index",B$1,$A$4,$A32,101) -> 9.5558182 | C32: =[1]!thsiFinD("ths_int_chg_ratio_index",C$1,$A$4,$A32,101) -> 48.6817 | D32: =[1]!thsiFinD("ths_int_chg_ratio_index",D$1,$A$4,$A32,101) -> 32.225827 | E32: =[1]!thsiFinD("ths_int_chg_ratio_index",E$1,$A$4,$A32,101) -> 20.643619 | F32: =[1]!thsiFinD("ths_adjustment_nvg_ratio_fund",F$1,$A$4,$A32,101) -> 27.808471 | G32: =[1]!thsiFinD("ths_adjustment_nvg_ratio_fund",G$1,$A$4,$A32,101) -> 23.212259 | H32: =[1]!thsiFinD("ths_adjustment_nvg_ratio_fund",H$1,$A$4,$A32,101) -> 26.769231 | I32: =[1]!thsiFinD("ths_adjustment_nvg_ratio_fund",I$1,$A$4,$A32,101) -> 16.015625 | J32: =50%*K32+50%*L32 -> 0.25614069 | K32: =SUMPRODUCT(B32:E32,B$3:E$3)/100 -> 0.27776741 | L32: =SUMPRODUCT(F32:I32,F$3:I$3)/100 -> 0.23451397 | M32: =[1]!thsiFinD("ths_int_chg_ratio_index",M$1,$A$4,$A32,101)/100 -> 0.24631134 | N32: =[1]!thsiFinD("ths_int_chg_ratio_index",N$1,$A$4,$A32,101)/100 -> 0.013743474 | O32: =J32+1 -> 1.2561407 | P32: =K32+1 -> 1.2777674 | Q32: =L32+1 -> 1.234514 | R32: =M32+1 -> 1.2463113 | S32: =N32+1 -> 1.0137435 | T32: =O32/O31-1 -> 0.018229772 | U32: =P32/P31-1 -> 0.011749831 | V32: =Q32/Q31-1 -> 0.02502475 | W32: =R32/R31-1 -> 0.0089814973 | X32: =S32/S31-1 -> 0.021890545 | Y32: =MAX(O$4:O32) -> 1.2561407 | Z32: =MAX(P$4:P32) -> 1.2777674 | AA32: =MAX(Q$4:Q32) -> 1.234514 | AB32: =MAX(R$4:R32) -> 1.2563283 | AC32: =MAX(S$4:S32) -> 1.0180839 | AD32: =O32/Y32-1 -> 0 | AE32: =P32/Z32-1 -> 0 | AF32: =Q32/AA32-1 -> 0 | AG32: =R32/AB32-1 -> -0.0079731887 | AH32: =S32/AC32-1 -> -0.0042633335 | AT32: 000940.OF | AU32: 富国曹晋 | AV32: 0.25
A33: 43882 | B33: =[1]!thsiFinD("ths_int_chg_ratio_index",B$1,$A$4,$A33,101) -> 12.821787 | C33: =[1]!thsiFinD("ths_int_chg_ratio_index",C$1,$A$4,$A33,101) -> 51.776538 | D33: =[1]!thsiFinD("ths_int_chg_ratio_index",D$1,$A$4,$A33,101) -> 32.08119 | E33: =[1]!thsiFinD("ths_int_chg_ratio_index",E$1,$A$4,$A33,101) -> 23.476276 | F33: =[1]!thsiFinD("ths_adjustment_nvg_ratio_fund",F$1,$A$4,$A33,101) -> 29.343155 | G33: =[1]!thsiFinD("ths_adjustment_nvg_ratio_fund",G$1,$A$4,$A33,101) -> 25.425653 | H33: =[1]!thsiFinD("ths_adjustment_nvg_ratio_fund",H$1,$A$4,$A33,101) -> 30.538462 | I33: =[1]!thsiFinD("ths_adjustment_nvg_ratio_fund",I$1,$A$4,$A33,101) -> 17.96875 | J33: =50%*K33+50%*L33 -> 0.27928976 | K33: =SUMPRODUCT(B33:E33,B$3:E$3)/100 -> 0.30038948 | L33: =SUMPRODUCT(F33:I33,F$3:I$3)/100 -> 0.25819005 | M33: =[1]!thsiFinD("ths_int_chg_ratio_index",M$1,$A$4,$A33,101)/100 -> 0.26533503 | N33: =[1]!thsiFinD("ths_int_chg_ratio_index",N$1,$A$4,$A33,101)/100 -> 0.018069004 | O33: =J33+1 -> 1.2792898 | P33: =K33+1 -> 1.3003895 | Q33: =L33+1 -> 1.25819 | R33: =M33+1 -> 1.265335 | S33: =N33+1 -> 1.018069 | T33: =O33/O32-1 -> 0.018428727 | U33: =P33/P32-1 -> 0.017704369 | V33: =Q33/Q32-1 -> 0.019178466 | W33: =R33/R32-1 -> 0.015263999 | X33: =S33/S32-1 -> 0.0042668879 | Y33: =MAX(O$4:O33) -> 1.2792898 | Z33: =MAX(P$4:P33) -> 1.3003895 | AA33: =MAX(Q$4:Q33) -> 1.25819 | AB33: =MAX(R$4:R33) -> 1.265335 | AC33: =MAX(S$4:S33) -> 1.0180839 | AD33: =O33/Y33-1 -> 0 | AE33: =P33/Z33-1 -> 0 | AF33: =Q33/AA33-1 -> 0 | AG33: =R33/AB33-1 -> 0 | AH33: =S33/AC33-1 -> -1.4636793e-05 | AT33: 001513.OF | AU33: 易方达郑希 | AV33: 0.25
A34: 43885 | B34: =[1]!thsiFinD("ths_int_chg_ratio_index",B$1,$A$4,$A34,101) -> 20.464126 | C34: =[1]!thsiFinD("ths_int_chg_ratio_index",C$1,$A$4,$A34,101) -> 60.847763 | D34: =[1]!thsiFinD("ths_int_chg_ratio_index",D$1,$A$4,$A34,101) -> 32.556515 | E34: =[1]!thsiFinD("ths_int_chg_ratio_index",E$1,$A$4,$A34,101) -> 25.674586 | F34: =[1]!thsiFinD("ths_adjustment_nvg_ratio_fund",F$1,$A$4,$A34,101) -> 33.210559 | G34: =[1]!thsiFinD("ths_adjustment_nvg_ratio_fund",G$1,$A$4,$A34,101) -> 28.320091 | H34: =[1]!thsiFinD("ths_adjustment_nvg_ratio_fund",H$1,$A$4,$A34,101) -> 37.076923 | I34: =[1]!thsiFinD("ths_adjustment_nvg_ratio_fund",I$1,$A$4,$A34,101) -> 20.507812 | J34: =50%*K34+50%*L34 -> 0.32332297 | K34: =SUMPRODUCT(B34:E34,B$3:E$3)/100 -> 0.34885747 | L34: =SUMPRODUCT(F34:I34,F$3:I$3)/100 -> 0.29778846 | M34: =[1]!thsiFinD("ths_int_chg_ratio_index",M$1,$A$4,$A34,101)/100 -> 0.28401597 | N34: =[1]!thsiFinD("ths_int_chg_ratio_index",N$1,$A$4,$A34,101)/100 -> 0.018638255 | O34: =J34+1 -> 1.323323 | P34: =K34+1 -> 1.3488575 | Q34: =L34+1 -> 1.2977885 | R34: =M34+1 -> 1.284016 | S34: =N34+1 -> 1.0186383 | T34: =O34/O33-1 -> 0.03442004 | U34: =P34/P33-1 -> 0.037271908 | V34: =Q34/Q33-1 -> 0.031472522 | W34: =R34/R33-1 -> 0.014763628 | X34: =S34/S33-1 -> 0.00055914724 | Y34: =MAX(O$4:O34) -> 1.323323 | Z34: =MAX(P$4:P34) -> 1.3488575 | AA34: =MAX(Q$4:Q34) -> 1.2977885 | AB34: =MAX(R$4:R34) -> 1.284016 | AC34: =MAX(S$4:S34) -> 1.0186383 | AD34: =O34/Y34-1 -> 0 | AE34: =P34/Z34-1 -> 0 | AF34: =Q34/AA34-1 -> 0 | AG34: =R34/AB34-1 -> 0 | AH34: =S34/AC34-1 -> 0 | AT34: 001480.OF | AU34: 财通金梓才 | AV34: 0.25
A35: 43886 | B35: =[1]!thsiFinD("ths_int_chg_ratio_index",B$1,$A$4,$A35,101) -> 25.195928 | C35: =[1]!thsiFinD("ths_int_chg_ratio_index",C$1,$A$4,$A35,101) -> 63.041891 | D35: =[1]!thsiFinD("ths_int_chg_ratio_index",D$1,$A$4,$A35,101) -> 34.092078 | E35: =[1]!thsiFinD("ths_int_chg_ratio_index",E$1,$A$4,$A35,101) -> 27.723126 | F35: =[1]!thsiFinD("ths_adjustment_nvg_ratio_fund",F$1,$A$4,$A35,101) -> 34.254144 | G35: =[1]!thsiFinD("ths_adjustment_nvg_ratio_fund",G$1,$A$4,$A35,101) -> 30.022701 | H35: =[1]!thsiFinD("ths_adjustment_nvg_ratio_fund",H$1,$A$4,$A35,101) -> 41.923077 | I35: =[1]!thsiFinD("ths_adjustment_nvg_ratio_fund",I$1,$A$4,$A35,101) -> 21.777344 | J35: =50%*K35+50%*L35 -> 0.34753786 | K35: =SUMPRODUCT(B35:E35,B$3:E$3)/100 -> 0.37513256 | L35: =SUMPRODUCT(F35:I35,F$3:I$3)/100 -> 0.31994316 | M35: =[1]!thsiFinD("ths_int_chg_ratio_index",M$1,$A$4,$A35,101)/100 -> 0.29587829 | N35: =[1]!thsiFinD("ths_int_chg_ratio_index",N$1,$A$4,$A35,101)/100 -> 0.018425718 | O35: =J35+1 -> 1.3475379 | P35: =K35+1 -> 1.3751326 | Q35: =L35+1 -> 1.3199432 | R35: =M35+1 -> 1.2958783 | S35: =N35+1 -> 1.0184257 | T35: =O35/O34-1 -> 0.018298552 | U35: =P35/P34-1 -> 0.019479512 | V35: =Q35/Q34-1 -> 0.01707112 | W35: =R35/R34-1 -> 0.0092384564 | X35: =S35/S34-1 -> -0.00020864732 | Y35: =MAX(O$4:O35) -> 1.3475379 | Z35: =MAX(P$4:P35) -> 1.3751326 | AA35: =MAX(Q$4:Q35) -> 1.3199432 | AB35: =MAX(R$4:R35) -> 1.2958783 | AC35: =MAX(S$4:S35) -> 1.0186383 | AD35: =O35/Y35-1 -> 0 | AE35: =P35/Z35-1 -> 0 | AF35: =Q35/AA35-1 -> 0 | AG35: =R35/AB35-1 -> 0 | AH35: =S35/AC35-1 -> -0.00020864732 | AT35: 001323.OF | AU35: 东吴刘元海 | AV35: 0.25
A36: 43887 | B36: =[1]!thsiFinD("ths_int_chg_ratio_index",B$1,$A$4,$A36,101) -> 18.279601 | C36: =[1]!thsiFinD("ths_int_chg_ratio_index",C$1,$A$4,$A36,101) -> 49.068329 | D36: =[1]!thsiFinD("ths_int_chg_ratio_index",D$1,$A$4,$A36,101) -> 26.332474 | E36: =[1]!thsiFinD("ths_int_chg_ratio_index",E$1,$A$4,$A36,101) -> 21.020379 | F36: =[1]!thsiFinD("ths_adjustment_nvg_ratio_fund",F$1,$A$4,$A36,101) -> 27.255985 | G36: =[1]!thsiFinD("ths_adjustment_nvg_ratio_fund",G$1,$A$4,$A36,101) -> 23.269012 | H36: =[1]!thsiFinD("ths_adjustment_nvg_ratio_fund",H$1,$A$4,$A36,101) -> 32.769231 | I36: =[1]!thsiFinD("ths_adjustment_nvg_ratio_fund",I$1,$A$4,$A36,101) -> 17.285156 | J36: =50%*K36+50%*L36 -> 0.26910021 | K36: =SUMPRODUCT(B36:E36,B$3:E$3)/100 -> 0.28675196 | L36: =SUMPRODUCT(F36:I36,F$3:I$3)/100 -> 0.25144846 | M36: =[1]!thsiFinD("ths_int_chg_ratio_index",M$1,$A$4,$A36,101)/100 -> 0.2307821 | N36: =[1]!thsiFinD("ths_int_chg_ratio_index",N$1,$A$4,$A36,101)/100 -> 0.002239944 | O36: =J36+1 -> 1.2691002 | P36: =K36+1 -> 1.286752 | Q36: =L36+1 -> 1.2514485 | R36: =M36+1 -> 1.2307821 | S36: =N36+1 -> 1.0022399 | T36: =O36/O35-1 -> -0.058208124 | U36: =P36/P35-1 -> -0.064270604 | V36: =Q36/Q35-1 -> -0.051892161 | W36: =R36/R35-1 -> -0.050233262 | X36: =S36/S35-1 -> -0.015892936 | Y36: =MAX(O$4:O36) -> 1.3475379 | Z36: =MAX(P$4:P36) -> 1.3751326 | AA36: =MAX(Q$4:Q36) -> 1.3199432 | AB36: =MAX(R$4:R36) -> 1.2958783 | AC36: =MAX(S$4:S36) -> 1.0186383 | AD36: =O36/Y36-1 -> -0.058208124 | AE36: =P36/Z36-1 -> -0.064270604 | AF36: =Q36/AA36-1 -> -0.051892161 | AG36: =R36/AB36-1 -> -0.050233262 | AH36: =S36/AC36-1 -> -0.016098267
A37: 43888 | B37: =[1]!thsiFinD("ths_int_chg_ratio_index",B$1,$A$4,$A37,101) -> 17.760372 | C37: =[1]!thsiFinD("ths_int_chg_ratio_index",C$1,$A$4,$A37,101) -> 44.979852 | D37: =[1]!thsiFinD("ths_int_chg_ratio_index",D$1,$A$4,$A37,101) -> 24.047433 | E37: =[1]!thsiFinD("ths_int_chg_ratio_index",E$1,$A$4,$A37,101) -> 21.612615 | F37: =[1]!thsiFinD("ths_adjustment_nvg_ratio_fund",F$1,$A$4,$A37,101) -> 27.133211 | G37: =[1]!thsiFinD("ths_adjustment_nvg_ratio_fund",G$1,$A$4,$A37,101) -> 23.269012 | H37: =[1]!thsiFinD("ths_adjustment_nvg_ratio_fund",H$1,$A$4,$A37,101) -> 29.615385 | I37: =[1]!thsiFinD("ths_adjustment_nvg_ratio_fund",I$1,$A$4,$A37,101) -> 17.1875 | J37: =50%*K37+50%*L37 -> 0.25700672 | K37: =SUMPRODUCT(B37:E37,B$3:E$3)/100 -> 0.27100068 | L37: =SUMPRODUCT(F37:I37,F$3:I$3)/100 -> 0.24301277 | M37: =[1]!thsiFinD("ths_int_chg_ratio_index",M$1,$A$4,$A37,101)/100 -> 0.21846899 | N37: =[1]!thsiFinD("ths_int_chg_ratio_index",N$1,$A$4,$A37,101)/100 -> 0.004874259 | O37: =J37+1 -> 1.2570067 | P37: =K37+1 -> 1.2710007 | Q37: =L37+1 -> 1.2430128 | R37: =M37+1 -> 1.218469 | S37: =N37+1 -> 1.0048743 | T37: =O37/O36-1 -> -0.0095291809 | U37: =P37/P36-1 -> -0.012241115 | V37: =Q37/Q36-1 -> -0.0067407433 | W37: =R37/R36-1 -> -0.0100043 | X37: =S37/S36-1 -> 0.0026284275 | Y37: =MAX(O$4:O37) -> 1.3475379 | Z37: =MAX(P$4:P37) -> 1.3751326 | AA37: =MAX(Q$4:Q37) -> 1.3199432 | AB37: =MAX(R$4:R37) -> 1.2958783 | AC37: =MAX(S$4:S37) -> 1.0186383 | AD37: =O37/Y37-1 -> -0.067182629 | AE37: =P37/Z37-1 -> -0.075724975 | AF37: =Q37/AA37-1 -> -0.058283112 | AG37: =R37/AB37-1 -> -0.059735013 | AH37: =S37/AC37-1 -> -0.013512153
A38: 43889 | B38: =[1]!thsiFinD("ths_int_chg_ratio_index",B$1,$A$4,$A38,101) -> 10.375426 | C38: =[1]!thsiFinD("ths_int_chg_ratio_index",C$1,$A$4,$A38,101) -> 35.815878 | D38: =[1]!thsiFinD("ths_int_chg_ratio_index",D$1,$A$4,$A38,101) -> 16.801752 | E38: =[1]!thsiFinD("ths_int_chg_ratio_index",E$1,$A$4,$A38,101) -> 14.448354 | F38: =[1]!thsiFinD("ths_adjustment_nvg_ratio_fund",F$1,$A$4,$A38,101) -> 22.467772 | G38: =[1]!thsiFinD("ths_adjustment_nvg_ratio_fund",G$1,$A$4,$A38,101) -> 17.650397 | H38: =[1]!thsiFinD("ths_adjustment_nvg_ratio_fund",H$1,$A$4,$A38,101) -> 22.461538 | I38: =[1]!thsiFinD("ths_adjustment_nvg_ratio_fund",I$1,$A$4,$A38,101) -> 12.890625 | J38: =50%*K38+50%*L38 -> 0.19113968 | K38: =SUMPRODUCT(B38:E38,B$3:E$3)/100 -> 0.19360353 | L38: =SUMPRODUCT(F38:I38,F$3:I$3)/100 -> 0.18867583 | M38: =[1]!thsiFinD("ths_int_chg_ratio_index",M$1,$A$4,$A38,101)/100 -> 0.15295915 | N38: =[1]!thsiFinD("ths_int_chg_ratio_index",N$1,$A$4,$A38,101)/100 -> -0.035131801 | O38: =J38+1 -> 1.1911397 | P38: =K38+1 -> 1.1936035 | Q38: =L38+1 -> 1.1886758 | R38: =M38+1 -> 1.1529592 | S38: =N38+1 -> 0.9648682 | T38: =O38/O37-1 -> -0.052399916 | U38: =P38/P37-1 -> -0.06089466 | V38: =Q38/Q37-1 -> -0.043713902 | W38: =R38/R37-1 -> -0.053764053 | X38: =S38/S37-1 -> -0.039812006 | Y38: =MAX(O$4:O38) -> 1.3475379 | Z38: =MAX(P$4:P38) -> 1.3751326 | AA38: =MAX(Q$4:Q38) -> 1.3199432 | AB38: =MAX(R$4:R38) -> 1.2958783 | AC38: =MAX(S$4:S38) -> 1.0186383 | AD38: =O38/Y38-1 -> -0.11606218 | AE38: =P38/Z38-1 -> -0.13200839 | AF38: =Q38/AA38-1 -> -0.099449232 | AG38: =R38/AB38-1 -> -0.11028747 | AH38: =S38/AC38-1 -> -0.052786213
A39: 43892 | B39: =[1]!thsiFinD("ths_int_chg_ratio_index",B$1,$A$4,$A39,101) -> 16.930372 | C39: =[1]!thsiFinD("ths_int_chg_ratio_index",C$1,$A$4,$A39,101) -> 37.232351 | D39: =[1]!thsiFinD("ths_int_chg_ratio_index",D$1,$A$4,$A39,101) -> 22.839615 | E39: =[1]!thsiFinD("ths_int_chg_ratio_index",E$1,$A$4,$A39,101) -> 18.08448 | F39: =[1]!thsiFinD("ths_adjustment_nvg_ratio_fund",F$1,$A$4,$A39,101) -> 26.273788 | G39: =[1]!thsiFinD("ths_adjustment_nvg_ratio_fund",G$1,$A$4,$A39,101) -> 20.942111 | H39: =[1]!thsiFinD("ths_adjustment_nvg_ratio_fund",H$1,$A$4,$A39,101) -> 27.307692 | I39: =[1]!thsiFinD("ths_adjustment_nvg_ratio_fund",I$1,$A$4,$A39,101) -> 15.527344 | J39: =50%*K39+50%*L39 -> 0.23142219 | K39: =SUMPRODUCT(B39:E39,B$3:E$3)/100 -> 0.23771705 | L39: =SUMPRODUCT(F39:I39,F$3:I$3)/100 -> 0.22512734 | M39: =[1]!thsiFinD("ths_int_chg_ratio_index",M$1,$A$4,$A39,101)/100 -> 0.19498776 | N39: =[1]!thsiFinD("ths_int_chg_ratio_index",N$1,$A$4,$A39,101)/100 -> -0.0022427078 | O39: =J39+1 -> 1.2314222 | P39: =K39+1 -> 1.237717 | Q39: =L39+1 -> 1.2251273 | R39: =M39+1 -> 1.1949878 | S39: =N39+1 -> 0.99775729 | T39: =O39/O38-1 -> 0.033818463 | U39: =P39/P38-1 -> 0.036958268 | V39: =Q39/Q38-1 -> 0.030665641 | W39: =R39/R38-1 -> 0.036452819 | X39: =S39/S38-1 -> 0.034086618 | Y39: =MAX(O$4:O39) -> 1.3475379 | Z39: =MAX(P$4:P39) -> 1.3751326 | AA39: =MAX(Q$4:Q39) -> 1.3199432 | AB39: =MAX(R$4:R39) -> 1.2958783 | AC39: =MAX(S$4:S39) -> 1.0186383 | AD39: =O39/Y39-1 -> -0.086168763 | AE39: =P39/Z39-1 -> -0.099928921 | AF39: =Q39/AA39-1 -> -0.071833265 | AG39: =R39/AB39-1 -> -0.077854941 | AH39: =S39/AC39-1 -> -0.020498899
A40: 43893 | B40: =[1]!thsiFinD("ths_int_chg_ratio_index",B$1,$A$4,$A40,101) -> 16.57116 | C40: =[1]!thsiFinD("ths_int_chg_ratio_index",C$1,$A$4,$A40,101) -> 38.096746 | D40: =[1]!thsiFinD("ths_int_chg_ratio_index",D$1,$A$4,$A40,101) -> 26.017918 | E40: =[1]!thsiFinD("ths_int_chg_ratio_index",E$1,$A$4,$A40,101) -> 20.568715 | F40: =[1]!thsiFinD("ths_adjustment_nvg_ratio_fund",F$1,$A$4,$A40,101) -> 26.580724 | G40: =[1]!thsiFinD("ths_adjustment_nvg_ratio_fund",G$1,$A$4,$A40,101) -> 22.077185 | H40: =[1]!thsiFinD("ths_adjustment_nvg_ratio_fund",H$1,$A$4,$A40,101) -> 27.307692 | I40: =[1]!thsiFinD("ths_adjustment_nvg_ratio_fund",I$1,$A$4,$A40,101) -> 16.308594 | J40: =50%*K40+50%*L40 -> 0.24191092 | K40: =SUMPRODUCT(B40:E40,B$3:E$3)/100 -> 0.25313635 | L40: =SUMPRODUCT(F40:I40,F$3:I$3)/100 -> 0.23068549 | M40: =[1]!thsiFinD("ths_int_chg_ratio_index",M$1,$A$4,$A40,101)/100 -> 0.21443223 | N40: =[1]!thsiFinD("ths_int_chg_ratio_index",N$1,$A$4,$A40,101)/100 -> 0.0041193734 | O40: =J40+1 -> 1.2419109 | P40: =K40+1 -> 1.2531363 | Q40: =L40+1 -> 1.2306855 | R40: =M40+1 -> 1.2144322 | S40: =N40+1 -> 1.0041194 | T40: =O40/O39-1 -> 0.0085175717 | U40: =P40/P39-1 -> 0.012457857 | V40: =Q40/Q39-1 -> 0.0045367948 | W40: =R40/R39-1 -> 0.016271689 | X40: =S40/S39-1 -> 0.0063763815 | Y40: =MAX(O$4:O40) -> 1.3475379 | Z40: =MAX(P$4:P40) -> 1.3751326 | AA40: =MAX(Q$4:Q40) -> 1.3199432 | AB40: =MAX(R$4:R40) -> 1.2958783 | AC40: =MAX(S$4:S40) -> 1.0186383 | AD40: =O40/Y40-1 -> -0.07838514 | AE40: =P40/Z40-1 -> -0.088715964 | AF40: =Q40/AA40-1 -> -0.067622363 | AG40: =R40/AB40-1 -> -0.062850083 | AH40: =S40/AC40-1 -> -0.014253226
A41: 43894 | B41: =[1]!thsiFinD("ths_int_chg_ratio_index",B$1,$A$4,$A41,101) -> 15.246268 | C41: =[1]!thsiFinD("ths_int_chg_ratio_index",C$1,$A$4,$A41,101) -> 32.4588 | D41: =[1]!thsiFinD("ths_int_chg_ratio_index",D$1,$A$4,$A41,101) -> 23.143511 | E41: =[1]!thsiFinD("ths_int_chg_ratio_index",E$1,$A$4,$A41,101) -> 20.177837 | F41: =[1]!thsiFinD("ths_adjustment_nvg_ratio_fund",F$1,$A$4,$A41,101) -> 25.598527 | G41: =[1]!thsiFinD("ths_adjustment_nvg_ratio_fund",G$1,$A$4,$A41,101) -> 19.920545 | H41: =[1]!thsiFinD("ths_adjustment_nvg_ratio_fund",H$1,$A$4,$A41,101) -> 23.307692 | I41: =[1]!thsiFinD("ths_adjustment_nvg_ratio_fund",I$1,$A$4,$A41,101) -> 14.648438 | J41: =50%*K41+50%*L41 -> 0.21812702 | K41: =SUMPRODUCT(B41:E41,B$3:E$3)/100 -> 0.22756604 | L41: =SUMPRODUCT(F41:I41,F$3:I$3)/100 -> 0.208688 | M41: =[1]!thsiFinD("ths_int_chg_ratio_index",M$1,$A$4,$A41,101)/100 -> 0.20410528 | N41: =[1]!thsiFinD("ths_int_chg_ratio_index",N$1,$A$4,$A41,101)/100 -> 0.0087515927 | O41: =J41+1 -> 1.218127 | P41: =K41+1 -> 1.227566 | Q41: =L41+1 -> 1.208688 | R41: =M41+1 -> 1.2041053 | S41: =N41+1 -> 1.0087516 | T41: =O41/O40-1 -> -0.019151048 | U41: =P41/P40-1 -> -0.020405047 | V41: =Q41/Q40-1 -> -0.017874173 | W41: =R41/R40-1 -> -0.0085035213 | X41: =S41/S40-1 -> 0.0046132157 | Y41: =MAX(O$4:O41) -> 1.3475379 | Z41: =MAX(P$4:P41) -> 1.3751326 | AA41: =MAX(Q$4:Q41) -> 1.3199432 | AB41: =MAX(R$4:R41) -> 1.2958783 | AC41: =MAX(S$4:S41) -> 1.0186383 | AD41: =O41/Y41-1 -> -0.09603503 | AE41: =P41/Z41-1 -> -0.10731076 | AF41: =Q41/AA41-1 -> -0.084287842 | AG41: =R41/AB41-1 -> -0.070819157 | AH41: =S41/AC41-1 -> -0.0097057634
A42: 43895 | B42: =[1]!thsiFinD("ths_int_chg_ratio_index",B$1,$A$4,$A42,101) -> 16.253632 | C42: =[1]!thsiFinD("ths_int_chg_ratio_index",C$1,$A$4,$A42,101) -> 33.842165 | D42: =[1]!thsiFinD("ths_int_chg_ratio_index",D$1,$A$4,$A42,101) -> 24.032419 | E42: =[1]!thsiFinD("ths_int_chg_ratio_index",E$1,$A$4,$A42,101) -> 21.796487 | F42: =[1]!thsiFinD("ths_adjustment_nvg_ratio_fund",F$1,$A$4,$A42,101) -> 26.089626 | G42: =[1]!thsiFinD("ths_adjustment_nvg_ratio_fund",G$1,$A$4,$A42,101) -> 19.296254 | H42: =[1]!thsiFinD("ths_adjustment_nvg_ratio_fund",H$1,$A$4,$A42,101) -> 23.769231 | I42: =[1]!thsiFinD("ths_adjustment_nvg_ratio_fund",I$1,$A$4,$A42,101) -> 16.40625 | J42: =50%*K42+50%*L42 -> 0.22685758 | K42: =SUMPRODUCT(B42:E42,B$3:E$3)/100 -> 0.23981176 | L42: =SUMPRODUCT(F42:I42,F$3:I$3)/100 -> 0.2139034 | M42: =[1]!thsiFinD("ths_int_chg_ratio_index",M$1,$A$4,$A42,101)/100 -> 0.22062506 | N42: =[1]!thsiFinD("ths_int_chg_ratio_index",N$1,$A$4,$A42,101)/100 -> 0.029322848 | O42: =J42+1 -> 1.2268576 | P42: =K42+1 -> 1.2398118 | Q42: =L42+1 -> 1.2139034 | R42: =M42+1 -> 1.2206251 | S42: =N42+1 -> 1.0293228 | T42: =O42/O41-1 -> 0.0071671984 | U42: =P42/P41-1 -> 0.0099756084 | V42: =Q42/Q41-1 -> 0.004314925 | W42: =R42/R41-1 -> 0.013719545 | X42: =S42/S41-1 -> 0.020392786 | Y42: =MAX(O$4:O42) -> 1.3475379 | Z42: =MAX(P$4:P42) -> 1.3751326 | AA42: =MAX(Q$4:Q42) -> 1.3199432 | AB42: =MAX(R$4:R42) -> 1.2958783 | AC42: =MAX(S$4:S42) -> 1.0293228 | AD42: =O42/Y42-1 -> -0.089556134 | AE42: =P42/Z42-1 -> -0.09840564 | AF42: =Q42/AA42-1 -> -0.080336613 | AG42: =R42/AB42-1 -> -0.058071219 | AH42: =S42/AC42-1 -> 0
A43: 43896 | B43: =[1]!thsiFinD("ths_int_chg_ratio_index",B$1,$A$4,$A43,101) -> 15.186434 | C43: =[1]!thsiFinD("ths_int_chg_ratio_index",C$1,$A$4,$A43,101) -> 31.369736 | D43: =[1]!thsiFinD("ths_int_chg_ratio_index",D$1,$A$4,$A43,101) -> 21.93233 | E43: =[1]!thsiFinD("ths_int_chg_ratio_index",E$1,$A$4,$A43,101) -> 20.962435 | F43: =[1]!thsiFinD("ths_adjustment_nvg_ratio_fund",F$1,$A$4,$A43,101) -> 24.616329 | G43: =[1]!thsiFinD("ths_adjustment_nvg_ratio_fund",G$1,$A$4,$A43,101) -> 18.331442 | H43: =[1]!thsiFinD("ths_adjustment_nvg_ratio_fund",H$1,$A$4,$A43,101) -> 23.076923 | I43: =[1]!thsiFinD("ths_adjustment_nvg_ratio_fund",I$1,$A$4,$A43,101) -> 15.332031 | J43: =50%*K43+50%*L43 -> 0.21350957 | K43: =SUMPRODUCT(B43:E43,B$3:E$3)/100 -> 0.22362734 | L43: =SUMPRODUCT(F43:I43,F$3:I$3)/100 -> 0.20339181 | M43: =[1]!thsiFinD("ths_int_chg_ratio_index",M$1,$A$4,$A43,101)/100 -> 0.20926563 | N43: =[1]!thsiFinD("ths_int_chg_ratio_index",N$1,$A$4,$A43,101)/100 -> 0.015158056 | O43: =J43+1 -> 1.2135096 | P43: =K43+1 -> 1.2236273 | Q43: =L43+1 -> 1.2033918 | R43: =M43+1 -> 1.2092656 | S43: =N43+1 -> 1.0151581 | T43: =O43/O42-1 -> -0.010879834 | U43: =P43/P42-1 -> -0.013053936 | V43: =Q43/Q42-1 -> -0.0086593292 | W43: =R43/R42-1 -> -0.0093062405 | X43: =S43/S42-1 -> -0.013761273 | Y43: =MAX(O$4:O43) -> 1.3475379 | Z43: =MAX(P$4:P43) -> 1.3751326 | AA43: =MAX(Q$4:Q43) -> 1.3199432 | AB43: =MAX(R$4:R43) -> 1.2958783 | AC43: =MAX(S$4:S43) -> 1.0293228 | AD43: =O43/Y43-1 -> -0.099461612 | AE43: =P43/Z43-1 -> -0.110175 | AF43: =Q43/AA43-1 -> -0.088300281 | AG43: =R43/AB43-1 -> -0.066837034 | AH43: =S43/AC43-1 -> -0.013761273
A44: 43899 | B44: =[1]!thsiFinD("ths_int_chg_ratio_index",B$1,$A$4,$A44,101) -> 12.005641 | C44: =[1]!thsiFinD("ths_int_chg_ratio_index",C$1,$A$4,$A44,101) -> 21.890751 | D44: =[1]!thsiFinD("ths_int_chg_ratio_index",D$1,$A$4,$A44,101) -> 14.91932 | E44: =[1]!thsiFinD("ths_int_chg_ratio_index",E$1,$A$4,$A44,101) -> 15.294389 | F44: =[1]!thsiFinD("ths_adjustment_nvg_ratio_fund",F$1,$A$4,$A44,101) -> 19.152855 | G44: =[1]!thsiFinD("ths_adjustment_nvg_ratio_fund",G$1,$A$4,$A44,101) -> 12.088536 | H44: =[1]!thsiFinD("ths_adjustment_nvg_ratio_fund",H$1,$A$4,$A44,101) -> 16.846154 | I44: =[1]!thsiFinD("ths_adjustment_nvg_ratio_fund",I$1,$A$4,$A44,101) -> 9.4726562 | J44: =50%*K44+50%*L44 -> 0.15208788 | K44: =SUMPRODUCT(B44:E44,B$3:E$3)/100 -> 0.16027525 | L44: =SUMPRODUCT(F44:I44,F$3:I$3)/100 -> 0.1439005 | M44: =[1]!thsiFinD("ths_int_chg_ratio_index",M$1,$A$4,$A44,101)/100 -> 0.14740814 | N44: =[1]!thsiFinD("ths_int_chg_ratio_index",N$1,$A$4,$A44,101)/100 -> -0.021350739 | O44: =J44+1 -> 1.1520879 | P44: =K44+1 -> 1.1602753 | Q44: =L44+1 -> 1.1439005 | R44: =M44+1 -> 1.1474081 | S44: =N44+1 -> 0.97864926 | T44: =O44/O43-1 -> -0.050614925 | U44: =P44/P43-1 -> -0.051774 | V44: =Q44/Q43-1 -> -0.04943636 | W44: =R44/R43-1 -> -0.051152935 | X44: =S44/S43-1 -> -0.035963656 | Y44: =MAX(O$4:O44) -> 1.3475379 | Z44: =MAX(P$4:P44) -> 1.3751326 | AA44: =MAX(Q$4:Q44) -> 1.3199432 | AB44: =MAX(R$4:R44) -> 1.2958783 | AC44: =MAX(S$4:S44) -> 1.0293228 | AD44: =O44/Y44-1 -> -0.14504229 | AE44: =P44/Z44-1 -> -0.15624479 | AF44: =Q44/AA44-1 -> -0.1333714 | AG44: =R44/AB44-1 -> -0.11457106 | AH44: =S44/AC44-1 -> -0.049230023
A45: 43900 | B45: =[1]!thsiFinD("ths_int_chg_ratio_index",B$1,$A$4,$A45,101) -> 19.762405 | C45: =[1]!thsiFinD("ths_int_chg_ratio_index",C$1,$A$4,$A45,101) -> 30.711769 | D45: =[1]!thsiFinD("ths_int_chg_ratio_index",D$1,$A$4,$A45,101) -> 19.280228 | E45: =[1]!thsiFinD("ths_int_chg_ratio_index",E$1,$A$4,$A45,101) -> 18.99358 | F45: =[1]!thsiFinD("ths_adjustment_nvg_ratio_fund",F$1,$A$4,$A45,101) -> 21.669736 | G45: =[1]!thsiFinD("ths_adjustment_nvg_ratio_fund",G$1,$A$4,$A45,101) -> 16.742338 | H45: =[1]!thsiFinD("ths_adjustment_nvg_ratio_fund",H$1,$A$4,$A45,101) -> 23 | I45: =[1]!thsiFinD("ths_adjustment_nvg_ratio_fund",I$1,$A$4,$A45,101) -> 13.183594 | J45: =50%*K45+50%*L45 -> 0.20417956 | K45: =SUMPRODUCT(B45:E45,B$3:E$3)/100 -> 0.22186996 | L45: =SUMPRODUCT(F45:I45,F$3:I$3)/100 -> 0.18648917 | M45: =[1]!thsiFinD("ths_int_chg_ratio_index",M$1,$A$4,$A45,101)/100 -> 0.18800687 | N45: =[1]!thsiFinD("ths_int_chg_ratio_index",N$1,$A$4,$A45,101)/100 -> 0.00098418884 | O45: =J45+1 -> 1.2041796 | P45: =K45+1 -> 1.22187 | Q45: =L45+1 -> 1.1864892 | R45: =M45+1 -> 1.1880069 | S45: =N45+1 -> 1.0009842 | T45: =O45/O44-1 -> 0.045215028 | U45: =P45/P44-1 -> 0.053086284 | V45: =Q45/Q44-1 -> 0.037231096 | W45: =R45/R44-1 -> 0.035382983 | X45: =S45/S44-1 -> 0.022822199 | Y45: =MAX(O$4:O45) -> 1.3475379 | Z45: =MAX(P$4:P45) -> 1.3751326 | AA45: =MAX(Q$4:Q45) -> 1.3199432 | AB45: =MAX(R$4:R45) -> 1.2958783 | AC45: =MAX(S$4:S45) -> 1.0293228 | AD45: =O45/Y45-1 -> -0.10638536 | AE45: =P45/Z45-1 -> -0.11145297 | AF45: =Q45/AA45-1 -> -0.10110586 | AG45: =R45/AB45-1 -> -0.083241942 | AH45: =S45/AC45-1 -> -0.027531362
A46: 43901 | B46: =[1]!thsiFinD("ths_int_chg_ratio_index",B$1,$A$4,$A46,101) -> 17.900158 | C46: =[1]!thsiFinD("ths_int_chg_ratio_index",C$1,$A$4,$A46,101) -> 24.485729 | D46: =[1]!thsiFinD("ths_int_chg_ratio_index",D$1,$A$4,$A46,101) -> 16.179554 | E46: =[1]!thsiFinD("ths_int_chg_ratio_index",E$1,$A$4,$A46,101) -> 16.302438 | F46: =[1]!thsiFinD("ths_adjustment_nvg_ratio_fund",F$1,$A$4,$A46,101) -> 19.521179 | G46: =[1]!thsiFinD("ths_adjustment_nvg_ratio_fund",G$1,$A$4,$A46,101) -> 13.8479 | H46: =[1]!thsiFinD("ths_adjustment_nvg_ratio_fund",H$1,$A$4,$A46,101) -> 19.615385 | I46: =[1]!thsiFinD("ths_adjustment_nvg_ratio_fund",I$1,$A$4,$A46,101) -> 11.132812 | J46: =50%*K46+50%*L46 -> 0.17373144 | K46: =SUMPRODUCT(B46:E46,B$3:E$3)/100 -> 0.1871697 | L46: =SUMPRODUCT(F46:I46,F$3:I$3)/100 -> 0.16029319 | M46: =[1]!thsiFinD("ths_int_chg_ratio_index",M$1,$A$4,$A46,101)/100 -> 0.1583645 | N46: =[1]!thsiFinD("ths_int_chg_ratio_index",N$1,$A$4,$A46,101)/100 -> -0.012778609 | O46: =J46+1 -> 1.1737314 | P46: =K46+1 -> 1.1871697 | Q46: =L46+1 -> 1.1602932 | R46: =M46+1 -> 1.1583645 | S46: =N46+1 -> 0.98722139 | T46: =O46/O45-1 -> -0.025285364 | U46: =P46/P45-1 -> -0.028399305 | V46: =Q46/Q45-1 -> -0.022078567 | W46: =R46/R45-1 -> -0.024951347 | X46: =S46/S45-1 -> -0.013749266 | Y46: =MAX(O$4:O46) -> 1.3475379 | Z46: =MAX(P$4:P46) -> 1.3751326 | AA46: =MAX(Q$4:Q46) -> 1.3199432 | AB46: =MAX(R$4:R46) -> 1.2958783 | AC46: =MAX(S$4:S46) -> 1.0293228 | AD46: =O46/Y46-1 -> -0.12898073 | AE46: =P46/Z46-1 -> -0.13668708 | AF46: =Q46/AA46-1 -> -0.12095216 | AG46: =R46/AB46-1 -> -0.10611629 | AH46: =S46/AC46-1 -> -0.040902092
A47: 43902 | B47: =[1]!thsiFinD("ths_int_chg_ratio_index",B$1,$A$4,$A47,101) -> 18.55371 | C47: =[1]!thsiFinD("ths_int_chg_ratio_index",C$1,$A$4,$A47,101) -> 24.813437 | D47: =[1]!thsiFinD("ths_int_chg_ratio_index",D$1,$A$4,$A47,101) -> 14.449163 | E47: =[1]!thsiFinD("ths_int_chg_ratio_index",E$1,$A$4,$A47,101) -> 13.378939 | F47: =[1]!thsiFinD("ths_adjustment_nvg_ratio_fund",F$1,$A$4,$A47,101) -> 17.740945 | G47: =[1]!thsiFinD("ths_adjustment_nvg_ratio_fund",G$1,$A$4,$A47,101) -> 11.634506 | H47: =[1]!thsiFinD("ths_adjustment_nvg_ratio_fund",H$1,$A$4,$A47,101) -> 17.153846 | I47: =[1]!thsiFinD("ths_adjustment_nvg_ratio_fund",I$1,$A$4,$A47,101) -> 9.4726562 | J47: =50%*K47+50%*L47 -> 0.1589965 | K47: =SUMPRODUCT(B47:E47,B$3:E$3)/100 -> 0.17798812 | L47: =SUMPRODUCT(F47:I47,F$3:I$3)/100 -> 0.14000489 | M47: =[1]!thsiFinD("ths_int_chg_ratio_index",M$1,$A$4,$A47,101)/100 -> 0.12797462 | N47: =[1]!thsiFinD("ths_int_chg_ratio_index",N$1,$A$4,$A47,101)/100 -> -0.031245646 | O47: =J47+1 -> 1.1589965 | P47: =K47+1 -> 1.1779881 | Q47: =L47+1 -> 1.1400049 | R47: =M47+1 -> 1.1279746 | S47: =N47+1 -> 0.96875435 | T47: =O47/O46-1 -> -0.012553928 | U47: =P47/P46-1 -> -0.0077340051 | V47: =Q47/Q46-1 -> -0.017485498 | W47: =R47/R46-1 -> -0.026235154 | X47: =S47/S46-1 -> -0.018706075 | Y47: =MAX(O$4:O47) -> 1.3475379 | Z47: =MAX(P$4:P47) -> 1.3751326 | AA47: =MAX(Q$4:Q47) -> 1.3199432 | AB47: =MAX(R$4:R47) -> 1.2958783 | AC47: =MAX(S$4:S47) -> 1.0293228 | AD47: =O47/Y47-1 -> -0.13991544 | AE47: =P47/Z47-1 -> -0.14336395 | AF47: =Q47/AA47-1 -> -0.13632275 | AG47: =R47/AB47-1 -> -0.12956747 | AH47: =S47/AC47-1 -> -0.058843049
... A1617: 46265 | B1617: =[1]!thsiFinD("ths_int_chg_ratio_index",B$1,$A$4,$A1617,101) -> 235.83853 | C1617: =[1]!thsiFinD("ths_int_chg_ratio_index",C$1,$A$4,$A1617,101) -> 328.16226 | D1617: =[1]!thsiFinD("ths_int_chg_ratio_index",D$1,$A$4,$A1617,101) -> 65.180803 | E1617: =[1]!thsiFinD("ths_int_chg_ratio_index",E$1,$A$4,$A1617,101) -> 133.42655 | F1617: =[1]!thsiFinD("ths_adjustment_nvg_ratio_fund",F$1,$A$4,$A1617,101) -> 315.89932 | G1617: =[1]!thsiFinD("ths_adjustment_nvg_ratio_fund",G$1,$A$4,$A1617,101) -> 373.87759 | H1617: =[1]!thsiFinD("ths_adjustment_nvg_ratio_fund",H$1,$A$4,$A1617,101) -> 474.30769 | I1617: =[1]!thsiFinD("ths_adjustment_nvg_ratio_fund",I$1,$A$4,$A1617,101) -> 549.63867 | J1617: =50%*K1617+50%*L1617 -> 3.0954143 | K1617: =SUMPRODUCT(B1617:E1617,B$3:E$3)/100 -> 1.9065204 | L1617: =SUMPRODUCT(F1617:I1617,F$3:I$3)/100 -> 4.2843082 | M1617: =[1]!thsiFinD("ths_int_chg_ratio_index",M$1,$A$4,$A1617,101)/100 -> 0.57138962 | N1617: =[1]!thsiFinD("ths_int_chg_ratio_index",N$1,$A$4,$A1617,101)/100 -> 0.19645901 | O1617: =J1617+1 -> 4.0954143 | P1617: =K1617+1 -> 2.9065204 | Q1617: =L1617+1 -> 5.2843082 | R1617: =M1617+1 -> 1.5713896 | S1617: =N1617+1 -> 1.196459 | T1617: =O1617/O1616-1 -> 0.011286444 | U1617: =P1617/P1616-1 -> 0.005596338 | V1617: =Q1617/Q1616-1 -> 0.014443701 | W1617: =R1617/R1616-1 -> 0.0038639691 | X1617: =S1617/S1616-1 -> 0.0044721127 | Y1617: =MAX(O$4:O1617) -> 5.4188062 | Z1617: =MAX(P$4:P1617) -> 3.865125 | AA1617: =MAX(Q$4:Q1617) -> 7.0927502 | AB1617: =MAX(R$4:R1617) -> 1.976585 | AC1617: =MAX(S$4:S1617) -> 1.3589987 | AD1617: =O1617/Y1617-1 -> -0.24422204 | AE1617: =P1617/Z1617-1 -> -0.24801387 | AF1617: =Q1617/AA1617-1 -> -0.25497049 | AG1617: =R1617/AB1617-1 -> -0.20499769 | AH1617: =S1617/AC1617-1 -> -0.11960252
A1618: 46266 | B1618: =[1]!thsiFinD("ths_int_chg_ratio_index",B$1,$A$4,$A1618,101) -> 230.70712 | C1618: =[1]!thsiFinD("ths_int_chg_ratio_index",C$1,$A$4,$A1618,101) -> 312.10232 | D1618: =[1]!thsiFinD("ths_int_chg_ratio_index",D$1,$A$4,$A1618,101) -> 61.566843 | E1618: =[1]!thsiFinD("ths_int_chg_ratio_index",E$1,$A$4,$A1618,101) -> 130.65982 | F1618: =[1]!thsiFinD("ths_adjustment_nvg_ratio_fund",F$1,$A$4,$A1618,101) -> 306.93677 | G1618: =[1]!thsiFinD("ths_adjustment_nvg_ratio_fund",G$1,$A$4,$A1618,101) -> 361.24394 | H1618: =[1]!thsiFinD("ths_adjustment_nvg_ratio_fund",H$1,$A$4,$A1618,101) -> 450.84615 | I1618: =[1]!thsiFinD("ths_adjustment_nvg_ratio_fund",I$1,$A$4,$A1618,101) -> 536.15234 | J1618: =50%*K1618+50%*L1618 -> 2.9877691 | K1618: =SUMPRODUCT(B1618:E1618,B$3:E$3)/100 -> 1.8375903 | L1618: =SUMPRODUCT(F1618:I1618,F$3:I$3)/100 -> 4.137948 | M1618: =[1]!thsiFinD("ths_int_chg_ratio_index",M$1,$A$4,$A1618,101)/100 -> 0.54080471 | N1618: =[1]!thsiFinD("ths_int_chg_ratio_index",N$1,$A$4,$A1618,101)/100 -> 0.19002956 | O1618: =J1618+1 -> 3.9877691 | P1618: =K1618+1 -> 2.8375903 | Q1618: =L1618+1 -> 5.137948 | R1618: =M1618+1 -> 1.5408047 | S1618: =N1618+1 -> 1.1900296 | T1618: =O1618/O1617-1 -> -0.026284311 | U1618: =P1618/P1617-1 -> -0.023715685 | V1618: =Q1618/Q1617-1 -> -0.027697128 | W1618: =R1618/R1617-1 -> -0.019463606 | X1618: =S1618/S1617-1 -> -0.0053737309 | Y1618: =MAX(O$4:O1618) -> 5.4188062 | Z1618: =MAX(P$4:P1618) -> 3.865125 | AA1618: =MAX(Q$4:Q1618) -> 7.0927502 | AB1618: =MAX(R$4:R1618) -> 1.976585 | AC1618: =MAX(S$4:S1618) -> 1.3589987 | AD1618: =O1618/Y1618-1 -> -0.26408714 | AE1618: =P1618/Z1618-1 -> -0.26584773 | AF1618: =Q1618/AA1618-1 -> -0.27560567 | AG1618: =R1618/AB1618-1 -> -0.2204713
A1619: 46267 | B1619: =[1]!thsiFinD("ths_int_chg_ratio_index",B$1,$A$4,$A1619,101) -> 223.67154 | C1619: =[1]!thsiFinD("ths_int_chg_ratio_index",C$1,$A$4,$A1619,101) -> 305.37292 | D1619: =[1]!thsiFinD("ths_int_chg_ratio_index",D$1,$A$4,$A1619,101) -> 58.630929 | E1619: =[1]!thsiFinD("ths_int_chg_ratio_index",E$1,$A$4,$A1619,101) -> 124.67839 | F1619: =[1]!thsiFinD("ths_adjustment_nvg_ratio_fund",F$1,$A$4,$A1619,101) -> 302.02578 | G1619: =[1]!thsiFinD("ths_adjustment_nvg_ratio_fund",G$1,$A$4,$A1619,101) -> 353.65217 | H1619: =[1]!thsiFinD("ths_adjustment_nvg_ratio_fund",H$1,$A$4,$A1619,101) -> 441.38462 | I1619: =[1]!thsiFinD("ths_adjustment_nvg_ratio_fund",I$1,$A$4,$A1619,101) -> 523.07617 | J1619: =50%*K1619+50%*L1619 -> 2.9156156 | K1619: =SUMPRODUCT(B1619:E1619,B$3:E$3)/100 -> 1.7808844 | L1619: =SUMPRODUCT(F1619:I1619,F$3:I$3)/100 -> 4.0503468 | M1619: =[1]!thsiFinD("ths_int_chg_ratio_index",M$1,$A$4,$A1619,101)/100 -> 0.51683839 | N1619: =[1]!thsiFinD("ths_int_chg_ratio_index",N$1,$A$4,$A1619,101)/100 -> 0.17277468 | O1619: =J1619+1 -> 3.9156156 | P1619: =K1619+1 -> 2.7808844 | Q1619: =L1619+1 -> 5.0503468 | R1619: =M1619+1 -> 1.5168384 | S1619: =N1619+1 -> 1.1727747 | T1619: =O1619/O1618-1 -> -0.0180937 | U1619: =P1619/P1618-1 -> -0.019983789 | V1619: =Q1619/Q1618-1 -> -0.01704984 | W1619: =R1619/R1618-1 -> -0.015554419 | X1619: =S1619/S1618-1 -> -0.01449954 | Y1619: =MAX(O$4:O1619) -> 5.4188062 | Z1619: =MAX(P$4:P1619) -> 3.865125 | AA1619: =MAX(Q$4:Q1619) -> 7.0927502 | AB1619: =MAX(R$4:R1619) -> 1.976585 | AC1619: =MAX(S$4:S1619) -> 1.3589987 | AD1619: =O1619/Y1619-1 -> -0.27740253 | AE1619: =P1619/Z1619-1 -> -0.28051888 | AF1619: =Q1619/AA1619-1 -> -0.28795648 | AG1619: =R1619/AB1619-1 -> -0.23259642
A1620: 46268 | B1620: =[1]!thsiFinD("ths_int_chg_ratio_index",B$1,$A$4,$A1620,101) -> 222.80876 | C1620: =[1]!thsiFinD("ths_int_chg_ratio_index",C$1,$A$4,$A1620,101) -> 300.85914 | D1620: =[1]!thsiFinD("ths_int_chg_ratio_index",D$1,$A$4,$A1620,101) -> 58.000218 | E1620: =[1]!thsiFinD("ths_int_chg_ratio_index",E$1,$A$4,$A1620,101) -> 124.43494 | F1620: =[1]!thsiFinD("ths_adjustment_nvg_ratio_fund",F$1,$A$4,$A1620,101) -> 301.41191 | G1620: =[1]!thsiFinD("ths_adjustment_nvg_ratio_fund",G$1,$A$4,$A1620,101) -> 352.72493 | H1620: =[1]!thsiFinD("ths_adjustment_nvg_ratio_fund",H$1,$A$4,$A1620,101) -> 442.23077 | I1620: =[1]!thsiFinD("ths_adjustment_nvg_ratio_fund",I$1,$A$4,$A1620,101) -> 519.72656 | J1620: =50%*K1620+50%*L1620 -> 2.9027465 | K1620: =SUMPRODUCT(B1620:E1620,B$3:E$3)/100 -> 1.7652577 | L1620: =SUMPRODUCT(F1620:I1620,F$3:I$3)/100 -> 4.0402354 | M1620: =[1]!thsiFinD("ths_int_chg_ratio_index",M$1,$A$4,$A1620,101)/100 -> 0.51101687 | N1620: =[1]!thsiFinD("ths_int_chg_ratio_index",N$1,$A$4,$A1620,101)/100 -> 0.17472215 | O1620: =J1620+1 -> 3.9027465 | P1620: =K1620+1 -> 2.7652577 | Q1620: =L1620+1 -> 5.0402354 | R1620: =M1620+1 -> 1.5110169 | S1620: =N1620+1 -> 1.1747221 | T1620: =O1620/O1619-1 -> -0.0032866109 | U1620: =P1620/P1619-1 -> -0.0056193589 | V1620: =Q1620/Q1619-1 -> -0.0020021244 | W1620: =R1620/R1619-1 -> -0.003837931 | X1620: =S1620/S1619-1 -> 0.0016605619 | Y1620: =MAX(O$4:O1620) -> 5.4188062 | Z1620: =MAX(P$4:P1620) -> 3.865125 | AA1620: =MAX(Q$4:Q1620) -> 7.0927502 | AB1620: =MAX(R$4:R1620) -> 1.976585 | AC1620: =MAX(S$4:S1620) -> 1.3589987 | AD1620: =O1620/Y1620-1 -> -0.27977742 | AE1620: =P1620/Z1620-1 -> -0.2845619 | AF1620: =Q1620/AA1620-1 -> -0.28938208 | AG1620: =R1620/AB1620-1 -> -0.23554166
A1621: 46269 | B1621: =[1]!thsiFinD("ths_int_chg_ratio_index",B$1,$A$4,$A1621,101) -> 218.89998 | C1621: =[1]!thsiFinD("ths_int_chg_ratio_index",C$1,$A$4,$A1621,101) -> 287.05322 | D1621: =[1]!thsiFinD("ths_int_chg_ratio_index",D$1,$A$4,$A1621,101) -> 54.685143 | E1621: =[1]!thsiFinD("ths_int_chg_ratio_index",E$1,$A$4,$A1621,101) -> 123.14969 | F1621: =[1]!thsiFinD("ths_adjustment_nvg_ratio_fund",F$1,$A$4,$A1621,101) -> 295.02762 | G1621: =[1]!thsiFinD("ths_adjustment_nvg_ratio_fund",G$1,$A$4,$A1621,101) -> 341.7719 | H1621: =[1]!thsiFinD("ths_adjustment_nvg_ratio_fund",H$1,$A$4,$A1621,101) -> 427.38462 | I1621: =[1]!thsiFinD("ths_adjustment_nvg_ratio_fund",I$1,$A$4,$A1621,101) -> 510.66406 | J1621: =50%*K1621+50%*L1621 -> 2.8232953 | K1621: =SUMPRODUCT(B1621:E1621,B$3:E$3)/100 -> 1.7094701 | L1621: =SUMPRODUCT(F1621:I1621,F$3:I$3)/100 -> 3.9371205 | M1621: =[1]!thsiFinD("ths_int_chg_ratio_index",M$1,$A$4,$A1621,101)/100 -> 0.48741618 | N1621: =[1]!thsiFinD("ths_int_chg_ratio_index",N$1,$A$4,$A1621,101)/100 -> 0.16962757 | O1621: =J1621+1 -> 3.8232953 | P1621: =K1621+1 -> 2.7094701 | Q1621: =L1621+1 -> 4.9371205 | R1621: =M1621+1 -> 1.4874162 | S1621: =N1621+1 -> 1.1696276 | T1621: =O1621/O1620-1 -> -0.020357774 | U1621: =P1621/P1620-1 -> -0.020174453 | V1621: =Q1621/Q1620-1 -> -0.02045835 | W1621: =R1621/R1620-1 -> -0.015619076 | X1621: =S1621/S1620-1 -> -0.0043368382 | Y1621: =MAX(O$4:O1621) -> 5.4188062 | Z1621: =MAX(P$4:P1621) -> 3.865125 | AA1621: =MAX(Q$4:Q1621) -> 7.0927502 | AB1621: =MAX(R$4:R1621) -> 1.976585 | AC1621: =MAX(S$4:S1621) -> 1.3589987 | AD1621: =O1621/Y1621-1 -> -0.29443955 | AE1621: =P1621/Z1621-1 -> -0.29899547 | AF1621: =Q1621/AA1621-1 -> -0.30392015 | AG1621: =R1621/AB1621-1 -> -0.24748179
A1622: 46272 | B1622: =[1]!thsiFinD("ths_int_chg_ratio_index",B$1,$A$4,$A1622,101) -> 237.57831 | C1622: =[1]!thsiFinD("ths_int_chg_ratio_index",C$1,$A$4,$A1622,101) -> 302.49747 | D1622: =[1]!thsiFinD("ths_int_chg_ratio_index",D$1,$A$4,$A1622,101) -> 58.428305 | E1622: =[1]!thsiFinD("ths_int_chg_ratio_index",E$1,$A$4,$A1622,101) -> 131.54364 | F1622: =[1]!thsiFinD("ths_adjustment_nvg_ratio_fund",F$1,$A$4,$A1622,101) -> 310.43585 | G1622: =[1]!thsiFinD("ths_adjustment_nvg_ratio_fund",G$1,$A$4,$A1622,101) -> 365.9381 | H1622: =[1]!thsiFinD("ths_adjustment_nvg_ratio_fund",H$1,$A$4,$A1622,101) -> 471.30769 | I1622: =[1]!thsiFinD("ths_adjustment_nvg_ratio_fund",I$1,$A$4,$A1622,101) -> 543.86719 | J1622: =50%*K1622+50%*L1622 -> 3.0269957 | K1622: =SUMPRODUCT(B1622:E1622,B$3:E$3)/100 -> 1.8251193 | L1622: =SUMPRODUCT(F1622:I1622,F$3:I$3)/100 -> 4.2288721 | M1622: =[1]!thsiFinD("ths_int_chg_ratio_index",M$1,$A$4,$A1622,101)/100 -> 0.50517325 | N1622: =[1]!thsiFinD("ths_int_chg_ratio_index",N$1,$A$4,$A1622,101)/100 -> 0.17909874 | O1622: =J1622+1 -> 4.0269957 | P1622: =K1622+1 -> 2.8251193 | Q1622: =L1622+1 -> 5.2288721 | R1622: =M1622+1 -> 1.5051733 | S1622: =N1622+1 -> 1.1790987 | T1622: =O1622/O1621-1 -> 0.053278744 | U1622: =P1622/P1621-1 -> 0.042683326 | V1622: =Q1622/Q1621-1 -> 0.059093463 | W1622: =R1622/R1621-1 -> 0.0119382 | X1622: =S1622/S1621-1 -> 0.0080975954 | Y1622: =MAX(O$4:O1622) -> 5.4188062 | Z1622: =MAX(P$4:P1622) -> 3.865125 | AA1622: =MAX(Q$4:Q1622) -> 7.0927502 | AB1622: =MAX(R$4:R1622) -> 1.976585 | AC1622: =MAX(S$4:S1622) -> 1.3589987 | AD1622: =O1622/Y1622-1 -> -0.25684818 | AE1622: =P1622/Z1622-1 -> -0.26907427 | AF1622: =Q1622/AA1622-1 -> -0.26278638 | AG1622: =R1622/AB1622-1 -> -0.23849808
A1623: 46273 | B1623: =[1]!thsiFinD("ths_int_chg_ratio_index",B$1,$A$4,$A1623,101) -> 235.20214 | C1623: =[1]!thsiFinD("ths_int_chg_ratio_index",C$1,$A$4,$A1623,101) -> 296.12805 | D1623: =[1]!thsiFinD("ths_int_chg_ratio_index",D$1,$A$4,$A1623,101) -> 56.022251 | E1623: =[1]!thsiFinD("ths_int_chg_ratio_index",E$1,$A$4,$A1623,101) -> 128.65578 | F1623: =[1]!thsiFinD("ths_adjustment_nvg_ratio_fund",F$1,$A$4,$A1623,101) -> 311.78637 | G1623: =[1]!thsiFinD("ths_adjustment_nvg_ratio_fund",G$1,$A$4,$A1623,101) -> 361.99733 | H1623: =[1]!thsiFinD("ths_adjustment_nvg_ratio_fund",H$1,$A$4,$A1623,101) -> 469.23077 | I1623: =[1]!thsiFinD("ths_adjustment_nvg_ratio_fund",I$1,$A$4,$A1623,101) -> 538.31055 | J1623: =50%*K1623+50%*L1623 -> 2.9966665 | K1623: =SUMPRODUCT(B1623:E1623,B$3:E$3)/100 -> 1.7900205 | L1623: =SUMPRODUCT(F1623:I1623,F$3:I$3)/100 -> 4.2033125 | M1623: =[1]!thsiFinD("ths_int_chg_ratio_index",M$1,$A$4,$A1623,101)/100 -> 0.48310911 | N1623: =[1]!thsiFinD("ths_int_chg_ratio_index",N$1,$A$4,$A1623,101)/100 -> 0.17651302 | O1623: =J1623+1 -> 3.9966665 | P1623: =K1623+1 -> 2.7900205 | Q1623: =L1623+1 -> 5.2033125 | R1623: =M1623+1 -> 1.4831091 | S1623: =N1623+1 -> 1.176513 | T1623: =O1623/O1622-1 -> -0.0075314563 | U1623: =P1623/P1622-1 -> -0.012423813 | V1623: =Q1623/Q1622-1 -> -0.0048881536 | W1623: =R1623/R1622-1 -> -0.01465887 | X1623: =S1623/S1622-1 -> -0.0021929616 | Y1623: =MAX(O$4:O1623) -> 5.4188062 | Z1623: =MAX(P$4:P1623) -> 3.865125 | AA1623: =MAX(Q$4:Q1623) -> 7.0927502 | AB1623: =MAX(R$4:R1623) -> 1.976585 | AC1623: =MAX(S$4:S1623) -> 1.3589987 | AD1623: =O1623/Y1623-1 -> -0.26244519 | AE1623: =P1623/Z1623-1 -> -0.27815515 | AF1623: =Q1623/AA1623-1 -> -0.26638999 | AG1623: =R1623/AB1623-1 -> -0.24966083
A1624: 46274 | B1624: =[1]!thsiFinD("ths_int_chg_ratio_index",B$1,$A$4,$A1624,101) -> 237.86189 | C1624: =[1]!thsiFinD("ths_int_chg_ratio_index",C$1,$A$4,$A1624,101) -> 293.54651 | D1624: =[1]!thsiFinD("ths_int_chg_ratio_index",D$1,$A$4,$A1624,101) -> 54.949744 | E1624: =[1]!thsiFinD("ths_int_chg_ratio_index",E$1,$A$4,$A1624,101) -> 128.52895 | F1624: =[1]!thsiFinD("ths_adjustment_nvg_ratio_fund",F$1,$A$4,$A1624,101) -> 312.27747 | G1624: =[1]!thsiFinD("ths_adjustment_nvg_ratio_fund",G$1,$A$4,$A1624,101) -> 362.22914 | H1624: =[1]!thsiFinD("ths_adjustment_nvg_ratio_fund",H$1,$A$4,$A1624,101) -> 471.07692 | I1624: =[1]!thsiFinD("ths_adjustment_nvg_ratio_fund",I$1,$A$4,$A1624,101) -> 541.86523 | J1624: =50%*K1624+50%*L1624 -> 3.0029198 | K1624: =SUMPRODUCT(B1624:E1624,B$3:E$3)/100 -> 1.7872177 | L1624: =SUMPRODUCT(F1624:I1624,F$3:I$3)/100 -> 4.2186219 | M1624: =[1]!thsiFinD("ths_int_chg_ratio_index",M$1,$A$4,$A1624,101)/100 -> 0.47275371 | N1624: =[1]!thsiFinD("ths_int_chg_ratio_index",N$1,$A$4,$A1624,101)/100 -> 0.17900507 | O1624: =J1624+1 -> 4.0029198 | P1624: =K1624+1 -> 2.7872177 | Q1624: =L1624+1 -> 5.2186219 | R1624: =M1624+1 -> 1.4727537 | S1624: =N1624+1 -> 1.1790051 | T1624: =O1624/O1623-1 -> 0.0015646254 | U1624: =P1624/P1623-1 -> -0.0010045817 | V1624: =Q1624/Q1623-1 -> 0.0029422364 | W1624: =R1624/R1623-1 -> -0.0069822237 | X1624: =S1624/S1623-1 -> 0.0021181648 | Y1624: =MAX(O$4:O1624) -> 5.4188062 | Z1624: =MAX(P$4:P1624) -> 3.865125 | AA1624: =MAX(Q$4:Q1624) -> 7.0927502 | AB1624: =MAX(R$4:R1624) -> 1.976585 | AC1624: =MAX(S$4:S1624) -> 1.3589987 | AD1624: =O1624/Y1624-1 -> -0.26129119 | AE1624: =P1624/Z1624-1 -> -0.2788803 | AF1624: =Q1624/AA1624-1 -> -0.26423154 | AG1624: =R1624/AB1624-1 -> -0.25489987
A1625: 46275 | B1625: =[1]!thsiFinD("ths_int_chg_ratio_index",B$1,$A$4,$A1625,101) -> 235.10321 | C1625: =[1]!thsiFinD("ths_int_chg_ratio_index",C$1,$A$4,$A1625,101) -> 293.38369 | D1625: =[1]!thsiFinD("ths_int_chg_ratio_index",D$1,$A$4,$A1625,101) -> 53.886652 | E1625: =[1]!thsiFinD("ths_int_chg_ratio_index",E$1,$A$4,$A1625,101) -> 127.42817 | F1625: =[1]!thsiFinD("ths_adjustment_nvg_ratio_fund",F$1,$A$4,$A1625,101) -> 310.86556 | G1625: =[1]!thsiFinD("ths_adjustment_nvg_ratio_fund",G$1,$A$4,$A1625,101) -> 360.37466 | H1625: =[1]!thsiFinD("ths_adjustment_nvg_ratio_fund",H$1,$A$4,$A1625,101) -> 474 | I1625: =[1]!thsiFinD("ths_adjustment_nvg_ratio_fund",I$1,$A$4,$A1625,101) -> 535.06836 | J1625: =50%*K1625+50%*L1625 -> 2.9876379 | K1625: =SUMPRODUCT(B1625:E1625,B$3:E$3)/100 -> 1.7745043 | L1625: =SUMPRODUCT(F1625:I1625,F$3:I$3)/100 -> 4.2007714 | M1625: =[1]!thsiFinD("ths_int_chg_ratio_index",M$1,$A$4,$A1625,101)/100 -> 0.45575822 | N1625: =[1]!thsiFinD("ths_int_chg_ratio_index",N$1,$A$4,$A1625,101)/100 -> 0.1723833 | O1625: =J1625+1 -> 3.9876379 | P1625: =K1625+1 -> 2.7745043 | Q1625: =L1625+1 -> 5.2007714 | R1625: =M1625+1 -> 1.4557582 | S1625: =N1625+1 -> 1.1723833 | T1625: =O1625/O1624-1 -> -0.0038177025 | U1625: =P1625/P1624-1 -> -0.0045613394 | V1625: =Q1625/Q1624-1 -> -0.0034205329 | W1625: =R1625/R1624-1 -> -0.011539943 | X1625: =S1625/S1624-1 -> -0.0056163992 | Y1625: =MAX(O$4:O1625) -> 5.4188062 | Z1625: =MAX(P$4:P1625) -> 3.865125 | AA1625: =MAX(Q$4:Q1625) -> 7.0927502 | AB1625: =MAX(R$4:R1625) -> 1.976585 | AC1625: =MAX(S$4:S1625) -> 1.3589987 | AD1625: =O1625/Y1625-1 -> -0.26411136 | AE1625: =P1625/Z1625-1 -> -0.28216958 | AF1625: =Q1625/AA1625-1 -> -0.26674826 | AG1625: =R1625/AB1625-1 -> -0.26349828
A1626: 46276 | B1626: =[1]!thsiFinD("ths_int_chg_ratio_index",B$1,$A$4,$A1626,101) -> 237.55742 | C1626: =[1]!thsiFinD("ths_int_chg_ratio_index",C$1,$A$4,$A1626,101) -> 286.98687 | D1626: =[1]!thsiFinD("ths_int_chg_ratio_index",D$1,$A$4,$A1626,101) -> 52.334839 | E1626: =[1]!thsiFinD("ths_int_chg_ratio_index",E$1,$A$4,$A1626,101) -> 126.50602 | F1626: =[1]!thsiFinD("ths_adjustment_nvg_ratio_fund",F$1,$A$4,$A1626,101) -> 308.28729 | G1626: =[1]!thsiFinD("ths_adjustment_nvg_ratio_fund",G$1,$A$4,$A1626,101) -> 360.95418 | H1626: =[1]!thsiFinD("ths_adjustment_nvg_ratio_fund",H$1,$A$4,$A1626,101) -> 481.53846 | I1626: =[1]!thsiFinD("ths_adjustment_nvg_ratio_fund",I$1,$A$4,$A1626,101) -> 537.8418 | J1626: =50%*K1626+50%*L1626 -> 2.9900086 | K1626: =SUMPRODUCT(B1626:E1626,B$3:E$3)/100 -> 1.7584629 | L1626: =SUMPRODUCT(F1626:I1626,F$3:I$3)/100 -> 4.2215543 | M1626: =[1]!thsiFinD("ths_int_chg_ratio_index",M$1,$A$4,$A1626,101)/100 -> 0.44295297 | N1626: =[1]!thsiFinD("ths_int_chg_ratio_index",N$1,$A$4,$A1626,101)/100 -> 0.15953532 | O1626: =J1626+1 -> 3.9900086 | P1626: =K1626+1 -> 2.7584629 | Q1626: =L1626+1 -> 5.2215543 | R1626: =M1626+1 -> 1.442953 | S1626: =N1626+1 -> 1.1595353 | T1626: =O1626/O1625-1 -> 0.00059452175 | U1626: =P1626/P1625-1 -> -0.0057817222 | V1626: =Q1626/Q1625-1 -> 0.0039961164 | W1626: =R1626/R1625-1 -> -0.0087962781 | X1626: =S1626/S1625-1 -> -0.010958857 | Y1626: =MAX(O$4:O1626) -> 5.4188062 | Z1626: =MAX(P$4:P1626) -> 3.865125 | AA1626: =MAX(Q$4:Q1626) -> 7.0927502 | AB1626: =MAX(R$4:R1626) -> 1.976585 | AC1626: =MAX(S$4:S1626) -> 1.3589987 | AD1626: =O1626/Y1626-1 -> -0.26367386 | AE1626: =P1626/Z1626-1 -> -0.28631987 | AF1626: =Q1626/AA1626-1 -> -0.2638181 | AG1626: =R1626/AB1626-1 -> -0.26997676
A1627: 46279 | B1627: =[1]!thsiFinD("ths_int_chg_ratio_index",B$1,$A$4,$A1627,101) -> 228.04837 | C1627: =[1]!thsiFinD("ths_int_chg_ratio_index",C$1,$A$4,$A1627,101) -> 283.35114 | D1627: =[1]!thsiFinD("ths_int_chg_ratio_index",D$1,$A$4,$A1627,101) -> 49.870651 | E1627: =[1]!thsiFinD("ths_int_chg_ratio_index",E$1,$A$4,$A1627,101) -> 122.91542 | F1627: =[1]!thsiFinD("ths_adjustment_nvg_ratio_fund",F$1,$A$4,$A1627,101) -> 304.97238 | G1627: =[1]!thsiFinD("ths_adjustment_nvg_ratio_fund",G$1,$A$4,$A1627,101) -> 352.31926 | H1627: =[1]!thsiFinD("ths_adjustment_nvg_ratio_fund",H$1,$A$4,$A1627,101) -> 477.15385 | I1627: =[1]!thsiFinD("ths_adjustment_nvg_ratio_fund",I$1,$A$4,$A1627,101) -> 515.99609 | J1627: =50%*K1627+50%*L1627 -> 2.9182839 | K1627: =SUMPRODUCT(B1627:E1627,B$3:E$3)/100 -> 1.7104639 | L1627: =SUMPRODUCT(F1627:I1627,F$3:I$3)/100 -> 4.1261039 | M1627: =[1]!thsiFinD("ths_int_chg_ratio_index",M$1,$A$4,$A1627,101)/100 -> 0.42470854 | N1627: =[1]!thsiFinD("ths_int_chg_ratio_index",N$1,$A$4,$A1627,101)/100 -> 0.15350748 | O1627: =J1627+1 -> 3.9182839 | P1627: =K1627+1 -> 2.7104639 | Q1627: =L1627+1 -> 5.1261039 | R1627: =M1627+1 -> 1.4247085 | S1627: =N1627+1 -> 1.1535075 | T1627: =O1627/O1626-1 -> -0.017976067 | U1627: =P1627/P1626-1 -> -0.017400607 | V1627: =Q1627/Q1626-1 -> -0.018280073 | W1627: =R1627/R1626-1 -> -0.012643809 | X1627: =S1627/S1626-1 -> -0.0051985011 | Y1627: =MAX(O$4:O1627) -> 5.4188062 | Z1627: =MAX(P$4:P1627) -> 3.865125 | AA1627: =MAX(Q$4:Q1627) -> 7.0927502 | AB1627: =MAX(R$4:R1627) -> 1.976585 | AC1627: =MAX(S$4:S1627) -> 1.3589987 | AD1627: =O1627/Y1627-1 -> -0.27691011 | AE1627: =P1627/Z1627-1 -> -0.29873834 | AF1627: =Q1627/AA1627-1 -> -0.27727556 | AG1627: =R1627/AB1627-1 -> -0.27920703
A1628: 46280 | B1628: =[1]!thsiFinD("ths_int_chg_ratio_index",B$1,$A$4,$A1628,101) -> 226.00712 | C1628: =[1]!thsiFinD("ths_int_chg_ratio_index",C$1,$A$4,$A1628,101) -> 295.47945 | D1628: =[1]!thsiFinD("ths_int_chg_ratio_index",D$1,$A$4,$A1628,101) -> 52.194026 | E1628: =[1]!thsiFinD("ths_int_chg_ratio_index",E$1,$A$4,$A1628,101) -> 119.52103 | F1628: =[1]!thsiFinD("ths_adjustment_nvg_ratio_fund",F$1,$A$4,$A1628,101) -> 308.16452 | G1628: =[1]!thsiFinD("ths_adjustment_nvg_ratio_fund",G$1,$A$4,$A1628,101) -> 354.3476 | H1628: =[1]!thsiFinD("ths_adjustment_nvg_ratio_fund",H$1,$A$4,$A1628,101) -> 481.53846 | I1628: =[1]!thsiFinD("ths_adjustment_nvg_ratio_fund",I$1,$A$4,$A1628,101) -> 513.97461 | J1628: =50%*K1628+50%*L1628 -> 2.9390335 | K1628: =SUMPRODUCT(B1628:E1628,B$3:E$3)/100 -> 1.733004 | L1628: =SUMPRODUCT(F1628:I1628,F$3:I$3)/100 -> 4.145063 | M1628: =[1]!thsiFinD("ths_int_chg_ratio_index",M$1,$A$4,$A1628,101)/100 -> 0.42872916 | N1628: =[1]!thsiFinD("ths_int_chg_ratio_index",N$1,$A$4,$A1628,101)/100 -> 0.14747457 | O1628: =J1628+1 -> 3.9390335 | P1628: =K1628+1 -> 2.733004 | Q1628: =L1628+1 -> 5.145063 | R1628: =M1628+1 -> 1.4287292 | S1628: =N1628+1 -> 1.1474746 | T1628: =O1628/O1627-1 -> 0.0052955739 | U1628: =P1628/P1627-1 -> 0.0083159552 | V1628: =Q1628/Q1627-1 -> 0.0036985257 | W1628: =R1628/R1627-1 -> 0.0028220651 | X1628: =S1628/S1627-1 -> -0.0052300594 | Y1628: =MAX(O$4:O1628) -> 5.4188062 | Z1628: =MAX(P$4:P1628) -> 3.865125 | AA1628: =MAX(Q$4:Q1628) -> 7.0927502 | AB1628: =MAX(R$4:R1628) -> 1.976585 | AC1628: =MAX(S$4:S1628) -> 1.3589987 | AD1628: =O1628/Y1628-1 -> -0.27308094 | AE1628: =P1628/Z1628-1 -> -0.29290668 | AF1628: =Q1628/AA1628-1 -> -0.27460254 | AG1628: =R1628/AB1628-1 -> -0.27717291
A1629: 46281 | B1629: =[1]!thsiFinD("ths_int_chg_ratio_index",B$1,$A$4,$A1629,101) -> 241.4069 | C1629: =[1]!thsiFinD("ths_int_chg_ratio_index",C$1,$A$4,$A1629,101) -> 315.6092 | D1629: =[1]!thsiFinD("ths_int_chg_ratio_index",D$1,$A$4,$A1629,101) -> 58.492548 | E1629: =[1]!thsiFinD("ths_int_chg_ratio_index",E$1,$A$4,$A1629,101) -> 124.18118 | F1629: =[1]!thsiFinD("ths_adjustment_nvg_ratio_fund",F$1,$A$4,$A1629,101) -> 315.28545 | G1629: =[1]!thsiFinD("ths_adjustment_nvg_ratio_fund",G$1,$A$4,$A1629,101) -> 369.99477 | H1629: =[1]!thsiFinD("ths_adjustment_nvg_ratio_fund",H$1,$A$4,$A1629,101) -> 501.76923 | I1629: =[1]!thsiFinD("ths_adjustment_nvg_ratio_fund",I$1,$A$4,$A1629,101) -> 534.53125 | J1629: =50%*K1629+50%*L1629 -> 3.0765882 | K1629: =SUMPRODUCT(B1629:E1629,B$3:E$3)/100 -> 1.8492246 | L1629: =SUMPRODUCT(F1629:I1629,F$3:I$3)/100 -> 4.3039518 | M1629: =[1]!thsiFinD("ths_int_chg_ratio_index",M$1,$A$4,$A1629,101)/100 -> 0.46573645 | N1629: =[1]!thsiFinD("ths_int_chg_ratio_index",N$1,$A$4,$A1629,101)/100 -> 0.15818514 | O1629: =J1629+1 -> 4.0765882 | P1629: =K1629+1 -> 2.8492246 | Q1629: =L1629+1 -> 5.3039518 | R1629: =M1629+1 -> 1.4657364 | S1629: =N1629+1 -> 1.1581851 | T1629: =O1629/O1628-1 -> 0.034920919 | U1629: =P1629/P1628-1 -> 0.042524834 | V1629: =Q1629/Q1628-1 -> 0.030881798 | W1629: =R1629/R1628-1 -> 0.025902239 | X1629: =S1629/S1628-1 -> 0.0093340399 | Y1629: =MAX(O$4:O1629) -> 5.4188062 | Z1629: =MAX(P$4:P1629) -> 3.865125 | AA1629: =MAX(Q$4:Q1629) -> 7.0927502 | AB1629: =MAX(R$4:R1629) -> 1.976585 | AC1629: =MAX(S$4:S1629) -> 1.3589987 | AD1629: =O1629/Y1629-1 -> -0.24769625 | AE1629: =P1629/Z1629-1 -> -0.26283765 | AF1629: =Q1629/AA1629-1 -> -0.25220097 | AG1629: =R1629/AB1629-1 -> -0.25845007
... A1631: 46283 | B1631: =[1]!thsiFinD("ths_int_chg_ratio_index",B$1,$A$4,$A1631,101) -> 251.55212 | C1631: =[1]!thsiFinD("ths_int_chg_ratio_index",C$1,$A$4,$A1631,101) -> 331.12853 | D1631: =[1]!thsiFinD("ths_int_chg_ratio_index",D$1,$A$4,$A1631,101) -> 62.066596 | E1631: =[1]!thsiFinD("ths_int_chg_ratio_index",E$1,$A$4,$A1631,101) -> 128.20285 | F1631: =[1]!thsiFinD("ths_adjustment_nvg_ratio_fund",F$1,$A$4,$A1631,101) -> 314.91713 | G1631: =[1]!thsiFinD("ths_adjustment_nvg_ratio_fund",G$1,$A$4,$A1631,101) -> 377.00702 | H1631: =[1]!thsiFinD("ths_adjustment_nvg_ratio_fund",H$1,$A$4,$A1631,101) -> 510.23077 | I1631: =[1]!thsiFinD("ths_adjustment_nvg_ratio_fund",I$1,$A$4,$A1631,101) -> 542.91016 | J1631: =50%*K1631+50%*L1631 -> 3.147519 | K1631: =SUMPRODUCT(B1631:E1631,B$3:E$3)/100 -> 1.9323752 | L1631: =SUMPRODUCT(F1631:I1631,F$3:I$3)/100 -> 4.3626627 | M1631: =[1]!thsiFinD("ths_int_chg_ratio_index",M$1,$A$4,$A1631,101)/100 -> 0.50747294 | N1631: =[1]!thsiFinD("ths_int_chg_ratio_index",N$1,$A$4,$A1631,101)/100 -> 0.1680768 | O1631: =J1631+1 -> 4.147519 | P1631: =K1631+1 -> 2.9323752 | Q1631: =L1631+1 -> 5.3626627 | R1631: =M1631+1 -> 1.5074729 | S1631: =N1631+1 -> 1.1680768 | T1631: =O1631/O1630-1 -> 0.026025155 | U1631: =P1631/P1630-1 -> 0.029356525 | V1631: =Q1631/Q1630-1 -> 0.02421262 | W1631: =R1631/R1630-1 -> 0.028861115 | X1631: =S1631/S1630-1 -> 0.012870546 | Y1631: =MAX(O$4:O1631) -> 5.4188062 | Z1631: =MAX(P$4:P1631) -> 3.865125 | AA1631: =MAX(Q$4:Q1631) -> 7.0927502 | AB1631: =MAX(R$4:R1631) -> 1.976585 | AC1631: =MAX(S$4:S1631) -> 1.3589987 | AD1631: =O1631/Y1631-1 -> -0.23460651 | AE1631: =P1631/Z1631-1 -> -0.2413246 | AF1631: =Q1631/AA1631-1 -> -0.24392337 | AG1631: =R1631/AB1631-1 -> -0.23733461

Sheet 增值-指数增强
F1: 000852.SH | G1: 000852.SH | H1: 932000.CSI | I1: 932000.CSI
A2: 宽基指增组合 | B2: 003957.OF | C2: 007044.OF | D2: 001556.OF | E2: 006593.OF | F2: 017953.OF | G2: 015867.OF | H2: 019923.OF | I2: 019918.OF | K2: 000906.SH | L2: 000985.CSI
A3: 基金简称 | B3: 安信量化精选沪深300指数增强A | C3: 博道沪深300指数增强A | D3: 天弘中证500指数增强A | E3: 博道中证500指数增强A | F3: 汇添富中证1000指数增强A | G3: 国泰海通中证1000指数增强A | H3: 华泰柏瑞中证2000指数增强A | I3: 招商中证2000指数增强A | K3: 中证800 | L3: 中证全指
A4: 等权 | B4: 0.125 | C4: 0.125 | D4: 0.125 | E4: 0.125 | F4: 0.125 | G4: 0.125 | H4: 0.125 | I4: 0.125 | J4: 指增组合 | K4: 基准
A5: =[1]!HX_AutoDate(1,"2020-01-01","2026-08-31",-1,-1,0,1,0,0,0,"SSE",1615,0) -> 日期 | B5: =[1]!thsiFinD("ths_fund_establishment_date_fund",B2) -> 2017-03-16 | C5: =[1]!thsiFinD("ths_fund_establishment_date_fund",C2) -> 2019-04-26 | D5: =[1]!thsiFinD("ths_fund_establishment_date_fund",D2) -> 2019-08-12 | E5: =[1]!thsiFinD("ths_fund_establishment_date_fund",E2) -> 2019-01-03 | F5: =[1]!thsiFinD("ths_fund_establishment_date_fund",F2) -> 2023-05-19 | G5: =[1]!thsiFinD("ths_fund_establishment_date_fund",G2) -> 2022-08-16 | H5: =[1]!thsiFinD("ths_fund_establishment_date_fund",H2) -> 2024-01-12 | I5: =[1]!thsiFinD("ths_fund_establishment_date_fund",I2) -> 2024-01-02 | J5: 指增组合 | K5: 中证800 | M5: 增值-指数增强 | N5: 中证800 | O5: 中证全指
A6: 43832 | B6: =[1]!thsiFinD("ths_adjustment_nvg_ratio_fund",B$2,$A$6,$A6,101)/100 -> 0.013267263 | C6: =[1]!thsiFinD("ths_adjustment_nvg_ratio_fund",C$2,$A$6,$A6,101)/100 -> 0.010251064 | D6: =[1]!thsiFinD("ths_adjustment_nvg_ratio_fund",D$2,$A$6,$A6,101)/100 -> 0.017852864 | E6: =[1]!thsiFinD("ths_adjustment_nvg_ratio_fund",E$2,$A$6,$A6,101)/100 -> 0.016333026 | F6: =[1]!thsiFinD("ths_int_chg_ratio_index",F$1,$A$6,$A6,101)/100 -> 0.019673837 | G6: =[1]!thsiFinD("ths_int_chg_ratio_index",G$1,$A$6,$A6,101)/100 -> 0.019673837 | H6: =[1]!thsiFinD("ths_int_chg_ratio_index",H$1,$A$6,$A6,101)/100 -> 0.020714398 | I6: =[1]!thsiFinD("ths_int_chg_ratio_index",I$1,$A$6,$A6,101)/100 -> 0.020714398 | J6: =SUMPRODUCT(B6:I6,$B$4:$I$4) -> 0.017310086 | K6: =[1]!thsiFinD("ths_int_chg_ratio_index",K$2,$A$6,$A6,101)/100 -> 0.014798646 | L6: =[1]!thsiFinD("ths_int_chg_ratio_index",L$2,$A$6,$A6,101)/100 -> 0.015909866 | M6: =1+J6 -> 1.0173101 | N6: =1+K6 -> 1.0147986 | O6: =1+L6 -> 1.0159099 | AD6: 2020/1/1-2026/4/30 | AE6: =M5 -> 增值-指数增强 | AF6: =N5 -> 中证800 | AG6: =O5 -> 中证全指
A7: 43833 | B7: =[1]!thsiFinD("ths_adjustment_nvg_ratio_fund",B$2,$A$6,$A7,101)/100 -> 0.011508951 | C7: =[1]!thsiFinD("ths_adjustment_nvg_ratio_fund",C$2,$A$6,$A7,101)/100 -> 0.0050386587 | D7: =[1]!thsiFinD("ths_adjustment_nvg_ratio_fund",D$2,$A$6,$A7,101)/100 -> 0.020848311 | E7: =[1]!thsiFinD("ths_adjustment_nvg_ratio_fund",E$2,$A$6,$A7,101)/100 -> 0.019013318 | F7: =[1]!thsiFinD("ths_int_chg_ratio_index",F$1,$A$6,$A7,101)/100 -> 0.024970357 | G7: =[1]!thsiFinD("ths_int_chg_ratio_index",G$1,$A$6,$A7,101)/100 -> 0.024970357 | H7: =[1]!thsiFinD("ths_int_chg_ratio_index",H$1,$A$6,$A7,101)/100 -> 0.027680657 | I7: =[1]!thsiFinD("ths_int_chg_ratio_index",I$1,$A$6,$A7,101)/100 -> 0.027680657 | J7: =SUMPRODUCT(B7:I7,$B$4:$I$4) -> 0.020213908 | K7: =[1]!thsiFinD("ths_int_chg_ratio_index",K$2,$A$6,$A7,101)/100 -> 0.014097168 | L7: =[1]!thsiFinD("ths_int_chg_ratio_index",L$2,$A$6,$A7,101)/100 -> 0.016981525 | M7: =1+J7 -> 1.0202139 | N7: =1+K7 -> 1.0140972 | O7: =1+L7 -> 1.0169815 | P7: =M7/M6-1 -> 0.0028544122 | Q7: =N7/N6-1 -> -0.00069124917 | R7: =O7/O6-1 -> 0.001054876 | S7: =MAX(M$6:M7) -> 1.0202139 | T7: =MAX(N$6:N7) -> 1.0147986 | U7: =MAX(O$6:O7) -> 1.0169815 | V7: =M7/S7-1 -> 0 | W7: =N7/T7-1 -> -0.00069124917 | X7: =O7/U7-1 -> 0 | AD7: 累计收益率 | AE7: =M1537-1 -> 1.0825817 | AF7: =N1537-1 -> 0.26580537 | AG7: =O1537-1 -> 0.40935251
A8: 43836 | B8: =[1]!thsiFinD("ths_adjustment_nvg_ratio_fund",B$2,$A$6,$A8,101)/100 -> 0.0085517903 | C8: =[1]!thsiFinD("ths_adjustment_nvg_ratio_fund",C$2,$A$6,$A8,101)/100 -> 0.00078186083 | D8: =[1]!thsiFinD("ths_adjustment_nvg_ratio_fund",D$2,$A$6,$A8,101)/100 -> 0.03330937 | E8: =[1]!thsiFinD("ths_adjustment_nvg_ratio_fund",E$2,$A$6,$A8,101)/100 -> 0.025127733 | F8: =[1]!thsiFinD("ths_int_chg_ratio_index",F$1,$A$6,$A8,101)/100 -> 0.035512705 | G8: =[1]!thsiFinD("ths_int_chg_ratio_index",G$1,$A$6,$A8,101)/100 -> 0.035512705 | H8: =[1]!thsiFinD("ths_int_chg_ratio_index",H$1,$A$6,$A8,101)/100 -> 0.036190635 | I8: =[1]!thsiFinD("ths_int_chg_ratio_index",I$1,$A$6,$A8,101)/100 -> 0.036190635 | J8: =SUMPRODUCT(B8:I8,$B$4:$I$4) -> 0.026397179 | K8: =[1]!thsiFinD("ths_int_chg_ratio_index",K$2,$A$6,$A8,101)/100 -> 0.013622426 | L8: =[1]!thsiFinD("ths_int_chg_ratio_index",L$2,$A$6,$A8,101)/100 -> 0.019071667 | M8: =1+J8 -> 1.0263972 | N8: =1+K8 -> 1.0136224 | O8: =1+L8 -> 1.0190717 | P8: =M8/M7-1 -> 0.0060607591 | Q8: =N8/N7-1 -> -0.00046814265 | R8: =O8/O7-1 -> 0.0020552405 | S8: =MAX(M$6:M8) -> 1.0263972 | T8: =MAX(N$6:N8) -> 1.0147986 | U8: =MAX(O$6:O8) -> 1.0190717 | V8: =M8/S8-1 -> 0 | W8: =N8/T8-1 -> -0.0011590682 | X8: =O8/U8-1 -> 0 | AD8: 最大回撤 | AE8: =MIN(V10:V1537) -> -0.39461055 | AF8: =MIN(W10:W1537) -> -0.42957366 | AG8: =MIN(X10:X1537) -> -0.39331486
A9: 43837 | B9: =[1]!thsiFinD("ths_adjustment_nvg_ratio_fund",B$2,$A$6,$A9,101)/100 -> 0.015105499 | C9: =[1]!thsiFinD("ths_adjustment_nvg_ratio_fund",C$2,$A$6,$A9,101)/100 -> 0.010251064 | D9: =[1]!thsiFinD("ths_adjustment_nvg_ratio_fund",D$2,$A$6,$A9,101)/100 -> 0.048286604 | E9: =[1]!thsiFinD("ths_adjustment_nvg_ratio_fund",E$2,$A$6,$A9,101)/100 -> 0.037356563 | F9: =[1]!thsiFinD("ths_int_chg_ratio_index",F$1,$A$6,$A9,101)/100 -> 0.051253136 | G9: =[1]!thsiFinD("ths_int_chg_ratio_index",G$1,$A$6,$A9,101)/100 -> 0.051253136 | H9: =[1]!thsiFinD("ths_int_chg_ratio_index",H$1,$A$6,$A9,101)/100 -> 0.050539517 | I9: =[1]!thsiFinD("ths_int_chg_ratio_index",I$1,$A$6,$A9,101)/100 -> 0.050539517 | J9: =SUMPRODUCT(B9:I9,$B$4:$I$4) -> 0.03932313 | K9: =[1]!thsiFinD("ths_int_chg_ratio_index",K$2,$A$6,$A9,101)/100 -> 0.022309936 | L9: =[1]!thsiFinD("ths_int_chg_ratio_index",L$2,$A$6,$A9,101)/100 -> 0.029597284 | M9: =1+J9 -> 1.0393231 | N9: =1+K9 -> 1.0223099 | O9: =1+L9 -> 1.0295973 | P9: =M9/M8-1 -> 0.012593517 | Q9: =N9/N8-1 -> 0.0085707555 | R9: =O9/O8-1 -> 0.010328633 | S9: =MAX(M$6:M9) -> 1.0393231 | T9: =MAX(N$6:N9) -> 1.0223099 | U9: =MAX(O$6:O9) -> 1.0295973 | V9: =M9/S9-1 -> 0 | W9: =N9/T9-1 -> 0 | X9: =O9/U9-1 -> 0 | Z9: 43830 | AA9: 1 | AB9: 1 | AC9: 1 | AD9: 年化波动率 | AE9: =STDEV(P6:P1537)*250^0.5 -> 0.20526196 | AF9: =STDEV(Q6:Q1537)*250^0.5 -> 0.18932771 | AG9: =STDEV(R6:R1537)*250^0.5 -> 0.19956447
A10: 43838 | B10: =[1]!thsiFinD("ths_adjustment_nvg_ratio_fund",B$2,$A$6,$A10,101)/100 -> 0.0041560102 | C10: =[1]!thsiFinD("ths_adjustment_nvg_ratio_fund",C$2,$A$6,$A10,101)/100 -> -0.0013899748 | D10: =[1]!thsiFinD("ths_adjustment_nvg_ratio_fund",D$2,$A$6,$A10,101)/100 -> 0.039300264 | E10: =[1]!thsiFinD("ths_adjustment_nvg_ratio_fund",E$2,$A$6,$A10,101)/100 -> 0.024122623 | F10: =[1]!thsiFinD("ths_int_chg_ratio_index",F$1,$A$6,$A10,101)/100 -> 0.036903176 | G10: =[1]!thsiFinD("ths_int_chg_ratio_index",G$1,$A$6,$A10,101)/100 -> 0.036903176 | H10: =[1]!thsiFinD("ths_int_chg_ratio_index",H$1,$A$6,$A10,101)/100 -> 0.034725679 | I10: =[1]!thsiFinD("ths_int_chg_ratio_index",I$1,$A$6,$A10,101)/100 -> 0.034725679 | J10: =SUMPRODUCT(B10:I10,$B$4:$I$4) -> 0.026180829 | K10: =[1]!thsiFinD("ths_int_chg_ratio_index",K$2,$A$6,$A10,101)/100 -> 0.0099639288 | L10: =[1]!thsiFinD("ths_int_chg_ratio_index",L$2,$A$6,$A10,101)/100 -> 0.016718244 | M10: =1+J10 -> 1.0261808 | N10: =1+K10 -> 1.0099639 | O10: =1+L10 -> 1.0167182 | P10: =M10/M9-1 -> -0.012645057 | Q10: =N10/N9-1 -> -0.012076579 | R10: =O10/O9-1 -> -0.012508813 | S10: =MAX(M$6:M10) -> 1.0393231 | T10: =MAX(N$6:N10) -> 1.0223099 | U10: =MAX(O$6:O10) -> 1.0295973 | V10: =M10/S10-1 -> -0.012645057 | W10: =N10/T10-1 -> -0.012076579 | X10: =O10/U10-1 -> -0.012508813 | Z10: 44195 | AA10: =VLOOKUP($Z10,$A$3:$O$1537,13,0) -> 1.2909082 | AB10: =VLOOKUP($Z10,$A$3:$O$1537,14,0) -> 1.2352707 | AC10: =VLOOKUP($Z10,$A$3:$O$1537,15,0) -> 1.2275745 | AD10: 2020年 | AE10: =AA10/AA9-1 -> 0.29090822 | AF10: =AB10/AB9-1 -> 0.23527065 | AG10: =AC10/AC9-1 -> 0.2275745
A11: 43839 | B11: =[1]!thsiFinD("ths_adjustment_nvg_ratio_fund",B$2,$A$6,$A11,101)/100 -> 0.016464194 | C11: =[1]!thsiFinD("ths_adjustment_nvg_ratio_fund",C$2,$A$6,$A11,101)/100 -> 0.012075406 | D11: =[1]!thsiFinD("ths_adjustment_nvg_ratio_fund",D$2,$A$6,$A11,101)/100 -> 0.052600048 | E11: =[1]!thsiFinD("ths_adjustment_nvg_ratio_fund",E$2,$A$6,$A11,101)/100 -> 0.039031745 | F11: =[1]!thsiFinD("ths_int_chg_ratio_index",F$1,$A$6,$A11,101)/100 -> 0.053376565 | G11: =[1]!thsiFinD("ths_int_chg_ratio_index",G$1,$A$6,$A11,101)/100 -> 0.053376565 | H11: =[1]!thsiFinD("ths_int_chg_ratio_index",H$1,$A$6,$A11,101)/100 -> 0.053244578 | I11: =[1]!thsiFinD("ths_int_chg_ratio_index",I$1,$A$6,$A11,101)/100 -> 0.053244578 | J11: =SUMPRODUCT(B11:I11,$B$4:$I$4) -> 0.04167671 | K11: =[1]!thsiFinD("ths_int_chg_ratio_index",K$2,$A$6,$A11,101)/100 -> 0.022977407 | L11: =[1]!thsiFinD("ths_int_chg_ratio_index",L$2,$A$6,$A11,101)/100 -> 0.031051021 | M11: =1+J11 -> 1.0416767 | N11: =1+K11 -> 1.0229774 | O11: =1+L11 -> 1.031051 | P11: =M11/M10-1 -> 0.015100536 | Q11: =N11/N10-1 -> 0.012885092 | R11: =O11/O10-1 -> 0.014097098 | S11: =MAX(M$6:M11) -> 1.0416767 | T11: =MAX(N$6:N11) -> 1.0229774 | U11: =MAX(O$6:O11) -> 1.031051 | V11: =M11/S11-1 -> 0 | W11: =N11/T11-1 -> 0 | X11: =O11/U11-1 -> 0 | Z11: 44561 | AA11: =VLOOKUP($Z11,$A$3:$O$1537,13,0) -> 1.5316406 | AB11: =VLOOKUP($Z11,$A$3:$O$1537,14,0) -> 1.2483765 | AC11: =VLOOKUP($Z11,$A$3:$O$1537,15,0) -> 1.3265852 | AD11: 2021年 | AE11: =AA11/AA10-1 -> 0.18648292 | AF11: =AB11/AB10-1 -> 0.010609659 | AG11: =AC11/AC10-1 -> 0.080655515
A12: 43840 | B12: =[1]!thsiFinD("ths_adjustment_nvg_ratio_fund",B$2,$A$6,$A12,101)/100 -> 0.016624041 | C12: =[1]!thsiFinD("ths_adjustment_nvg_ratio_fund",C$2,$A$6,$A12,101)/100 -> 0.013726001 | D12: =[1]!thsiFinD("ths_adjustment_nvg_ratio_fund",D$2,$A$6,$A12,101)/100 -> 0.055475677 | E12: =[1]!thsiFinD("ths_adjustment_nvg_ratio_fund",E$2,$A$6,$A12,101)/100 -> 0.03668649 | F12: =[1]!thsiFinD("ths_int_chg_ratio_index",F$1,$A$6,$A12,101)/100 -> 0.051169052 | G12: =[1]!thsiFinD("ths_int_chg_ratio_index",G$1,$A$6,$A12,101)/100 -> 0.051169052 | H12: =[1]!thsiFinD("ths_int_chg_ratio_index",H$1,$A$6,$A12,101)/100 -> 0.050360639 | I12: =[1]!thsiFinD("ths_int_chg_ratio_index",I$1,$A$6,$A12,101)/100 -> 0.050360639 | J12: =SUMPRODUCT(B12:I12,$B$4:$I$4) -> 0.040696449 | K12: =[1]!thsiFinD("ths_int_chg_ratio_index",K$2,$A$6,$A12,101)/100 -> 0.021976176 | L12: =[1]!thsiFinD("ths_int_chg_ratio_index",L$2,$A$6,$A12,101)/100 -> 0.029621039 | M12: =1+J12 -> 1.0406964 | N12: =1+K12 -> 1.0219762 | O12: =1+L12 -> 1.029621 | P12: =M12/M11-1 -> -0.00094104152 | Q12: =N12/N11-1 -> -0.00097874203 | R12: =O12/O11-1 -> -0.0013869171 | S12: =MAX(M$6:M12) -> 1.0416767 | T12: =MAX(N$6:N12) -> 1.0229774 | U12: =MAX(O$6:O12) -> 1.031051 | V12: =M12/S12-1 -> -0.00094104152 | W12: =N12/T12-1 -> -0.00097874203 | X12: =O12/U12-1 -> -0.0013869171 | Z12: 44925 | AA12: =VLOOKUP($Z12,$A$3:$O$1537,13,0) -> 1.2360576 | AB12: =VLOOKUP($Z12,$A$3:$O$1537,14,0) -> 0.98227152 | AC12: =VLOOKUP($Z12,$A$3:$O$1537,15,0) -> 1.0569979 | AD12: 2022年 | AE12: =AA12/AA11-1 -> -0.19298452 | AF12: =AB12/AB11-1 -> -0.21316081 | AG12: =AC12/AC11-1 -> -0.20321895
A13: 43843 | B13: =[1]!thsiFinD("ths_adjustment_nvg_ratio_fund",B$2,$A$6,$A13,101)/100 -> 0.025895141 | C13: =[1]!thsiFinD("ths_adjustment_nvg_ratio_fund",C$2,$A$6,$A13,101)/100 -> 0.025453914 | D13: =[1]!thsiFinD("ths_adjustment_nvg_ratio_fund",D$2,$A$6,$A13,101)/100 -> 0.070812365 | E13: =[1]!thsiFinD("ths_adjustment_nvg_ratio_fund",E$2,$A$6,$A13,101)/100 -> 0.04891532 | F13: =[1]!thsiFinD("ths_int_chg_ratio_index",F$1,$A$6,$A13,101)/100 -> 0.064610574 | G13: =[1]!thsiFinD("ths_int_chg_ratio_index",G$1,$A$6,$A13,101)/100 -> 0.064610574 | H13: =[1]!thsiFinD("ths_int_chg_ratio_index",H$1,$A$6,$A13,101)/100 -> 0.063413966 | I13: =[1]!thsiFinD("ths_int_chg_ratio_index",I$1,$A$6,$A13,101)/100 -> 0.063413966 | J13: =SUMPRODUCT(B13:I13,$B$4:$I$4) -> 0.053390728 | K13: =[1]!thsiFinD("ths_int_chg_ratio_index",K$2,$A$6,$A13,101)/100 -> 0.033150169 | L13: =[1]!thsiFinD("ths_int_chg_ratio_index",L$2,$A$6,$A13,101)/100 -> 0.041183693 | M13: =1+J13 -> 1.0533907 | N13: =1+K13 -> 1.0331502 | O13: =1+L13 -> 1.0411837 | P13: =M13/M12-1 -> 0.012197869 | Q13: =N13/N12-1 -> 0.010933712 | R13: =O13/O12-1 -> 0.01123001 | S13: =MAX(M$6:M13) -> 1.0533907 | T13: =MAX(N$6:N13) -> 1.0331502 | U13: =MAX(O$6:O13) -> 1.0411837 | V13: =M13/S13-1 -> 0 | W13: =N13/T13-1 -> 0 | X13: =O13/U13-1 -> 0 | Z13: 45289 | AA13: =VLOOKUP($Z13,$A$3:$O$1537,13,0) -> 1.2128247 | AB13: =VLOOKUP($Z13,$A$3:$O$1537,14,0) -> 0.88037842 | AC13: =VLOOKUP($Z13,$A$3:$O$1537,15,0) -> 0.98262962 | AD13: 2023年 | AE13: =AA13/AA12-1 -> -0.018795985 | AF13: =AB13/AB12-1 -> -0.10373211 | AG13: =AC13/AC12-1 -> -0.070358037
A14: 43844 | B14: =[1]!thsiFinD("ths_adjustment_nvg_ratio_fund",B$2,$A$6,$A14,101)/100 -> 0.022538363 | C14: =[1]!thsiFinD("ths_adjustment_nvg_ratio_fund",C$2,$A$6,$A14,101)/100 -> 0.023021458 | D14: =[1]!thsiFinD("ths_adjustment_nvg_ratio_fund",D$2,$A$6,$A14,101)/100 -> 0.069734004 | E14: =[1]!thsiFinD("ths_adjustment_nvg_ratio_fund",E$2,$A$6,$A14,101)/100 -> 0.047658933 | F14: =[1]!thsiFinD("ths_int_chg_ratio_index",F$1,$A$6,$A14,101)/100 -> 0.062345616 | G14: =[1]!thsiFinD("ths_int_chg_ratio_index",G$1,$A$6,$A14,101)/100 -> 0.062345616 | H14: =[1]!thsiFinD("ths_int_chg_ratio_index",H$1,$A$6,$A14,101)/100 -> 0.063628957 | I14: =[1]!thsiFinD("ths_int_chg_ratio_index",I$1,$A$6,$A14,101)/100 -> 0.063628957 | J14: =SUMPRODUCT(B14:I14,$B$4:$I$4) -> 0.051862738 | K14: =[1]!thsiFinD("ths_int_chg_ratio_index",K$2,$A$6,$A14,101)/100 -> 0.029745568 | L14: =[1]!thsiFinD("ths_int_chg_ratio_index",L$2,$A$6,$A14,101)/100 -> 0.038338262 | M14: =1+J14 -> 1.0518627 | N14: =1+K14 -> 1.0297456 | O14: =1+L14 -> 1.0383383 | P14: =M14/M13-1 -> -0.001450544 | Q14: =N14/N13-1 -> -0.0032953596 | R14: =O14/O13-1 -> -0.0027328814 | S14: =MAX(M$6:M14) -> 1.0533907 | T14: =MAX(N$6:N14) -> 1.0331502 | U14: =MAX(O$6:O14) -> 1.0411837 | V14: =M14/S14-1 -> -0.001450544 | W14: =N14/T14-1 -> -0.0032953596 | X14: =O14/U14-1 -> -0.0027328814 | Z14: 45657 | AA14: =VLOOKUP($Z14,$A$3:$O$1537,13,0) -> 1.3278276 | AB14: =VLOOKUP($Z14,$A$3:$O$1537,14,0) -> 0.98780937 | AC14: =VLOOKUP($Z14,$A$3:$O$1537,15,0) -> 1.0556757 | AD14: 2024年 | AE14: =AA14/AA13-1 -> 0.094822329 | AF14: =AB14/AB13-1 -> 0.12202815 | AG14: =AC14/AC13-1 -> 0.07433736
A15: 43845 | B15: =[1]!thsiFinD("ths_adjustment_nvg_ratio_fund",B$2,$A$6,$A15,101)/100 -> 0.017663043 | C15: =[1]!thsiFinD("ths_adjustment_nvg_ratio_fund",C$2,$A$6,$A15,101)/100 -> 0.01850404 | D15: =[1]!thsiFinD("ths_adjustment_nvg_ratio_fund",D$2,$A$6,$A15,101)/100 -> 0.068535826 | E15: =[1]!thsiFinD("ths_adjustment_nvg_ratio_fund",E$2,$A$6,$A15,101)/100 -> 0.044392328 | F15: =[1]!thsiFinD("ths_int_chg_ratio_index",F$1,$A$6,$A15,101)/100 -> 0.062238719 | G15: =[1]!thsiFinD("ths_int_chg_ratio_index",G$1,$A$6,$A15,101)/100 -> 0.062238719 | H15: =[1]!thsiFinD("ths_int_chg_ratio_index",H$1,$A$6,$A15,101)/100 -> 0.059622622 | I15: =[1]!thsiFinD("ths_int_chg_ratio_index",I$1,$A$6,$A15,101)/100 -> 0.059622622 | J15: =SUMPRODUCT(B15:I15,$B$4:$I$4) -> 0.04910224 | K15: =[1]!thsiFinD("ths_int_chg_ratio_index",K$2,$A$6,$A15,101)/100 -> 0.024881541 | L15: =[1]!thsiFinD("ths_int_chg_ratio_index",L$2,$A$6,$A15,101)/100 -> 0.034398527 | M15: =1+J15 -> 1.0491022 | N15: =1+K15 -> 1.0248815 | O15: =1+L15 -> 1.0343985 | P15: =M15/M14-1 -> -0.0026243904 | Q15: =N15/N14-1 -> -0.0047235229 | R15: =O15/O14-1 -> -0.0037942686 | S15: =MAX(M$6:M15) -> 1.0533907 | T15: =MAX(N$6:N15) -> 1.0331502 | U15: =MAX(O$6:O15) -> 1.0411837 | V15: =M15/S15-1 -> -0.0040711276 | W15: =N15/T15-1 -> -0.0080033168 | X15: =O15/U15-1 -> -0.0065167808 | Z15: 46022 | AA15: =VLOOKUP($Z15,$A$3:$O$1537,13,0) -> 1.8492078 | AB15: =VLOOKUP($Z15,$A$3:$O$1537,14,0) -> 1.1941416 | AC15: =VLOOKUP($Z15,$A$3:$O$1537,15,0) -> 1.3153222 | AD15: 2025年 | AE15: =AA15/AA14-1 -> 0.39265658 | AF15: =AB15/AB14-1 -> 0.20887859 | AG15: =AC15/AC14-1 -> 0.24595287
A16: 43846 | B16: =[1]!thsiFinD("ths_adjustment_nvg_ratio_fund",B$2,$A$6,$A16,101)/100 -> 0.015025575 | C16: =[1]!thsiFinD("ths_adjustment_nvg_ratio_fund",C$2,$A$6,$A16,101)/100 -> 0.019199027 | D16: =[1]!thsiFinD("ths_adjustment_nvg_ratio_fund",D$2,$A$6,$A16,101)/100 -> 0.067577283 | E16: =[1]!thsiFinD("ths_adjustment_nvg_ratio_fund",E$2,$A$6,$A16,101)/100 -> 0.045313678 | F16: =[1]!thsiFinD("ths_int_chg_ratio_index",F$1,$A$6,$A16,101)/100 -> 0.060193428 | G16: =[1]!thsiFinD("ths_int_chg_ratio_index",G$1,$A$6,$A16,101)/100 -> 0.060193428 | H16: =[1]!thsiFinD("ths_int_chg_ratio_index",H$1,$A$6,$A16,101)/100 -> 0.056675335 | I16: =[1]!thsiFinD("ths_int_chg_ratio_index",I$1,$A$6,$A16,101)/100 -> 0.056675335 | J16: =SUMPRODUCT(B16:I16,$B$4:$I$4) -> 0.047606636 | K16: =[1]!thsiFinD("ths_int_chg_ratio_index",K$2,$A$6,$A16,101)/100 -> 0.021482386 | L16: =[1]!thsiFinD("ths_int_chg_ratio_index",L$2,$A$6,$A16,101)/100 -> 0.031352501 | M16: =1+J16 -> 1.0476066 | N16: =1+K16 -> 1.0214824 | O16: =1+L16 -> 1.0313525 | P16: =M16/M15-1 -> -0.0014256031 | Q16: =N16/N15-1 -> -0.0033166326 | R16: =O16/O15-1 -> -0.0029447315 | S16: =MAX(M$6:M16) -> 1.0533907 | T16: =MAX(N$6:N16) -> 1.0331502 | U16: =MAX(O$6:O16) -> 1.0411837 | V16: =M16/S16-1 -> -0.0054909269 | W16: =N16/T16-1 -> -0.011293405 | X16: =O16/U16-1 -> -0.0094423221 | Z16: 46142 | AA16: =VLOOKUP($Z16,$A$3:$O$1537,13,0) -> 2.0825817 | AB16: =VLOOKUP($Z16,$A$3:$O$1537,14,0) -> 1.2658054 | AC16: =VLOOKUP($Z16,$A$3:$O$1537,15,0) -> 1.4093525 | AD16: 2026年YTD | AE16: =AA16/AA15-1 -> 0.12620206 | AF16: =AB16/AB15-1 -> 0.060012787 | AG16: =AC16/AC15-1 -> 0.071488437
A17: 43847 | B17: =[1]!thsiFinD("ths_adjustment_nvg_ratio_fund",B$2,$A$6,$A17,101)/100 -> 0.017902813 | C17: =[1]!thsiFinD("ths_adjustment_nvg_ratio_fund",C$2,$A$6,$A17,101)/100 -> 0.018851533 | D17: =[1]!thsiFinD("ths_adjustment_nvg_ratio_fund",D$2,$A$6,$A17,101)/100 -> 0.063862928 | E17: =[1]!thsiFinD("ths_adjustment_nvg_ratio_fund",E$2,$A$6,$A17,101)/100 -> 0.041963314 | F17: =[1]!thsiFinD("ths_int_chg_ratio_index",F$1,$A$6,$A17,101)/100 -> 0.056112313 | G17: =[1]!thsiFinD("ths_int_chg_ratio_index",G$1,$A$6,$A17,101)/100 -> 0.056112313 | H17: =[1]!thsiFinD("ths_int_chg_ratio_index",H$1,$A$6,$A17,101)/100 -> 0.051928052 | I17: =[1]!thsiFinD("ths_int_chg_ratio_index",I$1,$A$6,$A17,101)/100 -> 0.051928052 | J17: =SUMPRODUCT(B17:I17,$B$4:$I$4) -> 0.044832665 | K17: =[1]!thsiFinD("ths_int_chg_ratio_index",K$2,$A$6,$A17,101)/100 -> 0.021769189 | L17: =[1]!thsiFinD("ths_int_chg_ratio_index",L$2,$A$6,$A17,101)/100 -> 0.030475459 | M17: =1+J17 -> 1.0448327 | N17: =1+K17 -> 1.0217692 | O17: =1+L17 -> 1.0304755 | P17: =M17/M16-1 -> -0.0026479131 | Q17: =N17/N16-1 -> 0.00028077224 | R17: =O17/O16-1 -> -0.00085038059 | S17: =MAX(M$6:M17) -> 1.0533907 | T17: =MAX(N$6:N17) -> 1.0331502 | U17: =MAX(O$6:O17) -> 1.0411837 | V17: =M17/S17-1 -> -0.0081243005 | W17: =N17/T17-1 -> -0.011015804 | X17: =O17/U17-1 -> -0.010284673
A18: 43850 | B18: =[1]!thsiFinD("ths_adjustment_nvg_ratio_fund",B$2,$A$6,$A18,101)/100 -> 0.02685422 | C18: =[1]!thsiFinD("ths_adjustment_nvg_ratio_fund",C$2,$A$6,$A18,101)/100 -> 0.027278256 | D18: =[1]!thsiFinD("ths_adjustment_nvg_ratio_fund",D$2,$A$6,$A18,101)/100 -> 0.081116703 | E18: =[1]!thsiFinD("ths_adjustment_nvg_ratio_fund",E$2,$A$6,$A18,101)/100 -> 0.054192143 | F18: =[1]!thsiFinD("ths_int_chg_ratio_index",F$1,$A$6,$A18,101)/100 -> 0.069666158 | G18: =[1]!thsiFinD("ths_int_chg_ratio_index",G$1,$A$6,$A18,101)/100 -> 0.069666158 | H18: =[1]!thsiFinD("ths_int_chg_ratio_index",H$1,$A$6,$A18,101)/100 -> 0.063850376 | I18: =[1]!thsiFinD("ths_int_chg_ratio_index",I$1,$A$6,$A18,101)/100 -> 0.063850376 | J18: =SUMPRODUCT(B18:I18,$B$4:$I$4) -> 0.057059299 | K18: =[1]!thsiFinD("ths_int_chg_ratio_index",K$2,$A$6,$A18,101)/100 -> 0.031028788 | L18: =[1]!thsiFinD("ths_int_chg_ratio_index",L$2,$A$6,$A18,101)/100 -> 0.040999609 | M18: =1+J18 -> 1.0570593 | N18: =1+K18 -> 1.0310288 | O18: =1+L18 -> 1.0409996 | P18: =M18/M17-1 -> 0.011702002 | Q18: =N18/N17-1 -> 0.0090623192 | R18: =O18/O17-1 -> 0.010212907 | S18: =MAX(M$6:M18) -> 1.0570593 | T18: =MAX(N$6:N18) -> 1.0331502 | U18: =MAX(O$6:O18) -> 1.0411837 | V18: =M18/S18-1 -> 0 | W18: =N18/T18-1 -> -0.0020533135 | X18: =O18/U18-1 -> -0.00017680237
A19: 43851 | B19: =[1]!thsiFinD("ths_adjustment_nvg_ratio_fund",B$2,$A$6,$A19,101)/100 -> 0.010629795 | C19: =[1]!thsiFinD("ths_adjustment_nvg_ratio_fund",C$2,$A$6,$A19,101)/100 -> 0.014420989 | D19: =[1]!thsiFinD("ths_adjustment_nvg_ratio_fund",D$2,$A$6,$A19,101)/100 -> 0.071171819 | E19: =[1]!thsiFinD("ths_adjustment_nvg_ratio_fund",E$2,$A$6,$A19,101)/100 -> 0.044894882 | F19: =[1]!thsiFinD("ths_int_chg_ratio_index",F$1,$A$6,$A19,101)/100 -> 0.060144371 | G19: =[1]!thsiFinD("ths_int_chg_ratio_index",G$1,$A$6,$A19,101)/100 -> 0.060144371 | H19: =[1]!thsiFinD("ths_int_chg_ratio_index",H$1,$A$6,$A19,101)/100 -> 0.052297572 | I19: =[1]!thsiFinD("ths_int_chg_ratio_index",I$1,$A$6,$A19,101)/100 -> 0.052297572 | J19: =SUMPRODUCT(B19:I19,$B$4:$I$4) -> 0.045750172 | K19: =[1]!thsiFinD("ths_int_chg_ratio_index",K$2,$A$6,$A19,101)/100 -> 0.014849996 | L19: =[1]!thsiFinD("ths_int_chg_ratio_index",L$2,$A$6,$A19,101)/100 -> 0.02653408 | M19: =1+J19 -> 1.0457502 | N19: =1+K19 -> 1.01485 | O19: =1+L19 -> 1.0265341 | P19: =M19/M18-1 -> -0.010698668 | Q19: =N19/N18-1 -> -0.015691892 | R19: =O19/O18-1 -> -0.013895806 | S19: =MAX(M$6:M19) -> 1.0570593 | T19: =MAX(N$6:N19) -> 1.0331502 | U19: =MAX(O$6:O19) -> 1.0411837 | V19: =M19/S19-1 -> -0.010698668 | W19: =N19/T19-1 -> -0.017712985 | X19: =O19/U19-1 -> -0.014070152
A20: 43852 | B20: =[1]!thsiFinD("ths_adjustment_nvg_ratio_fund",B$2,$A$6,$A20,101)/100 -> 0.016863811 | C20: =[1]!thsiFinD("ths_adjustment_nvg_ratio_fund",C$2,$A$6,$A20,101)/100 -> 0.01876466 | D20: =[1]!thsiFinD("ths_adjustment_nvg_ratio_fund",D$2,$A$6,$A20,101)/100 -> 0.079439252 | E20: =[1]!thsiFinD("ths_adjustment_nvg_ratio_fund",E$2,$A$6,$A20,101)/100 -> 0.052181925 | F20: =[1]!thsiFinD("ths_int_chg_ratio_index",F$1,$A$6,$A20,101)/100 -> 0.063328886 | G20: =[1]!thsiFinD("ths_int_chg_ratio_index",G$1,$A$6,$A20,101)/100 -> 0.063328886 | H20: =[1]!thsiFinD("ths_int_chg_ratio_index",H$1,$A$6,$A20,101)/100 -> 0.053532122 | I20: =[1]!thsiFinD("ths_int_chg_ratio_index",I$1,$A$6,$A20,101)/100 -> 0.053532122 | J20: =SUMPRODUCT(B20:I20,$B$4:$I$4) -> 0.050121458 | K20: =[1]!thsiFinD("ths_int_chg_ratio_index",K$2,$A$6,$A20,101)/100 -> 0.020455936 | L20: =[1]!thsiFinD("ths_int_chg_ratio_index",L$2,$A$6,$A20,101)/100 -> 0.031525585 | M20: =1+J20 -> 1.0501215 | N20: =1+K20 -> 1.0204559 | O20: =1+L20 -> 1.0315256 | P20: =M20/M19-1 -> 0.0041800486 | Q20: =N20/N19-1 -> 0.0055239099 | R20: =O20/O19-1 -> 0.0048624834 | S20: =MAX(M$6:M20) -> 1.0570593 | T20: =MAX(N$6:N20) -> 1.0331502 | U20: =MAX(O$6:O20) -> 1.0411837 | V20: =M20/S20-1 -> -0.0065633409 | W20: =N20/T20-1 -> -0.01228692 | X20: =O20/U20-1 -> -0.0092760844
A21: 43853 | B21: =[1]!thsiFinD("ths_adjustment_nvg_ratio_fund",B$2,$A$6,$A21,101)/100 -> -0.011828645 | C21: =[1]!thsiFinD("ths_adjustment_nvg_ratio_fund",C$2,$A$6,$A21,101)/100 -> -0.01216228 | D21: =[1]!thsiFinD("ths_adjustment_nvg_ratio_fund",D$2,$A$6,$A21,101)/100 -> 0.045650611 | E21: =[1]!thsiFinD("ths_adjustment_nvg_ratio_fund",E$2,$A$6,$A21,101)/100 -> 0.017756931 | F21: =[1]!thsiFinD("ths_int_chg_ratio_index",F$1,$A$6,$A21,101)/100 -> 0.023706578 | G21: =[1]!thsiFinD("ths_int_chg_ratio_index",G$1,$A$6,$A21,101)/100 -> 0.023706578 | H21: =[1]!thsiFinD("ths_int_chg_ratio_index",H$1,$A$6,$A21,101)/100 -> 0.017149102 | I21: =[1]!thsiFinD("ths_int_chg_ratio_index",I$1,$A$6,$A21,101)/100 -> 0.017149102 | J21: =SUMPRODUCT(B21:I21,$B$4:$I$4) -> 0.015140997 | K21: =[1]!thsiFinD("ths_int_chg_ratio_index",K$2,$A$6,$A21,101)/100 -> -0.012291666 | L21: =[1]!thsiFinD("ths_int_chg_ratio_index",L$2,$A$6,$A21,101)/100 -> -0.0024796862 | M21: =1+J21 -> 1.015141 | N21: =1+K21 -> 0.98770833 | O21: =1+L21 -> 0.99752031 | P21: =M21/M20-1 -> -0.033310872 | Q21: =N21/N20-1 -> -0.032091147 | R21: =O21/O20-1 -> -0.032965999 | S21: =MAX(M$6:M21) -> 1.0570593 | T21: =MAX(N$6:N21) -> 1.0331502 | U21: =MAX(O$6:O21) -> 1.0411837 | V21: =M21/S21-1 -> -0.039655582 | W21: =N21/T21-1 -> -0.043983766 | X21: =O21/U21-1 -> -0.041936288
A22: 43864 | B22: =[1]!thsiFinD("ths_adjustment_nvg_ratio_fund",B$2,$A$6,$A22,101)/100 -> -0.08519821 | C22: =[1]!thsiFinD("ths_adjustment_nvg_ratio_fund",C$2,$A$6,$A22,101)/100 -> -0.086265311 | D22: =[1]!thsiFinD("ths_adjustment_nvg_ratio_fund",D$2,$A$6,$A22,101)/100 -> -0.038221903 | E22: =[1]!thsiFinD("ths_adjustment_nvg_ratio_fund",E$2,$A$6,$A22,101)/100 -> -0.065248346 | F22: =[1]!thsiFinD("ths_int_chg_ratio_index",F$1,$A$6,$A22,101)/100 -> -0.065900561 | G22: =[1]!thsiFinD("ths_int_chg_ratio_index",G$1,$A$6,$A22,101)/100 -> -0.065900561 | H22: =[1]!thsiFinD("ths_int_chg_ratio_index",H$1,$A$6,$A22,101)/100 -> -0.073102335 | I22: =[1]!thsiFinD("ths_int_chg_ratio_index",I$1,$A$6,$A22,101)/100 -> -0.073102335 | J22: =SUMPRODUCT(B22:I22,$B$4:$I$4) -> -0.069117445 | K22: =[1]!thsiFinD("ths_int_chg_ratio_index",K$2,$A$6,$A22,101)/100 -> -0.092072933 | L22: =[1]!thsiFinD("ths_int_chg_ratio_index",L$2,$A$6,$A22,101)/100 -> -0.084114115 | M22: =1+J22 -> 0.93088255 | N22: =1+K22 -> 0.90792707 | O22: =1+L22 -> 0.91588588 | P22: =M22/M21-1 -> -0.083001714 | Q22: =N22/N21-1 -> -0.080774116 | R22: =O22/O21-1 -> -0.08183736 | S22: =MAX(M$6:M22) -> 1.0570593 | T22: =MAX(N$6:N22) -> 1.0331502 | U22: =MAX(O$6:O22) -> 1.0411837 | V22: =M22/S22-1 -> -0.11936581 | W22: =N22/T22-1 -> -0.12120513 | X22: =O22/U22-1 -> -0.12034169
A23: 43865 | B23: =[1]!thsiFinD("ths_adjustment_nvg_ratio_fund",B$2,$A$6,$A23,101)/100 -> -0.058024297 | C23: =[1]!thsiFinD("ths_adjustment_nvg_ratio_fund",C$2,$A$6,$A23,101)/100 -> -0.060898271 | D23: =[1]!thsiFinD("ths_adjustment_nvg_ratio_fund",D$2,$A$6,$A23,101)/100 -> -0.023484304 | E23: =[1]!thsiFinD("ths_adjustment_nvg_ratio_fund",E$2,$A$6,$A23,101)/100 -> -0.044978641 | F23: =[1]!thsiFinD("ths_int_chg_ratio_index",F$1,$A$6,$A23,101)/100 -> -0.063756223 | G23: =[1]!thsiFinD("ths_int_chg_ratio_index",G$1,$A$6,$A23,101)/100 -> -0.063756223 | H23: =[1]!thsiFinD("ths_int_chg_ratio_index",H$1,$A$6,$A23,101)/100 -> -0.081791735 | I23: =[1]!thsiFinD("ths_int_chg_ratio_index",I$1,$A$6,$A23,101)/100 -> -0.081791735 | J23: =SUMPRODUCT(B23:I23,$B$4:$I$4) -> -0.059810179 | K23: =[1]!thsiFinD("ths_int_chg_ratio_index",K$2,$A$6,$A23,101)/100 -> -0.070109495 | L23: =[1]!thsiFinD("ths_int_chg_ratio_index",L$2,$A$6,$A23,101)/100 -> -0.068254514 | M23: =1+J23 -> 0.94018982 | N23: =1+K23 -> 0.92989051 | O23: =1+L23 -> 0.93174549 | P23: =M23/M22-1 -> 0.0099983254 | Q23: =N23/N22-1 -> 0.024190752 | R23: =O23/O22-1 -> 0.017316132 | S23: =MAX(M$6:M23) -> 1.0570593 | T23: =MAX(N$6:N23) -> 1.0331502 | U23: =MAX(O$6:O23) -> 1.0411837 | V23: =M23/S23-1 -> -0.11056095 | W23: =N23/T23-1 -> -0.099946423 | X23: =O23/U23-1 -> -0.10510941
A24: 43866 | B24: =[1]!thsiFinD("ths_adjustment_nvg_ratio_fund",B$2,$A$6,$A24,101)/100 -> -0.045875959 | C24: =[1]!thsiFinD("ths_adjustment_nvg_ratio_fund",C$2,$A$6,$A24,101)/100 -> -0.050299713 | D24: =[1]!thsiFinD("ths_adjustment_nvg_ratio_fund",D$2,$A$6,$A24,101)/100 -> 0.0014378145 | E24: =[1]!thsiFinD("ths_adjustment_nvg_ratio_fund",E$2,$A$6,$A24,101)/100 -> -0.025881565 | F24: =[1]!thsiFinD("ths_int_chg_ratio_index",F$1,$A$6,$A24,101)/100 -> -0.039283439 | G24: =[1]!thsiFinD("ths_int_chg_ratio_index",G$1,$A$6,$A24,101)/100 -> -0.039283439 | H24: =[1]!thsiFinD("ths_int_chg_ratio_index",H$1,$A$6,$A24,101)/100 -> -0.052948809 | I24: =[1]!thsiFinD("ths_int_chg_ratio_index",I$1,$A$6,$A24,101)/100 -> -0.052948809 | J24: =SUMPRODUCT(B24:I24,$B$4:$I$4) -> -0.03813549 | K24: =[1]!thsiFinD("ths_int_chg_ratio_index",K$2,$A$6,$A24,101)/100 -> -0.056376283 | L24: =[1]!thsiFinD("ths_int_chg_ratio_index",L$2,$A$6,$A24,101)/100 -> -0.050462412 | M24: =1+J24 -> 0.96186451 | N24: =1+K24 -> 0.94362372 | O24: =1+L24 -> 0.94953759 | P24: =M24/M23-1 -> 0.023053524 | Q24: =N24/N23-1 -> 0.014768633 | R24: =O24/O23-1 -> 0.019095454 | S24: =MAX(M$6:M24) -> 1.0570593 | T24: =MAX(N$6:N24) -> 1.0331502 | U24: =MAX(O$6:O24) -> 1.0411837 | V24: =M24/S24-1 -> -0.090056242 | W24: =N24/T24-1 -> -0.086653862 | X24: =O24/U24-1 -> -0.088021072
A25: 43867 | B25: =[1]!thsiFinD("ths_adjustment_nvg_ratio_fund",B$2,$A$6,$A25,101)/100 -> -0.027893223 | C25: =[1]!thsiFinD("ths_adjustment_nvg_ratio_fund",C$2,$A$6,$A25,101)/100 -> -0.036747459 | D25: =[1]!thsiFinD("ths_adjustment_nvg_ratio_fund",D$2,$A$6,$A25,101)/100 -> 0.031991373 | E25: =[1]!thsiFinD("ths_adjustment_nvg_ratio_fund",E$2,$A$6,$A25,101)/100 -> -0.0039366781 | F25: =[1]!thsiFinD("ths_int_chg_ratio_index",F$1,$A$6,$A25,101)/100 -> -0.0092314703 | G25: =[1]!thsiFinD("ths_int_chg_ratio_index",G$1,$A$6,$A25,101)/100 -> -0.0092314703 | H25: =[1]!thsiFinD("ths_int_chg_ratio_index",H$1,$A$6,$A25,101)/100 -> -0.025116236 | I25: =[1]!thsiFinD("ths_int_chg_ratio_index",I$1,$A$6,$A25,101)/100 -> -0.025116236 | J25: =SUMPRODUCT(B25:I25,$B$4:$I$4) -> -0.013160175 | K25: =[1]!thsiFinD("ths_int_chg_ratio_index",K$2,$A$6,$A25,101)/100 -> -0.035947016 | L25: =[1]!thsiFinD("ths_int_chg_ratio_index",L$2,$A$6,$A25,101)/100 -> -0.027428722 | M25: =1+J25 -> 0.98683983 | N25: =1+K25 -> 0.96405298 | O25: =1+L25 -> 0.97257128 | P25: =M25/M24-1 -> 0.025965523 | Q25: =N25/N24-1 -> 0.021649803 | R25: =O25/O24-1 -> 0.024257796 | S25: =MAX(M$6:M25) -> 1.0570593 | T25: =MAX(N$6:N25) -> 1.0331502 | U25: =MAX(O$6:O25) -> 1.0411837 | V25: =M25/S25-1 -> -0.066429077 | W25: =N25/T25-1 -> -0.066880098 | X25: =O25/U25-1 -> -0.065898473
A26: 43868 | B26: =[1]!thsiFinD("ths_adjustment_nvg_ratio_fund",B$2,$A$6,$A26,101)/100 -> -0.028452685 | C26: =[1]!thsiFinD("ths_adjustment_nvg_ratio_fund",C$2,$A$6,$A26,101)/100 -> -0.036486839 | D26: =[1]!thsiFinD("ths_adjustment_nvg_ratio_fund",D$2,$A$6,$A26,101)/100 -> 0.038102085 | E26: =[1]!thsiFinD("ths_adjustment_nvg_ratio_fund",E$2,$A$6,$A26,101)/100 -> 0.0054443421 | F26: =[1]!thsiFinD("ths_int_chg_ratio_index",F$1,$A$6,$A26,101)/100 -> 0.0029751036 | G26: =[1]!thsiFinD("ths_int_chg_ratio_index",G$1,$A$6,$A26,101)/100 -> 0.0029751036 | H26: =[1]!thsiFinD("ths_int_chg_ratio_index",H$1,$A$6,$A26,101)/100 -> -0.011039864 | I26: =[1]!thsiFinD("ths_int_chg_ratio_index",I$1,$A$6,$A26,101)/100 -> -0.011039864 | J26: =SUMPRODUCT(B26:I26,$B$4:$I$4) -> -0.0046903274 | K26: =[1]!thsiFinD("ths_int_chg_ratio_index",K$2,$A$6,$A26,101)/100 -> -0.033937519 | L26: =[1]!thsiFinD("ths_int_chg_ratio_index",L$2,$A$6,$A26,101)/100 -> -0.022869361 | M26: =1+J26 -> 0.99530967 | N26: =1+K26 -> 0.96606248 | O26: =1+L26 -> 0.97713064 | P26: =M26/M25-1 -> 0.0085827988 | Q26: =N26/N25-1 -> 0.002084426 | R26: =O26/O25-1 -> 0.0046879458 | S26: =MAX(M$6:M26) -> 1.0570593 | T26: =MAX(N$6:N26) -> 1.0331502 | U26: =MAX(O$6:O26) -> 1.0411837 | V26: =M26/S26-1 -> -0.058416426 | W26: =N26/T26-1 -> -0.064935079 | X26: =O26/U26-1 -> -0.061519455
A27: 43871 | B27: =[1]!thsiFinD("ths_adjustment_nvg_ratio_fund",B$2,$A$6,$A27,101)/100 -> -0.023737212 | C27: =[1]!thsiFinD("ths_adjustment_nvg_ratio_fund",C$2,$A$6,$A27,101)/100 -> -0.0317088 | D27: =[1]!thsiFinD("ths_adjustment_nvg_ratio_fund",D$2,$A$6,$A27,101)/100 -> 0.04852624 | E27: =[1]!thsiFinD("ths_adjustment_nvg_ratio_fund",E$2,$A$6,$A27,101)/100 -> 0.017924449 | F27: =[1]!thsiFinD("ths_int_chg_ratio_index",F$1,$A$6,$A27,101)/100 -> 0.016980158 | G27: =[1]!thsiFinD("ths_int_chg_ratio_index",G$1,$A$6,$A27,101)/100 -> 0.016980158 | H27: =[1]!thsiFinD("ths_int_chg_ratio_index",H$1,$A$6,$A27,101)/100 -> 0.004110808 | I27: =[1]!thsiFinD("ths_int_chg_ratio_index",I$1,$A$6,$A27,101)/100 -> 0.004110808 | J27: =SUMPRODUCT(B27:I27,$B$4:$I$4) -> 0.0066483261 | K27: =[1]!thsiFinD("ths_int_chg_ratio_index",K$2,$A$6,$A27,101)/100 -> -0.028164465 | L27: =[1]!thsiFinD("ths_int_chg_ratio_index",L$2,$A$6,$A27,101)/100 -> -0.014554704 | M27: =1+J27 -> 1.0066483 | N27: =1+K27 -> 0.97183553 | O27: =1+L27 -> 0.9854453 | P27: =M27/M26-1 -> 0.011392086 | Q27: =N27/N26-1 -> 0.0059758591 | R27: =O27/O26-1 -> 0.0085092577 | S27: =MAX(M$6:M27) -> 1.0570593 | T27: =MAX(N$6:N27) -> 1.0331502 | U27: =MAX(O$6:O27) -> 1.0411837 | V27: =M27/S27-1 -> -0.047689824 | W27: =N27/T27-1 -> -0.059347263 | X27: =O27/U27-1 -> -0.053533683
A28: 43872 | B28: =[1]!thsiFinD("ths_adjustment_nvg_ratio_fund",B$2,$A$6,$A28,101)/100 -> -0.013107417 | C28: =[1]!thsiFinD("ths_adjustment_nvg_ratio_fund",C$2,$A$6,$A28,101)/100 -> -0.020241508 | D28: =[1]!thsiFinD("ths_adjustment_nvg_ratio_fund",D$2,$A$6,$A28,101)/100 -> 0.049964055 | E28: =[1]!thsiFinD("ths_adjustment_nvg_ratio_fund",E$2,$A$6,$A28,101)/100 -> 0.019934668 | F28: =[1]!thsiFinD("ths_int_chg_ratio_index",F$1,$A$6,$A28,101)/100 -> 0.010099743 | G28: =[1]!thsiFinD("ths_int_chg_ratio_index",G$1,$A$6,$A28,101)/100 -> 0.010099743 | H28: =[1]!thsiFinD("ths_int_chg_ratio_index",H$1,$A$6,$A28,101)/100 -> -0.0043569009 | I28: =[1]!thsiFinD("ths_int_chg_ratio_index",I$1,$A$6,$A28,101)/100 -> -0.0043569009 | J28: =SUMPRODUCT(B28:I28,$B$4:$I$4) -> 0.0060044351 | K28: =[1]!thsiFinD("ths_int_chg_ratio_index",K$2,$A$6,$A28,101)/100 -> -0.022605972 | L28: =[1]!thsiFinD("ths_int_chg_ratio_index",L$2,$A$6,$A28,101)/100 -> -0.01278862 | M28: =1+J28 -> 1.0060044 | N28: =1+K28 -> 0.97739403 | O28: =1+L28 -> 0.98721138 | P28: =M28/M27-1 -> -0.0006396385 | Q28: =N28/N27-1 -> 0.0057195827 | R28: =O28/O27-1 -> 0.0017921684 | S28: =MAX(M$6:M28) -> 1.0570593 | T28: =MAX(N$6:N28) -> 1.0331502 | U28: =MAX(O$6:O28) -> 1.0411837 | V28: =M28/S28-1 -> -0.048298959 | W28: =N28/T28-1 -> -0.053967122 | X28: =O28/U28-1 -> -0.051837456
... A831: 45077 | B831: =[1]!thsiFinD("ths_adjustment_nvg_ratio_fund",B$2,$A$6,$A831,101)/100 -> 0.13746803 | C831: =[1]!thsiFinD("ths_adjustment_nvg_ratio_fund",C$2,$A$6,$A831,101)/100 -> 0.091217097 | D831: =[1]!thsiFinD("ths_adjustment_nvg_ratio_fund",D$2,$A$6,$A831,101)/100 -> 0.44152888 | E831: =[1]!thsiFinD("ths_adjustment_nvg_ratio_fund",E$2,$A$6,$A831,101)/100 -> 0.51210319 | F831: =[1]!thsiFinD("ths_int_chg_ratio_index",F$1,$A$6,$A831,101)/100 -> 0.17866172 | G831: =[1]!thsiFinD("ths_int_chg_ratio_index",G$1,$A$6,$A831,101)/100 -> 0.17866172 | H831: =[1]!thsiFinD("ths_int_chg_ratio_index",H$1,$A$6,$A831,101)/100 -> 0.32285617 | I831: =[1]!thsiFinD("ths_int_chg_ratio_index",I$1,$A$6,$A831,101)/100 -> 0.32285617 | J831: =SUMPRODUCT(B831:I831,$B$4:$I$4) -> 0.27316912 | K831: =[1]!thsiFinD("ths_int_chg_ratio_index",K$2,$A$6,$A831,101)/100 -> -0.023724883 | L831: =[1]!thsiFinD("ths_int_chg_ratio_index",L$2,$A$6,$A831,101)/100 -> 0.06992449 | M831: =1+J831 -> 1.2731691 | N831: =1+K831 -> 0.97627512 | O831: =1+L831 -> 1.0699245 | P831: =M831/M830-1 -> -0.0023619928 | Q831: =N831/N830-1 -> -0.0081146978 | R831: =O831/O830-1 -> -0.0054617658 | S831: =MAX(M$6:M831) -> 1.5715177 | T831: =MAX(N$6:N831) -> 1.37911 | U831: =MAX(O$6:O831) -> 1.3429133 | V831: =M831/S831-1 -> -0.18984741 | W831: =N831/T831-1 -> -0.29209773 | X831: =O831/U831-1 -> -0.20328105
A832: 45078 | B832: =[1]!thsiFinD("ths_adjustment_nvg_ratio_fund",B$2,$A$6,$A832,101)/100 -> 0.13954604 | C832: =[1]!thsiFinD("ths_adjustment_nvg_ratio_fund",C$2,$A$6,$A832,101)/100 -> 0.095647641 | D832: =[1]!thsiFinD("ths_adjustment_nvg_ratio_fund",D$2,$A$6,$A832,101)/100 -> 0.43913252 | E832: =[1]!thsiFinD("ths_adjustment_nvg_ratio_fund",E$2,$A$6,$A832,101)/100 -> 0.50967418 | F832: =(1+F$831)*(1+[1]!thsiFinD("ths_adjustment_nvg_ratio_fund",F$2,$A$832,$A832,101)/100)-1 -> 0.17866172 | G832: =(1+G$831)*(1+[1]!thsiFinD("ths_adjustment_nvg_ratio_fund",G$2,$A$832,$A832,101)/100)-1 -> 0.18417677 | H832: =[1]!thsiFinD("ths_int_chg_ratio_index",H$1,$A$6,$A832,101)/100 -> 0.32837327 | I832: =[1]!thsiFinD("ths_int_chg_ratio_index",I$1,$A$6,$A832,101)/100 -> 0.32837327 | J832: =SUMPRODUCT(B832:I832,$B$4:$I$4) -> 0.27544818 | K832: =[1]!thsiFinD("ths_int_chg_ratio_index",K$2,$A$6,$A832,101)/100 -> -0.021995412 | L832: =[1]!thsiFinD("ths_int_chg_ratio_index",L$2,$A$6,$A832,101)/100 -> 0.072195404 | M832: =1+J832 -> 1.2754482 | N832: =1+K832 -> 0.97800459 | O832: =1+L832 -> 1.0721954 | P832: =M832/M831-1 -> 0.0017900632 | Q832: =N832/N831-1 -> 0.0017714998 | R832: =O832/O831-1 -> 0.0021224996 | S832: =MAX(M$6:M832) -> 1.5715177 | T832: =MAX(N$6:N832) -> 1.37911 | U832: =MAX(O$6:O832) -> 1.3429133 | V832: =M832/S832-1 -> -0.18839719 | W832: =N832/T832-1 -> -0.29084368 | X832: =O832/U832-1 -> -0.20159002
A833: 45079 | B833: =[1]!thsiFinD("ths_adjustment_nvg_ratio_fund",B$2,$A$6,$A833,101)/100 -> 0.15329284 | C833: =[1]!thsiFinD("ths_adjustment_nvg_ratio_fund",C$2,$A$6,$A833,101)/100 -> 0.110503 | D833: =[1]!thsiFinD("ths_adjustment_nvg_ratio_fund",D$2,$A$6,$A833,101)/100 -> 0.44739995 | E833: =[1]!thsiFinD("ths_adjustment_nvg_ratio_fund",E$2,$A$6,$A833,101)/100 -> 0.51805009 | F833: =(1+F$831)*(1+[1]!thsiFinD("ths_adjustment_nvg_ratio_fund",F$2,$A$832,$A833,101)/100)-1 -> 0.17889745 | G833: =(1+G$831)*(1+[1]!thsiFinD("ths_adjustment_nvg_ratio_fund",G$2,$A$832,$A833,101)/100)-1 -> 0.19352837 | H833: =[1]!thsiFinD("ths_int_chg_ratio_index",H$1,$A$6,$A833,101)/100 -> 0.33594654 | I833: =[1]!thsiFinD("ths_int_chg_ratio_index",I$1,$A$6,$A833,101)/100 -> 0.33594654 | J833: =SUMPRODUCT(B833:I833,$B$4:$I$4) -> 0.2841956 | K833: =[1]!thsiFinD("ths_int_chg_ratio_index",K$2,$A$6,$A833,101)/100 -> -0.0093108778 | L833: =[1]!thsiFinD("ths_int_chg_ratio_index",L$2,$A$6,$A833,101)/100 -> 0.0838705 | M833: =1+J833 -> 1.2841956 | N833: =1+K833 -> 0.99068912 | O833: =1+L833 -> 1.0838705 | P833: =M833/M832-1 -> 0.006858312 | Q833: =N833/N832-1 -> 0.01296981 | R833: =O833/O832-1 -> 0.010888963 | S833: =MAX(M$6:M833) -> 1.5715177 | T833: =MAX(N$6:N833) -> 1.37911 | U833: =MAX(O$6:O833) -> 1.3429133 | V833: =M833/S833-1 -> -0.18283096 | W833: =N833/T833-1 -> -0.28164606 | X833: =O833/U833-1 -> -0.19289616
A834: 45082 | B834: =[1]!thsiFinD("ths_adjustment_nvg_ratio_fund",B$2,$A$6,$A834,101)/100 -> 0.14785806 | C834: =[1]!thsiFinD("ths_adjustment_nvg_ratio_fund",C$2,$A$6,$A834,101)/100 -> 0.10685431 | D834: =[1]!thsiFinD("ths_adjustment_nvg_ratio_fund",D$2,$A$6,$A834,101)/100 -> 0.44200815 | E834: =[1]!thsiFinD("ths_adjustment_nvg_ratio_fund",E$2,$A$6,$A834,101)/100 -> 0.51930647 | F834: =(1+F$831)*(1+[1]!thsiFinD("ths_adjustment_nvg_ratio_fund",F$2,$A$832,$A834,101)/100)-1 -> 0.17889745 | G834: =(1+G$831)*(1+[1]!thsiFinD("ths_adjustment_nvg_ratio_fund",G$2,$A$832,$A834,101)/100)-1 -> 0.19280902 | H834: =[1]!thsiFinD("ths_int_chg_ratio_index",H$1,$A$6,$A834,101)/100 -> 0.34490774 | I834: =[1]!thsiFinD("ths_int_chg_ratio_index",I$1,$A$6,$A834,101)/100 -> 0.34490774 | J834: =SUMPRODUCT(B834:I834,$B$4:$I$4) -> 0.28469362 | K834: =[1]!thsiFinD("ths_int_chg_ratio_index",K$2,$A$6,$A834,101)/100 -> -0.012980617 | L834: =[1]!thsiFinD("ths_int_chg_ratio_index",L$2,$A$6,$A834,101)/100 -> 0.082606224 | M834: =1+J834 -> 1.2846936 | N834: =1+K834 -> 0.98701938 | O834: =1+L834 -> 1.0826062 | P834: =M834/M833-1 -> 0.00038780751 | Q834: =N834/N833-1 -> -0.0037042286 | R834: =O834/O833-1 -> -0.0011664454 | S834: =MAX(M$6:M834) -> 1.5715177 | T834: =MAX(N$6:N834) -> 1.37911 | U834: =MAX(O$6:O834) -> 1.3429133 | V834: =M834/S834-1 -> -0.18251406 | W834: =N834/T834-1 -> -0.284307 | X834: =O834/U834-1 -> -0.1938376
A835: 45083 | B835: =[1]!thsiFinD("ths_adjustment_nvg_ratio_fund",B$2,$A$6,$A835,101)/100 -> 0.13650895 | C835: =[1]!thsiFinD("ths_adjustment_nvg_ratio_fund",C$2,$A$6,$A835,101)/100 -> 0.097037616 | D835: =[1]!thsiFinD("ths_adjustment_nvg_ratio_fund",D$2,$A$6,$A835,101)/100 -> 0.41361131 | E835: =[1]!thsiFinD("ths_adjustment_nvg_ratio_fund",E$2,$A$6,$A835,101)/100 -> 0.49535137 | F835: =(1+F$831)*(1+[1]!thsiFinD("ths_adjustment_nvg_ratio_fund",F$2,$A$832,$A835,101)/100)-1 -> 0.17877959 | G835: =(1+G$831)*(1+[1]!thsiFinD("ths_adjustment_nvg_ratio_fund",G$2,$A$832,$A835,101)/100)-1 -> 0.16679238 | H835: =[1]!thsiFinD("ths_int_chg_ratio_index",H$1,$A$6,$A835,101)/100 -> 0.31619342 | I835: =[1]!thsiFinD("ths_int_chg_ratio_index",I$1,$A$6,$A835,101)/100 -> 0.31619342 | J835: =SUMPRODUCT(B835:I835,$B$4:$I$4) -> 0.26505851 | K835: =[1]!thsiFinD("ths_int_chg_ratio_index",K$2,$A$6,$A835,101)/100 -> -0.0246581 | L835: =[1]!thsiFinD("ths_int_chg_ratio_index",L$2,$A$6,$A835,101)/100 -> 0.066491363 | M835: =1+J835 -> 1.2650585 | N835: =1+K835 -> 0.9753419 | O835: =1+L835 -> 1.0664914 | P835: =M835/M834-1 -> -0.015283887 | Q835: =N835/N834-1 -> -0.011831058 | R835: =O835/O834-1 -> -0.014885247 | S835: =MAX(M$6:M835) -> 1.5715177 | T835: =MAX(N$6:N835) -> 1.37911 | U835: =MAX(O$6:O835) -> 1.3429133 | V835: =M835/S835-1 -> -0.19500842 | W835: =N835/T835-1 -> -0.29277441 | X835: =O835/U835-1 -> -0.20583753
A836: 45084 | B836: =[1]!thsiFinD("ths_adjustment_nvg_ratio_fund",B$2,$A$6,$A836,101)/100 -> 0.13251279 | C836: =[1]!thsiFinD("ths_adjustment_nvg_ratio_fund",C$2,$A$6,$A836,101)/100 -> 0.094257667 | D836: =[1]!thsiFinD("ths_adjustment_nvg_ratio_fund",D$2,$A$6,$A836,101)/100 -> 0.41780494 | E836: =[1]!thsiFinD("ths_adjustment_nvg_ratio_fund",E$2,$A$6,$A836,101)/100 -> 0.49786414 | F836: =(1+F$831)*(1+[1]!thsiFinD("ths_adjustment_nvg_ratio_fund",F$2,$A$832,$A836,101)/100)-1 -> 0.17807239 | G836: =(1+G$831)*(1+[1]!thsiFinD("ths_adjustment_nvg_ratio_fund",G$2,$A$832,$A836,101)/100)-1 -> 0.17038915 | H836: =[1]!thsiFinD("ths_int_chg_ratio_index",H$1,$A$6,$A836,101)/100 -> 0.32604296 | I836: =[1]!thsiFinD("ths_int_chg_ratio_index",I$1,$A$6,$A836,101)/100 -> 0.32604296 | J836: =SUMPRODUCT(B836:I836,$B$4:$I$4) -> 0.26787337 | K836: =[1]!thsiFinD("ths_int_chg_ratio_index",K$2,$A$6,$A836,101)/100 -> -0.028061463 | L836: =[1]!thsiFinD("ths_int_chg_ratio_index",L$2,$A$6,$A836,101)/100 -> 0.065474481 | M836: =1+J836 -> 1.2678734 | N836: =1+K836 -> 0.97193854 | O836: =1+L836 -> 1.0654745 | P836: =M836/M835-1 -> 0.0022250895 | Q836: =N836/N835-1 -> -0.0034894047 | R836: =O836/O835-1 -> -0.00095348422 | S836: =MAX(M$6:M836) -> 1.5715177 | T836: =MAX(N$6:N836) -> 1.37911 | U836: =MAX(O$6:O836) -> 1.3429133 | V836: =M836/S836-1 -> -0.19321724 | W836: =N836/T836-1 -> -0.2952422 | X836: =O836/U836-1 -> -0.20659475
A837: 45085 | B837: =[1]!thsiFinD("ths_adjustment_nvg_ratio_fund",B$2,$A$6,$A837,101)/100 -> 0.14098465 | C837: =[1]!thsiFinD("ths_adjustment_nvg_ratio_fund",C$2,$A$6,$A837,101)/100 -> 0.10094692 | D837: =[1]!thsiFinD("ths_adjustment_nvg_ratio_fund",D$2,$A$6,$A837,101)/100 -> 0.41301222 | E837: =[1]!thsiFinD("ths_adjustment_nvg_ratio_fund",E$2,$A$6,$A837,101)/100 -> 0.49551889 | F837: =(1+F$831)*(1+[1]!thsiFinD("ths_adjustment_nvg_ratio_fund",F$2,$A$832,$A837,101)/100)-1 -> 0.17323988 | G837: =(1+G$831)*(1+[1]!thsiFinD("ths_adjustment_nvg_ratio_fund",G$2,$A$832,$A837,101)/100)-1 -> 0.16343539 | H837: =[1]!thsiFinD("ths_int_chg_ratio_index",H$1,$A$6,$A837,101)/100 -> 0.31778774 | I837: =[1]!thsiFinD("ths_int_chg_ratio_index",I$1,$A$6,$A837,101)/100 -> 0.31778774 | J837: =SUMPRODUCT(B837:I837,$B$4:$I$4) -> 0.26533918 | K837: =[1]!thsiFinD("ths_int_chg_ratio_index",K$2,$A$6,$A837,101)/100 -> -0.023123906 | L837: =[1]!thsiFinD("ths_int_chg_ratio_index",L$2,$A$6,$A837,101)/100 -> 0.066468586 | M837: =1+J837 -> 1.2653392 | N837: =1+K837 -> 0.97687609 | O837: =1+L837 -> 1.0664686 | P837: =M837/M836-1 -> -0.0019987767 | Q837: =N837/N836-1 -> 0.005080112 | R837: =O837/O836-1 -> 0.00093301676 | S837: =MAX(M$6:M837) -> 1.5715177 | T837: =MAX(N$6:N837) -> 1.37911 | U837: =MAX(O$6:O837) -> 1.3429133 | V837: =M837/S837-1 -> -0.19482982 | W837: =N837/T837-1 -> -0.29166196 | X837: =O837/U837-1 -> -0.20585449
A838: 45086 | B838: =[1]!thsiFinD("ths_adjustment_nvg_ratio_fund",B$2,$A$6,$A838,101)/100 -> 0.14673913 | C838: =[1]!thsiFinD("ths_adjustment_nvg_ratio_fund",C$2,$A$6,$A838,101)/100 -> 0.10572496 | D838: =[1]!thsiFinD("ths_adjustment_nvg_ratio_fund",D$2,$A$6,$A838,101)/100 -> 0.42331656 | E838: =[1]!thsiFinD("ths_adjustment_nvg_ratio_fund",E$2,$A$6,$A838,101)/100 -> 0.50188458 | F838: =(1+F$831)*(1+[1]!thsiFinD("ths_adjustment_nvg_ratio_fund",F$2,$A$832,$A838,101)/100)-1 -> 0.17936892 | G838: =(1+G$831)*(1+[1]!thsiFinD("ths_adjustment_nvg_ratio_fund",G$2,$A$832,$A838,101)/100)-1 -> 0.172787 | H838: =[1]!thsiFinD("ths_int_chg_ratio_index",H$1,$A$6,$A838,101)/100 -> 0.32635104 | I838: =[1]!thsiFinD("ths_int_chg_ratio_index",I$1,$A$6,$A838,101)/100 -> 0.32635104 | J838: =SUMPRODUCT(B838:I838,$B$4:$I$4) -> 0.2728154 | K838: =[1]!thsiFinD("ths_int_chg_ratio_index",K$2,$A$6,$A838,101)/100 -> -0.018146733 | L838: =[1]!thsiFinD("ths_int_chg_ratio_index",L$2,$A$6,$A838,101)/100 -> 0.072637236 | M838: =1+J838 -> 1.2728154 | N838: =1+K838 -> 0.98185327 | O838: =1+L838 -> 1.0726372 | P838: =M838/M837-1 -> 0.0059084745 | Q838: =N838/N837-1 -> 0.0050949891 | R838: =O838/O837-1 -> 0.0057841833 | S838: =MAX(M$6:M838) -> 1.5715177 | T838: =MAX(N$6:N838) -> 1.37911 | U838: =MAX(O$6:O838) -> 1.3429133 | V838: =M838/S838-1 -> -0.19007249 | W838: =N838/T838-1 -> -0.28805298 | X838: =O838/U838-1 -> -0.20126101
A839: 45089 | B839: =[1]!thsiFinD("ths_adjustment_nvg_ratio_fund",B$2,$A$6,$A839,101)/100 -> 0.14857737 | C839: =[1]!thsiFinD("ths_adjustment_nvg_ratio_fund",C$2,$A$6,$A839,101)/100 -> 0.11171923 | D839: =[1]!thsiFinD("ths_adjustment_nvg_ratio_fund",D$2,$A$6,$A839,101)/100 -> 0.42930745 | E839: =[1]!thsiFinD("ths_adjustment_nvg_ratio_fund",E$2,$A$6,$A839,101)/100 -> 0.51151688 | F839: =(1+F$831)*(1+[1]!thsiFinD("ths_adjustment_nvg_ratio_fund",F$2,$A$832,$A839,101)/100)-1 -> 0.18974114 | G839: =(1+G$831)*(1+[1]!thsiFinD("ths_adjustment_nvg_ratio_fund",G$2,$A$832,$A839,101)/100)-1 -> 0.18022032 | H839: =[1]!thsiFinD("ths_int_chg_ratio_index",H$1,$A$6,$A839,101)/100 -> 0.33779926 | I839: =[1]!thsiFinD("ths_int_chg_ratio_index",I$1,$A$6,$A839,101)/100 -> 0.33779926 | J839: =SUMPRODUCT(B839:I839,$B$4:$I$4) -> 0.28083511 | K839: =[1]!thsiFinD("ths_int_chg_ratio_index",K$2,$A$6,$A839,101)/100 -> -0.015907765 | L839: =[1]!thsiFinD("ths_int_chg_ratio_index",L$2,$A$6,$A839,101)/100 -> 0.076604925 | M839: =1+J839 -> 1.2808351 | N839: =1+K839 -> 0.98409224 | O839: =1+L839 -> 1.0766049 | P839: =M839/M838-1 -> 0.006300765 | Q839: =N839/N838-1 -> 0.0022803491 | R839: =O839/O838-1 -> 0.0036990037 | S839: =MAX(M$6:M839) -> 1.5715177 | T839: =MAX(N$6:N839) -> 1.37911 | U839: =MAX(O$6:O839) -> 1.3429133 | V839: =M839/S839-1 -> -0.18496933 | W839: =N839/T839-1 -> -0.28642949 | X839: =O839/U839-1 -> -0.19830647
A840: 45090 | B840: =[1]!thsiFinD("ths_adjustment_nvg_ratio_fund",B$2,$A$6,$A840,101)/100 -> 0.15265345 | C840: =[1]!thsiFinD("ths_adjustment_nvg_ratio_fund",C$2,$A$6,$A840,101)/100 -> 0.11823473 | D840: =[1]!thsiFinD("ths_adjustment_nvg_ratio_fund",D$2,$A$6,$A840,101)/100 -> 0.43469926 | E840: =[1]!thsiFinD("ths_adjustment_nvg_ratio_fund",E$2,$A$6,$A840,101)/100 -> 0.51545356 | F840: =(1+F$831)*(1+[1]!thsiFinD("ths_adjustment_nvg_ratio_fund",F$2,$A$832,$A840,101)/100)-1 -> 0.19457365 | G840: =(1+G$831)*(1+[1]!thsiFinD("ths_adjustment_nvg_ratio_fund",G$2,$A$832,$A840,101)/100)-1 -> 0.18429666 | H840: =[1]!thsiFinD("ths_int_chg_ratio_index",H$1,$A$6,$A840,101)/100 -> 0.34455729 | I840: =[1]!thsiFinD("ths_int_chg_ratio_index",I$1,$A$6,$A840,101)/100 -> 0.34455729 | J840: =SUMPRODUCT(B840:I840,$B$4:$I$4) -> 0.28612824 | K840: =[1]!thsiFinD("ths_int_chg_ratio_index",K$2,$A$6,$A840,101)/100 -> -0.011349941 | L840: =[1]!thsiFinD("ths_int_chg_ratio_index",L$2,$A$6,$A840,101)/100 -> 0.081370659 | M840: =1+J840 -> 1.2861282 | N840: =1+K840 -> 0.98865006 | O840: =1+L840 -> 1.0813707 | P840: =M840/M839-1 -> 0.0041325552 | Q840: =N840/N839-1 -> 0.0046315005 | R840: =O840/O839-1 -> 0.0044266317 | S840: =MAX(M$6:M840) -> 1.5715177 | T840: =MAX(N$6:N840) -> 1.37911 | U840: =MAX(O$6:O840) -> 1.3429133 | V840: =M840/S840-1 -> -0.18160117 | W840: =N840/T840-1 -> -0.28312459 | X840: =O840/U840-1 -> -0.19475767
A841: 45091 | B841: =[1]!thsiFinD("ths_adjustment_nvg_ratio_fund",B$2,$A$6,$A841,101)/100 -> 0.15393223 | C841: =[1]!thsiFinD("ths_adjustment_nvg_ratio_fund",C$2,$A$6,$A841,101)/100 -> 0.12214404 | D841: =[1]!thsiFinD("ths_adjustment_nvg_ratio_fund",D$2,$A$6,$A841,101)/100 -> 0.43266235 | E841: =[1]!thsiFinD("ths_adjustment_nvg_ratio_fund",E$2,$A$6,$A841,101)/100 -> 0.51570483 | F841: =(1+F$831)*(1+[1]!thsiFinD("ths_adjustment_nvg_ratio_fund",F$2,$A$832,$A841,101)/100)-1 -> 0.19917044 | G841: =(1+G$831)*(1+[1]!thsiFinD("ths_adjustment_nvg_ratio_fund",G$2,$A$832,$A841,101)/100)-1 -> 0.18873268 | H841: =[1]!thsiFinD("ths_int_chg_ratio_index",H$1,$A$6,$A841,101)/100 -> 0.34767479 | I841: =[1]!thsiFinD("ths_int_chg_ratio_index",I$1,$A$6,$A841,101)/100 -> 0.34767479 | J841: =SUMPRODUCT(B841:I841,$B$4:$I$4) -> 0.28846202 | K841: =[1]!thsiFinD("ths_int_chg_ratio_index",K$2,$A$6,$A841,101)/100 -> -0.01151425 | L841: =[1]!thsiFinD("ths_int_chg_ratio_index",L$2,$A$6,$A841,101)/100 -> 0.082304899 | M841: =1+J841 -> 1.288462 | N841: =1+K841 -> 0.98848575 | O841: =1+L841 -> 1.0823049 | P841: =M841/M840-1 -> 0.0018145794 | Q841: =N841/N840-1 -> -0.00016619495 | R841: =O841/O840-1 -> 0.00086394109 | S841: =MAX(M$6:M841) -> 1.5715177 | T841: =MAX(N$6:N841) -> 1.37911 | U841: =MAX(O$6:O841) -> 1.3429133 | V841: =M841/S841-1 -> -0.18011612 | W841: =N841/T841-1 -> -0.28324373 | X841: =O841/U841-1 -> -0.19406199
A842: 45092 | B842: =[1]!thsiFinD("ths_adjustment_nvg_ratio_fund",B$2,$A$6,$A842,101)/100 -> 0.17047634 | C842: =[1]!thsiFinD("ths_adjustment_nvg_ratio_fund",C$2,$A$6,$A842,101)/100 -> 0.13465381 | D842: =[1]!thsiFinD("ths_adjustment_nvg_ratio_fund",D$2,$A$6,$A842,101)/100 -> 0.44224778 | E842: =[1]!thsiFinD("ths_adjustment_nvg_ratio_fund",E$2,$A$6,$A842,101)/100 -> 0.52692855 | F842: =(1+F$831)*(1+[1]!thsiFinD("ths_adjustment_nvg_ratio_fund",F$2,$A$832,$A842,101)/100)-1 -> 0.21048559 | G842: =(1+G$831)*(1+[1]!thsiFinD("ths_adjustment_nvg_ratio_fund",G$2,$A$832,$A842,101)/100)-1 -> 0.19568644 | H842: =[1]!thsiFinD("ths_int_chg_ratio_index",H$1,$A$6,$A842,101)/100 -> 0.35108719 | I842: =[1]!thsiFinD("ths_int_chg_ratio_index",I$1,$A$6,$A842,101)/100 -> 0.35108719 | J842: =SUMPRODUCT(B842:I842,$B$4:$I$4) -> 0.29783161 | K842: =[1]!thsiFinD("ths_int_chg_ratio_index",K$2,$A$6,$A842,101)/100 -> 0.0023312662 | L842: =[1]!thsiFinD("ths_int_chg_ratio_index",L$2,$A$6,$A842,101)/100 -> 0.093685159 | M842: =1+J842 -> 1.2978316 | N842: =1+K842 -> 1.0023313 | O842: =1+L842 -> 1.0936852 | P842: =M842/M841-1 -> 0.0072719211 | Q842: =N842/N841-1 -> 0.014006794 | R842: =O842/O841-1 -> 0.010514837 | S842: =MAX(M$6:M842) -> 1.5715177 | T842: =MAX(N$6:N842) -> 1.37911 | U842: =MAX(O$6:O842) -> 1.3429133 | V842: =M842/S842-1 -> -0.17415399 | W842: =N842/T842-1 -> -0.27320427 | X842: =O842/U842-1 -> -0.18558768
A843: 45093 | B843: =[1]!thsiFinD("ths_adjustment_nvg_ratio_fund",B$2,$A$6,$A843,101)/100 -> 0.18222506 | C843: =[1]!thsiFinD("ths_adjustment_nvg_ratio_fund",C$2,$A$6,$A843,101)/100 -> 0.14542611 | D843: =[1]!thsiFinD("ths_adjustment_nvg_ratio_fund",D$2,$A$6,$A843,101)/100 -> 0.45075485 | E843: =[1]!thsiFinD("ths_adjustment_nvg_ratio_fund",E$2,$A$6,$A843,101)/100 -> 0.53212162 | F843: =(1+F$831)*(1+[1]!thsiFinD("ths_adjustment_nvg_ratio_fund",F$2,$A$832,$A843,101)/100)-1 -> 0.21967915 | G843: =(1+G$831)*(1+[1]!thsiFinD("ths_adjustment_nvg_ratio_fund",G$2,$A$832,$A843,101)/100)-1 -> 0.20479825 | H843: =[1]!thsiFinD("ths_int_chg_ratio_index",H$1,$A$6,$A843,101)/100 -> 0.36394797 | I843: =[1]!thsiFinD("ths_int_chg_ratio_index",I$1,$A$6,$A843,101)/100 -> 0.36394797 | J843: =SUMPRODUCT(B843:I843,$B$4:$I$4) -> 0.30786262 | K843: =[1]!thsiFinD("ths_int_chg_ratio_index",K$2,$A$6,$A843,101)/100 -> 0.011667784 | L843: =[1]!thsiFinD("ths_int_chg_ratio_index",L$2,$A$6,$A843,101)/100 -> 0.10340993 | M843: =1+J843 -> 1.3078626 | N843: =1+K843 -> 1.0116678 | O843: =1+L843 -> 1.1034099 | P843: =M843/M842-1 -> 0.007729055 | Q843: =N843/N842-1 -> 0.0093148022 | R843: =O843/O842-1 -> 0.0088917478 | S843: =MAX(M$6:M843) -> 1.5715177 | T843: =MAX(N$6:N843) -> 1.37911 | U843: =MAX(O$6:O843) -> 1.3429133 | V843: =M843/S843-1 -> -0.16777098 | W843: =N843/T843-1 -> -0.26643432 | X843: =O843/U843-1 -> -0.17834613
... A997: 45322 | B997: =[1]!thsiFinD("ths_adjustment_nvg_ratio_fund",B$2,$A$6,$A997,101)/100 -> -0.019661125 | C997: =[1]!thsiFinD("ths_adjustment_nvg_ratio_fund",C$2,$A$6,$A997,101)/100 -> -0.017722179 | D997: =[1]!thsiFinD("ths_adjustment_nvg_ratio_fund",D$2,$A$6,$A997,101)/100 -> 0.11718188 | E997: =[1]!thsiFinD("ths_adjustment_nvg_ratio_fund",E$2,$A$6,$A997,101)/100 -> 0.23357044 | F997: =(1+F$831)*(1+[1]!thsiFinD("ths_adjustment_nvg_ratio_fund",F$2,$A$832,$A997,101)/100)-1 -> -0.046344801 | G997: =(1+G$831)*(1+[1]!thsiFinD("ths_adjustment_nvg_ratio_fund",G$2,$A$832,$A997,101)/100)-1 -> -0.063400939 | H997: =[1]!thsiFinD("ths_int_chg_ratio_index",H$1,$A$6,$A997,101)/100 -> 0.032936249 | I997: =[1]!thsiFinD("ths_int_chg_ratio_index",I$1,$A$6,$A997,101)/100 -> 0.032936249 | J997: =SUMPRODUCT(B997:I997,$B$4:$I$4) -> 0.033686972 | K997: =[1]!thsiFinD("ths_int_chg_ratio_index",K$2,$A$6,$A997,101)/100 -> -0.19201534 | L997: =[1]!thsiFinD("ths_int_chg_ratio_index",L$2,$A$6,$A997,101)/100 -> -0.13899791 | M997: =1+J997 -> 1.033687 | N997: =1+K997 -> 0.80798466 | O997: =1+L997 -> 0.86100209 | P997: =M997/M996-1 -> -0.033575741 | Q997: =N997/N996-1 -> -0.013085494 | R997: =O997/O996-1 -> -0.02440173 | S997: =MAX(M$6:M997) -> 1.5715177 | T997: =MAX(N$6:N997) -> 1.37911 | U997: =MAX(O$6:O997) -> 1.3429133 | V997: =M997/S997-1 -> -0.3422365 | W997: =N997/T997-1 -> -0.41412603 | X997: =O997/U997-1 -> -0.35885506
A998: 45323 | B998: =[1]!thsiFinD("ths_adjustment_nvg_ratio_fund",B$2,$A$6,$A998,101)/100 -> -0.018702046 | C998: =[1]!thsiFinD("ths_adjustment_nvg_ratio_fund",C$2,$A$6,$A998,101)/100 -> -0.019980888 | D998: =[1]!thsiFinD("ths_adjustment_nvg_ratio_fund",D$2,$A$6,$A998,101)/100 -> 0.10951354 | E998: =[1]!thsiFinD("ths_adjustment_nvg_ratio_fund",E$2,$A$6,$A998,101)/100 -> 0.22760441 | F998: =(1+F$831)*(1+[1]!thsiFinD("ths_adjustment_nvg_ratio_fund",F$2,$A$832,$A998,101)/100)-1 -> -0.060253009 | G998: =(1+G$831)*(1+[1]!thsiFinD("ths_adjustment_nvg_ratio_fund",G$2,$A$832,$A998,101)/100)-1 -> -0.072153081 | H998: =(1+H$997)*(1+[1]!thsiFinD("ths_adjustment_nvg_ratio_fund",H$2,$A$998,$A998,101)/100)-1 -> 0.032936249 | I998: =(1+I$997)*(1+[1]!thsiFinD("ths_adjustment_nvg_ratio_fund",I$2,$A$998,$A998,101)/100)-1 -> 0.016207555 | J998: =SUMPRODUCT(B998:I998,$B$4:$I$4) -> 0.026896591 | K998: =[1]!thsiFinD("ths_int_chg_ratio_index",K$2,$A$6,$A998,101)/100 -> -0.19236798 | L998: =[1]!thsiFinD("ths_int_chg_ratio_index",L$2,$A$6,$A998,101)/100 -> -0.14292112 | M998: =1+J998 -> 1.0268966 | N998: =1+K998 -> 0.80763202 | O998: =1+L998 -> 0.85707888 | P998: =M998/M997-1 -> -0.0065690886 | Q998: =N998/N997-1 -> -0.00043644915 | R998: =O998/O997-1 -> -0.0045565528 | S998: =MAX(M$6:M998) -> 1.5715177 | T998: =MAX(N$6:N998) -> 1.37911 | U998: =MAX(O$6:O998) -> 1.3429133 | V998: =M998/S998-1 -> -0.34655741 | W998: =N998/T998-1 -> -0.41438173 | X998: =O998/U998-1 -> -0.36177647
A999: 45324 | B999: =[1]!thsiFinD("ths_adjustment_nvg_ratio_fund",B$2,$A$6,$A999,101)/100 -> -0.037963555 | C999: =[1]!thsiFinD("ths_adjustment_nvg_ratio_fund",C$2,$A$6,$A999,101)/100 -> -0.038398054 | D999: =[1]!thsiFinD("ths_adjustment_nvg_ratio_fund",D$2,$A$6,$A999,101)/100 -> 0.083153607 | E999: =[1]!thsiFinD("ths_adjustment_nvg_ratio_fund",E$2,$A$6,$A999,101)/100 -> 0.18966417 | F999: =(1+F$831)*(1+[1]!thsiFinD("ths_adjustment_nvg_ratio_fund",F$2,$A$832,$A999,101)/100)-1 -> -0.10350989 | G999: =(1+G$831)*(1+[1]!thsiFinD("ths_adjustment_nvg_ratio_fund",G$2,$A$832,$A999,101)/100)-1 -> -0.10860036 | H999: =(1+H$997)*(1+[1]!thsiFinD("ths_adjustment_nvg_ratio_fund",H$2,$A$998,$A999,101)/100)-1 -> -0.034698944 | I999: =(1+I$997)*(1+[1]!thsiFinD("ths_adjustment_nvg_ratio_fund",I$2,$A$998,$A999,101)/100)-1 -> -0.026947627 | J999: =SUMPRODUCT(B999:I999,$B$4:$I$4) -> -0.0096625818 | K999: =[1]!thsiFinD("ths_int_chg_ratio_index",K$2,$A$6,$A999,101)/100 -> -0.20454725 | L999: =[1]!thsiFinD("ths_int_chg_ratio_index",L$2,$A$6,$A999,101)/100 -> -0.16321002 | M999: =1+J999 -> 0.99033742 | N999: =1+K999 -> 0.79545275 | O999: =1+L999 -> 0.83678998 | P999: =M999/M998-1 -> -0.035601611 | Q999: =N999/N998-1 -> -0.015080219 | R999: =O999/O998-1 -> -0.023672149 | S999: =MAX(M$6:M999) -> 1.5715177 | T999: =MAX(N$6:N999) -> 1.37911 | U999: =MAX(O$6:O999) -> 1.3429133 | V999: =M999/S999-1 -> -0.36982102 | W999: =N999/T999-1 -> -0.42321299 | X999: =O999/U999-1 -> -0.37688459
A1000: 45327 | B1000: =[1]!thsiFinD("ths_adjustment_nvg_ratio_fund",B$2,$A$6,$A1000,101)/100 -> -0.050271739 | C1000: =[1]!thsiFinD("ths_adjustment_nvg_ratio_fund",C$2,$A$6,$A1000,101)/100 -> -0.047693511 | D1000: =[1]!thsiFinD("ths_adjustment_nvg_ratio_fund",D$2,$A$6,$A1000,101)/100 -> 0.063263839 | E1000: =[1]!thsiFinD("ths_adjustment_nvg_ratio_fund",E$2,$A$6,$A1000,101)/100 -> 0.1409105 | F1000: =(1+F$831)*(1+[1]!thsiFinD("ths_adjustment_nvg_ratio_fund",F$2,$A$832,$A1000,101)/100)-1 -> -0.18200877 | G1000: =(1+G$831)*(1+[1]!thsiFinD("ths_adjustment_nvg_ratio_fund",G$2,$A$832,$A1000,101)/100)-1 -> -0.16411052 | H1000: =(1+H$997)*(1+[1]!thsiFinD("ths_adjustment_nvg_ratio_fund",H$2,$A$998,$A1000,101)/100)-1 -> -0.034698944 | I1000: =(1+I$997)*(1+[1]!thsiFinD("ths_adjustment_nvg_ratio_fund",I$2,$A$998,$A1000,101)/100)-1 -> -0.11434899 | J1000: =SUMPRODUCT(B1000:I1000,$B$4:$I$4) -> -0.048619766 | K1000: =[1]!thsiFinD("ths_int_chg_ratio_index",K$2,$A$6,$A1000,101)/100 -> -0.20513238 | L1000: =[1]!thsiFinD("ths_int_chg_ratio_index",L$2,$A$6,$A1000,101)/100 -> -0.18527444 | M1000: =1+J1000 -> 0.95138023 | N1000: =1+K1000 -> 0.79486762 | O1000: =1+L1000 -> 0.81472556 | P1000: =M1000/M999-1 -> -0.039337284 | Q1000: =N1000/N999-1 -> -0.00073559421 | R1000: =O1000/O999-1 -> -0.026367939 | S1000: =MAX(M$6:M1000) -> 1.5715177 | T1000: =MAX(N$6:N1000) -> 1.37911 | U1000: =MAX(O$6:O1000) -> 1.3429133 | V1000: =M1000/S1000-1 -> -0.39461055 | W1000: =N1000/T1000-1 -> -0.42363727 | X1000: =O1000/U1000-1 -> -0.39331486
A1001: 45328 | B1001: =[1]!thsiFinD("ths_adjustment_nvg_ratio_fund",B$2,$A$6,$A1001,101)/100 -> -0.017423274 | C1001: =[1]!thsiFinD("ths_adjustment_nvg_ratio_fund",C$2,$A$6,$A1001,101)/100 -> -0.013812875 | D1001: =[1]!thsiFinD("ths_adjustment_nvg_ratio_fund",D$2,$A$6,$A1001,101)/100 -> 0.13898874 | E1001: =[1]!thsiFinD("ths_adjustment_nvg_ratio_fund",E$2,$A$6,$A1001,101)/100 -> 0.21483337 | F1001: =(1+F$831)*(1+[1]!thsiFinD("ths_adjustment_nvg_ratio_fund",F$2,$A$832,$A1001,101)/100)-1 -> -0.14782758 | G1001: =(1+G$831)*(1+[1]!thsiFinD("ths_adjustment_nvg_ratio_fund",G$2,$A$832,$A1001,101)/100)-1 -> -0.11555411 | H1001: =(1+H$997)*(1+[1]!thsiFinD("ths_adjustment_nvg_ratio_fund",H$2,$A$998,$A1001,101)/100)-1 -> -0.034698944 | I1001: =(1+I$997)*(1+[1]!thsiFinD("ths_adjustment_nvg_ratio_fund",I$2,$A$998,$A1001,101)/100)-1 -> -0.099681079 | J1001: =SUMPRODUCT(B1001:I1001,$B$4:$I$4) -> -0.0093969691 | K1001: =[1]!thsiFinD("ths_int_chg_ratio_index",K$2,$A$6,$A1001,101)/100 -> -0.16919275 | L1001: =[1]!thsiFinD("ths_int_chg_ratio_index",L$2,$A$6,$A1001,101)/100 -> -0.14940969 | M1001: =1+J1001 -> 0.99060303 | N1001: =1+K1001 -> 0.83080725 | O1001: =1+L1001 -> 0.85059031 | P1001: =M1001/M1000-1 -> 0.041227257 | Q1001: =N1001/N1000-1 -> 0.045214611 | R1001: =O1001/O1000-1 -> 0.044020655 | S1001: =MAX(M$6:M1001) -> 1.5715177 | T1001: =MAX(N$6:N1001) -> 1.37911 | U1001: =MAX(O$6:O1001) -> 1.3429133 | V1001: =M1001/S1001-1 -> -0.369652 | W1001: =N1001/T1001-1 -> -0.39757725 | X1001: =O1001/U1001-1 -> -0.36660818
A1002: 45329 | B1002: =[1]!thsiFinD("ths_adjustment_nvg_ratio_fund",B$2,$A$6,$A1002,101)/100 -> -0.0079923274 | C1002: =[1]!thsiFinD("ths_adjustment_nvg_ratio_fund",C$2,$A$6,$A1002,101)/100 -> -0.0065155069 | D1002: =[1]!thsiFinD("ths_adjustment_nvg_ratio_fund",D$2,$A$6,$A1002,101)/100 -> 0.2090822 | E1002: =[1]!thsiFinD("ths_adjustment_nvg_ratio_fund",E$2,$A$6,$A1002,101)/100 -> 0.27551911 | F1002: =(1+F$831)*(1+[1]!thsiFinD("ths_adjustment_nvg_ratio_fund",F$2,$A$832,$A1002,101)/100)-1 -> -0.12401861 | G1002: =(1+G$831)*(1+[1]!thsiFinD("ths_adjustment_nvg_ratio_fund",G$2,$A$832,$A1002,101)/100)-1 -> -0.077907914 | H1002: =(1+H$997)*(1+[1]!thsiFinD("ths_adjustment_nvg_ratio_fund",H$2,$A$998,$A1002,101)/100)-1 -> -0.034698944 | I1002: =(1+I$997)*(1+[1]!thsiFinD("ths_adjustment_nvg_ratio_fund",I$2,$A$998,$A1002,101)/100)-1 -> -0.12234967 | J1002: =SUMPRODUCT(B1002:I1002,$B$4:$I$4) -> 0.013889791 | K1002: =[1]!thsiFinD("ths_int_chg_ratio_index",K$2,$A$6,$A1002,101)/100 -> -0.1499768 | L1002: =[1]!thsiFinD("ths_int_chg_ratio_index",L$2,$A$6,$A1002,101)/100 -> -0.13446769 | M1002: =1+J1002 -> 1.0138898 | N1002: =1+K1002 -> 0.8500232 | O1002: =1+L1002 -> 0.86553231 | P1002: =M1002/M1001-1 -> 0.023507661 | Q1002: =N1002/N1001-1 -> 0.023129257 | R1002: =O1002/O1001-1 -> 0.017566629 | S1002: =MAX(M$6:M1002) -> 1.5715177 | T1002: =MAX(N$6:N1002) -> 1.37911 | U1002: =MAX(O$6:O1002) -> 1.3429133 | V1002: =M1002/S1002-1 -> -0.35483399 | W1002: =N1002/T1002-1 -> -0.38364366 | X1002: =O1002/U1002-1 -> -0.35548162
A1003: 45330 | B1003: =[1]!thsiFinD("ths_adjustment_nvg_ratio_fund",B$2,$A$6,$A1003,101)/100 -> 0.0025575448 | C1003: =[1]!thsiFinD("ths_adjustment_nvg_ratio_fund",C$2,$A$6,$A1003,101)/100 -> 0.012596647 | D1003: =[1]!thsiFinD("ths_adjustment_nvg_ratio_fund",D$2,$A$6,$A1003,101)/100 -> 0.21878744 | E1003: =[1]!thsiFinD("ths_adjustment_nvg_ratio_fund",E$2,$A$6,$A1003,101)/100 -> 0.30767975 | F1003: =(1+F$831)*(1+[1]!thsiFinD("ths_adjustment_nvg_ratio_fund",F$2,$A$832,$A1003,101)/100)-1 -> -0.065321255 | G1003: =(1+G$831)*(1+[1]!thsiFinD("ths_adjustment_nvg_ratio_fund",G$2,$A$832,$A1003,101)/100)-1 -> -0.037504191 | H1003: =(1+H$997)*(1+[1]!thsiFinD("ths_adjustment_nvg_ratio_fund",H$2,$A$998,$A1003,101)/100)-1 -> -0.029941728 | I1003: =(1+I$997)*(1+[1]!thsiFinD("ths_adjustment_nvg_ratio_fund",I$2,$A$998,$A1003,101)/100)-1 -> -0.042100429 | J1003: =SUMPRODUCT(B1003:I1003,$B$4:$I$4) -> 0.045844223 | K1003: =[1]!thsiFinD("ths_int_chg_ratio_index",K$2,$A$6,$A1003,101)/100 -> -0.14420884 | L1003: =[1]!thsiFinD("ths_int_chg_ratio_index",L$2,$A$6,$A1003,101)/100 -> -0.11438114 | M1003: =1+J1003 -> 1.0458442 | N1003: =1+K1003 -> 0.85579116 | O1003: =1+L1003 -> 0.88561886 | P1003: =M1003/M1002-1 -> 0.031516672 | Q1003: =N1003/N1002-1 -> 0.0067856478 | R1003: =O1003/O1002-1 -> 0.023207163 | S1003: =MAX(M$6:M1003) -> 1.5715177 | T1003: =MAX(N$6:N1003) -> 1.37911 | U1003: =MAX(O$6:O1003) -> 1.3429133 | V1003: =M1003/S1003-1 -> -0.33450051 | W1003: =N1003/T1003-1 -> -0.37946128 | X1003: =O1003/U1003-1 -> -0.34052418
A1004: 45341 | B1004: =[1]!thsiFinD("ths_adjustment_nvg_ratio_fund",B$2,$A$6,$A1004,101)/100 -> 0.014066496 | C1004: =[1]!thsiFinD("ths_adjustment_nvg_ratio_fund",C$2,$A$6,$A1004,101)/100 -> 0.028755104 | D1004: =[1]!thsiFinD("ths_adjustment_nvg_ratio_fund",D$2,$A$6,$A1004,101)/100 -> 0.2111191 | E1004: =[1]!thsiFinD("ths_adjustment_nvg_ratio_fund",E$2,$A$6,$A1004,101)/100 -> 0.31336612 | F1004: =(1+F$831)*(1+[1]!thsiFinD("ths_adjustment_nvg_ratio_fund",F$2,$A$832,$A1004,101)/100)-1 -> -0.054006102 | G1004: =(1+G$831)*(1+[1]!thsiFinD("ths_adjustment_nvg_ratio_fund",G$2,$A$832,$A1004,101)/100)-1 -> -0.027912802 | H1004: =(1+H$997)*(1+[1]!thsiFinD("ths_adjustment_nvg_ratio_fund",H$2,$A$998,$A1004,101)/100)-1 -> -0.029941728 | I1004: =(1+I$997)*(1+[1]!thsiFinD("ths_adjustment_nvg_ratio_fund",I$2,$A$998,$A1004,101)/100)-1 -> -0.010825045 | J1004: =SUMPRODUCT(B1004:I1004,$B$4:$I$4) -> 0.055577643 | K1004: =[1]!thsiFinD("ths_int_chg_ratio_index",K$2,$A$6,$A1004,101)/100 -> -0.13728749 | L1004: =[1]!thsiFinD("ths_int_chg_ratio_index",L$2,$A$6,$A1004,101)/100 -> -0.1019122 | M1004: =1+J1004 -> 1.0555776 | N1004: =1+K1004 -> 0.86271251 | O1004: =1+L1004 -> 0.8980878 | P1004: =M1004/M1003-1 -> 0.0093067594 | Q1004: =N1004/N1003-1 -> 0.0080876554 | R1004: =O1004/O1003-1 -> 0.014079353 | S1004: =MAX(M$6:M1004) -> 1.5715177 | T1004: =MAX(N$6:N1004) -> 1.37911 | U1004: =MAX(O$6:O1004) -> 1.3429133 | V1004: =M1004/S1004-1 -> -0.32830686 | W1004: =N1004/T1004-1 -> -0.37444258 | X1004: =O1004/U1004-1 -> -0.33123919
A1005: 45342 | B1005: =[1]!thsiFinD("ths_adjustment_nvg_ratio_fund",B$2,$A$6,$A1005,101)/100 -> 0.019261509 | C1005: =[1]!thsiFinD("ths_adjustment_nvg_ratio_fund",C$2,$A$6,$A1005,101)/100 -> 0.034315003 | D1005: =[1]!thsiFinD("ths_adjustment_nvg_ratio_fund",D$2,$A$6,$A1005,101)/100 -> 0.21183801 | E1005: =[1]!thsiFinD("ths_adjustment_nvg_ratio_fund",E$2,$A$6,$A1005,101)/100 -> 0.31821353 | F1005: =(1+F$831)*(1+[1]!thsiFinD("ths_adjustment_nvg_ratio_fund",F$2,$A$832,$A1005,101)/100)-1 -> -0.045637604 | G1005: =(1+G$831)*(1+[1]!thsiFinD("ths_adjustment_nvg_ratio_fund",G$2,$A$832,$A1005,101)/100)-1 -> -0.02419614 | H1005: =(1+H$997)*(1+[1]!thsiFinD("ths_adjustment_nvg_ratio_fund",H$2,$A$998,$A1005,101)/100)-1 -> -0.029941728 | I1005: =(1+I$997)*(1+[1]!thsiFinD("ths_adjustment_nvg_ratio_fund",I$2,$A$998,$A1005,101)/100)-1 -> 0.00081230779 | J1005: =SUMPRODUCT(B1005:I1005,$B$4:$I$4) -> 0.06058311 | K1005: =[1]!thsiFinD("ths_int_chg_ratio_index",K$2,$A$6,$A1005,101)/100 -> -0.13599312 | L1005: =[1]!thsiFinD("ths_int_chg_ratio_index",L$2,$A$6,$A1005,101)/100 -> -0.09826152 | M1005: =1+J1005 -> 1.0605831 | N1005: =1+K1005 -> 0.86400688 | O1005: =1+L1005 -> 0.90173848 | P1005: =M1005/M1004-1 -> 0.0047419219 | Q1005: =N1005/N1004-1 -> 0.0015003478 | R1005: =O1005/O1004-1 -> 0.004064943 | S1005: =MAX(M$6:M1005) -> 1.5715177 | T1005: =MAX(N$6:N1005) -> 1.37911 | U1005: =MAX(O$6:O1005) -> 1.3429133 | V1005: =M1005/S1005-1 -> -0.32512175 | W1005: =N1005/T1005-1 -> -0.37350403 | X1005: =O1005/U1005-1 -> -0.32852071
A1006: 45343 | B1006: =[1]!thsiFinD("ths_adjustment_nvg_ratio_fund",B$2,$A$6,$A1006,101)/100 -> 0.034526854 | C1006: =[1]!thsiFinD("ths_adjustment_nvg_ratio_fund",C$2,$A$6,$A1006,101)/100 -> 0.050560334 | D1006: =[1]!thsiFinD("ths_adjustment_nvg_ratio_fund",D$2,$A$6,$A1006,101)/100 -> 0.213156 | E1006: =[1]!thsiFinD("ths_adjustment_nvg_ratio_fund",E$2,$A$6,$A1006,101)/100 -> 0.32753545 | F1006: =(1+F$831)*(1+[1]!thsiFinD("ths_adjustment_nvg_ratio_fund",F$2,$A$832,$A1006,101)/100)-1 -> -0.033615254 | G1006: =(1+G$831)*(1+[1]!thsiFinD("ths_adjustment_nvg_ratio_fund",G$2,$A$832,$A1006,101)/100)-1 -> -0.018321414 | H1006: =(1+H$997)*(1+[1]!thsiFinD("ths_adjustment_nvg_ratio_fund",H$2,$A$998,$A1006,101)/100)-1 -> -0.029941728 | I1006: =(1+I$997)*(1+[1]!thsiFinD("ths_adjustment_nvg_ratio_fund",I$2,$A$998,$A1006,101)/100)-1 -> 0.01645 | J1006: =SUMPRODUCT(B1006:I1006,$B$4:$I$4) -> 0.070043781 | K1006: =[1]!thsiFinD("ths_int_chg_ratio_index",K$2,$A$6,$A1006,101)/100 -> -0.12743994 | L1006: =[1]!thsiFinD("ths_int_chg_ratio_index",L$2,$A$6,$A1006,101)/100 -> -0.088892404 | M1006: =1+J1006 -> 1.0700438 | N1006: =1+K1006 -> 0.87256006 | O1006: =1+L1006 -> 0.9111076 | P1006: =M1006/M1005-1 -> 0.008920254 | Q1006: =N1006/N1005-1 -> 0.0098994447 | R1006: =O1006/O1005-1 -> 0.010390059 | S1006: =MAX(M$6:M1006) -> 1.5715177 | T1006: =MAX(N$6:N1006) -> 1.37911 | U1006: =MAX(O$6:O1006) -> 1.3429133 | V1006: =M1006/S1006-1 -> -0.31910166 | W1006: =N1006/T1006-1 -> -0.36730206 | X1006: =O1006/U1006-1 -> -0.321544
A1007: 45344 | B1007: =[1]!thsiFinD("ths_adjustment_nvg_ratio_fund",B$2,$A$6,$A1007,101)/100 -> 0.045716113 | C1007: =[1]!thsiFinD("ths_adjustment_nvg_ratio_fund",C$2,$A$6,$A1007,101)/100 -> 0.062722613 | D1007: =[1]!thsiFinD("ths_adjustment_nvg_ratio_fund",D$2,$A$6,$A1007,101)/100 -> 0.22369998 | E1007: =[1]!thsiFinD("ths_adjustment_nvg_ratio_fund",E$2,$A$6,$A1007,101)/100 -> 0.34245053 | F1007: =(1+F$831)*(1+[1]!thsiFinD("ths_adjustment_nvg_ratio_fund",F$2,$A$832,$A1007,101)/100)-1 -> -0.013460139 | G1007: =(1+G$831)*(1+[1]!thsiFinD("ths_adjustment_nvg_ratio_fund",G$2,$A$832,$A1007,101)/100)-1 -> -0.0032149778 | H1007: =(1+H$997)*(1+[1]!thsiFinD("ths_adjustment_nvg_ratio_fund",H$2,$A$998,$A1007,101)/100)-1 -> -0.029941728 | I1007: =(1+I$997)*(1+[1]!thsiFinD("ths_adjustment_nvg_ratio_fund",I$2,$A$998,$A1007,101)/100)-1 -> 0.042149153 | J1007: =SUMPRODUCT(B1007:I1007,$B$4:$I$4) -> 0.083765193 | K1007: =[1]!thsiFinD("ths_int_chg_ratio_index",K$2,$A$6,$A1007,101)/100 -> -0.12022197 | L1007: =[1]!thsiFinD("ths_int_chg_ratio_index",L$2,$A$6,$A1007,101)/100 -> -0.077655185 | M1007: =1+J1007 -> 1.0837652 | N1007: =1+K1007 -> 0.87977803 | O1007: =1+L1007 -> 0.92234482 | P1007: =M1007/M1006-1 -> 0.012823225 | Q1007: =N1007/N1006-1 -> 0.008272169 | R1007: =O1007/O1006-1 -> 0.012333581 | S1007: =MAX(M$6:M1007) -> 1.5715177 | T1007: =MAX(N$6:N1007) -> 1.37911 | U1007: =MAX(O$6:O1007) -> 1.3429133 | V1007: =M1007/S1007-1 -> -0.31037035 | W1007: =N1007/T1007-1 -> -0.36206828 | X1007: =O1007/U1007-1 -> -0.31317621
A1008: 45345 | B1008: =[1]!thsiFinD("ths_adjustment_nvg_ratio_fund",B$2,$A$6,$A1008,101)/100 -> 0.053069054 | C1008: =[1]!thsiFinD("ths_adjustment_nvg_ratio_fund",C$2,$A$6,$A1008,101)/100 -> 0.071236209 | D1008: =[1]!thsiFinD("ths_adjustment_nvg_ratio_fund",D$2,$A$6,$A1008,101)/100 -> 0.22837287 | E1008: =[1]!thsiFinD("ths_adjustment_nvg_ratio_fund",E$2,$A$6,$A1008,101)/100 -> 0.35829781 | F1008: =(1+F$831)*(1+[1]!thsiFinD("ths_adjustment_nvg_ratio_fund",F$2,$A$832,$A1008,101)/100)-1 -> 0.0096416307 | G1008: =(1+G$831)*(1+[1]!thsiFinD("ths_adjustment_nvg_ratio_fund",G$2,$A$832,$A1008,101)/100)-1 -> 0.012251136 | H1008: =(1+H$997)*(1+[1]!thsiFinD("ths_adjustment_nvg_ratio_fund",H$2,$A$998,$A1008,101)/100)-1 -> -0.019289702 | I1008: =(1+I$997)*(1+[1]!thsiFinD("ths_adjustment_nvg_ratio_fund",I$2,$A$998,$A1008,101)/100)-1 -> 0.074879207 | J1008: =SUMPRODUCT(B1008:I1008,$B$4:$I$4) -> 0.098557277 | K1008: =[1]!thsiFinD("ths_int_chg_ratio_index",K$2,$A$6,$A1008,101)/100 -> -0.11871599 | L1008: =[1]!thsiFinD("ths_int_chg_ratio_index",L$2,$A$6,$A1008,101)/100 -> -0.069446081 | M1008: =1+J1008 -> 1.0985573 | N1008: =1+K1008 -> 0.88128401 | O1008: =1+L1008 -> 0.93055392 | P1008: =M1008/M1007-1 -> 0.01364879 | Q1008: =N1008/N1007-1 -> 0.0017117766 | R1008: =O1008/O1007-1 -> 0.0089002548 | S1008: =MAX(M$6:M1008) -> 1.5715177 | T1008: =MAX(N$6:N1008) -> 1.37911 | U1008: =MAX(O$6:O1008) -> 1.3429133 | V1008: =M1008/S1008-1 -> -0.30095774 | W1008: =N1008/T1008-1 -> -0.36097628 | X1008: =O1008/U1008-1 -> -0.30706331
A1009: 45348 | B1009: =[1]!thsiFinD("ths_adjustment_nvg_ratio_fund",B$2,$A$6,$A1009,101)/100 -> 0.049392583 | C1009: =[1]!thsiFinD("ths_adjustment_nvg_ratio_fund",C$2,$A$6,$A1009,101)/100 -> 0.067413778 | D1009: =[1]!thsiFinD("ths_adjustment_nvg_ratio_fund",D$2,$A$6,$A1009,101)/100 -> 0.22657561 | E1009: =[1]!thsiFinD("ths_adjustment_nvg_ratio_fund",E$2,$A$6,$A1009,101)/100 -> 0.3636113 | F1009: =(1+F$831)*(1+[1]!thsiFinD("ths_adjustment_nvg_ratio_fund",F$2,$A$832,$A1009,101)/100)-1 -> 0.017538664 | G1009: =(1+G$831)*(1+[1]!thsiFinD("ths_adjustment_nvg_ratio_fund",G$2,$A$832,$A1009,101)/100)-1 -> 0.016807045 | H1009: =(1+H$997)*(1+[1]!thsiFinD("ths_adjustment_nvg_ratio_fund",H$2,$A$998,$A1009,101)/100)-1 -> -0.019289702 | I1009: =(1+I$997)*(1+[1]!thsiFinD("ths_adjustment_nvg_ratio_fund",I$2,$A$998,$A1009,101)/100)-1 -> 0.094638462 | J1009: =SUMPRODUCT(B1009:I1009,$B$4:$I$4) -> 0.10208597 | K1009: =[1]!thsiFinD("ths_int_chg_ratio_index",K$2,$A$6,$A1009,101)/100 -> -0.12564243 | L1009: =[1]!thsiFinD("ths_int_chg_ratio_index",L$2,$A$6,$A1009,101)/100 -> -0.070620315 | M1009: =1+J1009 -> 1.102086 | N1009: =1+K1009 -> 0.87435757 | O1009: =1+L1009 -> 0.92937969 | P1009: =M1009/M1008-1 -> 0.0032121136 | Q1009: =N1009/N1008-1 -> -0.0078594858 | R1009: =O1009/O1008-1 -> -0.0012618655 | S1009: =MAX(M$6:M1009) -> 1.5715177 | T1009: =MAX(N$6:N1009) -> 1.37911 | U1009: =MAX(O$6:O1009) -> 1.3429133 | V1009: =M1009/S1009-1 -> -0.29871234 | W1009: =N1009/T1009-1 -> -0.36599868 | X1009: =O1009/U1009-1 -> -0.3079377
... A1620: 46265 | B1620: =[1]!thsiFinD("ths_adjustment_nvg_ratio_fund",B$2,$A$6,$A1620,101)/100 -> 0.67159527 | C1620: =[1]!thsiFinD("ths_adjustment_nvg_ratio_fund",C$2,$A$6,$A1620,101)/100 -> 0.66423421 | D1620: =[1]!thsiFinD("ths_adjustment_nvg_ratio_fund",D$2,$A$6,$A1620,101)/100 -> 1.1546849 | E1620: =[1]!thsiFinD("ths_adjustment_nvg_ratio_fund",E$2,$A$6,$A1620,101)/100 -> 1.4892338 | F1620: =(1+F$831)*(1+[1]!thsiFinD("ths_adjustment_nvg_ratio_fund",F$2,$A$832,$A1620,101)/100)-1 -> 1.0590042 | G1620: =(1+G$831)*(1+[1]!thsiFinD("ths_adjustment_nvg_ratio_fund",G$2,$A$832,$A1620,101)/100)-1 -> 0.90532927 | H1620: =(1+H$997)*(1+[1]!thsiFinD("ths_adjustment_nvg_ratio_fund",H$2,$A$998,$A1620,101)/100)-1 -> 1.0072346 | I1620: =(1+I$997)*(1+[1]!thsiFinD("ths_adjustment_nvg_ratio_fund",I$2,$A$998,$A1620,101)/100)-1 -> 1.321773 | J1620: =SUMPRODUCT(B1620:I1620,$B$4:$I$4) -> 1.0341362 | K1620: =[1]!thsiFinD("ths_int_chg_ratio_index",K$2,$A$6,$A1620,101)/100 -> 0.21416499 | L1620: =[1]!thsiFinD("ths_int_chg_ratio_index",L$2,$A$6,$A1620,101)/100 -> 0.32647974 | M1620: =1+J1620 -> 2.0341362 | N1620: =1+K1620 -> 1.214165 | O1620: =1+L1620 -> 1.3264797 | P1620: =M1620/M1619-1 -> 0.010989079 | Q1620: =N1620/N1619-1 -> 0.0044721127 | R1620: =O1620/O1619-1 -> 0.0057786234 | S1620: =MAX(M$6:M1620) -> 2.2221297 | T1620: =MAX(N$6:N1620) -> 1.37911 | U1620: =MAX(O$6:O1620) -> 1.4859285 | V1620: =M1620/S1620-1 -> -0.084600606 | W1620: =N1620/T1620-1 -> -0.11960252 | X1620: =O1620/U1620-1 -> -0.10730579

Sheet 产业趋势产品池
H1: 46174 | I1: 46113 | J1: 46023 | K1: 45813 | L1: 45448 | M1: 45082 | N1: 45658 | O1: 45292 | P1: 44927 | Q1: 44562 | R1: 44197 | S1: 43831 | T1: 43466
H2: =M2 -> 46177 | I2: 46177 | J2: 46177 | K2: =J2 -> 46177 | L2: =K2 -> 46177 | M2: =L2 -> 46177 | N2: 46022 | O2: 45657 | P2: 45291 | Q2: 44926 | R2: 44561 | S2: 44196 | T2: 43830
A3: 十五五投资线 | B3: 指数/主动 | C3: 投资线 | D3: 产业趋势观察池 | E3: =K2 -> 46177 | F3: 基金经理 | G3: 重仓方向 | H3: 6月以来 | I3: Q2以来 | J3: 2026YTD | K3: 近1年 | L3: 近2年 | M3: 近3年 | N3: 2025年 | O3: 2024年 | P3: 2023年 | Q3: 2022年 | R3: 2021年 | S3: 2020年 | T3: 2019年 | U3: 成立日期 | V3: 申万前三大行业占比
D4: 932381.CSI | E4: 科创创业50等权指数 | F4: 基准指数 | H4: =[1]!thsiFinD("ths_int_chg_ratio_index",$D4,H$1,H$2,101) -> 0.030608028 | I4: =[1]!thsiFinD("ths_int_chg_ratio_index",$D4,I$1,I$2,101) -> 31.270374 | J4: =[1]!thsiFinD("ths_int_chg_ratio_index",$D4,J$1,J$2,101) -> 25.685326 | K4: =[1]!thsiFinD("ths_int_chg_ratio_index",$D4,K$1,K$2,101) -> 89.018639 | L4: =[1]!thsiFinD("ths_int_chg_ratio_index",$D4,L$1,L$2,101) -> 104.15275 | M4: =[1]!thsiFinD("ths_int_chg_ratio_index",$D4,M$1,M$2,101) -> 59.22683 | N4: =[1]!thsiFinD("ths_int_chg_ratio_index",$D4,N$1,N$2,101) -> 41.194122 | O4: =[1]!thsiFinD("ths_int_chg_ratio_index",$D4,O$1,O$2,101) -> 5.2329716 | ... T4: =[1]!thsiFinD("ths_int_chg_ratio_index",$D4,T$1,T$2,101) -> 0
D5: 931187.CSI | E5: 科技100 | H5: =[1]!thsiFinD("ths_int_chg_ratio_index",$D5,H$1,H$2,101) -> -0.15832134 | I5: =[1]!thsiFinD("ths_int_chg_ratio_index",$D5,I$1,I$2,101) -> 14.444511 | J5: =[1]!thsiFinD("ths_int_chg_ratio_index",$D5,J$1,J$2,101) -> 13.311774 | K5: =[1]!thsiFinD("ths_int_chg_ratio_index",$D5,K$1,K$2,101) -> 70.619457 | L5: =[1]!thsiFinD("ths_int_chg_ratio_index",$D5,L$1,L$2,101) -> 88.488106 | M5: =[1]!thsiFinD("ths_int_chg_ratio_index",$D5,M$1,M$2,101) -> 63.304818 | N5: =[1]!thsiFinD("ths_int_chg_ratio_index",$D5,N$1,N$2,101) -> 48.320998 | O5: =[1]!thsiFinD("ths_int_chg_ratio_index",$D5,O$1,O$2,101) -> 12.253018 | ... T5: =[1]!thsiFinD("ths_int_chg_ratio_index",$D5,T$1,T$2,101) -> 49.22205
D6: 000688.SH | E6: 科创50 | H6: =[1]!thsiFinD("ths_int_chg_ratio_index",$D6,H$1,H$2,101) -> -0.75739866 | I6: =[1]!thsiFinD("ths_int_chg_ratio_index",$D6,I$1,I$2,101) -> 38.344479 | J6: =[1]!thsiFinD("ths_int_chg_ratio_index",$D6,J$1,J$2,101) -> 29.300598 | K6: =[1]!thsiFinD("ths_int_chg_ratio_index",$D6,K$1,K$2,101) -> 76.253952 | L6: =[1]!thsiFinD("ths_int_chg_ratio_index",$D6,L$1,L$2,101) -> 130.62261 | M6: =[1]!thsiFinD("ths_int_chg_ratio_index",$D6,M$1,M$2,101) -> 65.012286 | N6: =[1]!thsiFinD("ths_int_chg_ratio_index",$D6,N$1,N$2,101) -> 35.924074 | O6: =[1]!thsiFinD("ths_int_chg_ratio_index",$D6,O$1,O$2,101) -> 16.071496 | ... T6: =[1]!thsiFinD("ths_int_chg_ratio_index",$D6,T$1,T$2,101) -> 0
D7: 399673.SZ | E7: 创业板50 | H7: =[1]!thsiFinD("ths_int_chg_ratio_index",$D7,H$1,H$2,101) -> 1.5096544 | I7: =[1]!thsiFinD("ths_int_chg_ratio_index",$D7,I$1,I$2,101) -> 32.523724 | J7: =[1]!thsiFinD("ths_int_chg_ratio_index",$D7,J$1,J$2,101) -> 30.957524 | K7: =[1]!thsiFinD("ths_int_chg_ratio_index",$D7,K$1,K$2,101) -> 122.85785 | L7: =[1]!thsiFinD("ths_int_chg_ratio_index",$D7,L$1,L$2,101) -> 151.06088 | M7: =[1]!thsiFinD("ths_int_chg_ratio_index",$D7,M$1,M$2,101) -> 107.4845 | N7: =[1]!thsiFinD("ths_int_chg_ratio_index",$D7,N$1,N$2,101) -> 57.452684 | O7: =[1]!thsiFinD("ths_int_chg_ratio_index",$D7,O$1,O$2,101) -> 21.06844 | ... T7: =[1]!thsiFinD("ths_int_chg_ratio_index",$D7,T$1,T$2,101) -> 50.925713
A8: js的基金，转换效率高 | B8: 指数 | D8: 013315.OF | E8: 嘉实中证科创创业50ETF发起式联接A | H8: =[1]!thsiFinD("ths_int_chg_ratio_index",$D8,H$1,H$2,101) -> 0 | I8: =[1]!thsiFinD("ths_int_chg_ratio_index",$D8,I$1,I$2,101) -> 0 | J8: =[1]!thsiFinD("ths_int_chg_ratio_index",$D8,J$1,J$2,101) -> 0 | K8: =[1]!thsiFinD("ths_int_chg_ratio_index",$D8,K$1,K$2,101) -> 0 | L8: =[1]!thsiFinD("ths_int_chg_ratio_index",$D8,L$1,L$2,101) -> 0 | M8: =[1]!thsiFinD("ths_int_chg_ratio_index",$D8,M$1,M$2,101) -> 0 | N8: =[1]!thsiFinD("ths_int_chg_ratio_index",$D8,N$1,N$2,101) -> 0 | O8: =[1]!thsiFinD("ths_int_chg_ratio_index",$D8,O$1,O$2,101) -> 0 | ... T8: =[1]!thsiFinD("ths_int_chg_ratio_index",$D8,T$1,T$2,101) -> 0
B9: 主动 | D9: 001170.OF | E9: 宏利复兴伟业A | F9: =[1]!thsiFinD("ths_fund_manager_current_fund",D9) -> 孙硕 | G9: 海外算力 | H9: =[1]!thsiFinD("ths_adjustment_nvg_ratio_fund",$D9,H$1,H$2,101) -> 6.8426396 | I9: =[1]!thsiFinD("ths_adjustment_nvg_ratio_fund",$D9,I$1,I$2,101) -> 75.166445 | J9: =[1]!thsiFinD("ths_adjustment_nvg_ratio_fund",$D9,J$1,J$2,101) -> 98.941399 | K9: =[1]!thsiFinD("ths_adjustment_nvg_ratio_fund",$D9,K$1,K$2,101) -> 315.31176 | L9: =[1]!thsiFinD("ths_adjustment_nvg_ratio_fund",$D9,L$1,L$2,101) -> 414.8728 | M9: =[1]!thsiFinD("ths_adjustment_nvg_ratio_fund",$D9,M$1,M$2,101) -> 281.58086 | N9: =[1]!thsiFinD("ths_adjustment_nvg_ratio_fund",$D9,N$1,N$2,101) -> 102.06264 | O9: =[1]!thsiFinD("ths_adjustment_nvg_ratio_fund",$D9,O$1,O$2,101) -> 33.299389 | ... T9: =[1]!thsiFinD("ths_adjustment_nvg_ratio_fund",$D9,T$1,T$2,101) -> 52.094972 | U9: =[1]!thsiFinD("ths_fund_establishment_date_fund",D9) -> 2015-04-21
B10: 主动 | D10: 016370.OF | E10: 信澳业绩驱动A | F10: =[1]!thsiFinD("ths_fund_manager_current_fund",D10) -> 童昌希 | G10: 海外算力 | H10: =[1]!thsiFinD("ths_adjustment_nvg_ratio_fund",$D10,H$1,H$2,101) -> 6.3711108 | I10: =[1]!thsiFinD("ths_adjustment_nvg_ratio_fund",$D10,I$1,I$2,101) -> 70.100541 | J10: =[1]!thsiFinD("ths_adjustment_nvg_ratio_fund",$D10,J$1,J$2,101) -> 86.833163 | K10: =[1]!thsiFinD("ths_adjustment_nvg_ratio_fund",$D10,K$1,K$2,101) -> 390.71843 | L10: =[1]!thsiFinD("ths_adjustment_nvg_ratio_fund",$D10,L$1,L$2,101) -> 513.10165 | M10: =[1]!thsiFinD("ths_adjustment_nvg_ratio_fund",$D10,M$1,M$2,101) -> 346.1861 | N10: =[1]!thsiFinD("ths_adjustment_nvg_ratio_fund",$D10,N$1,N$2,101) -> 143.08921 | O10: =[1]!thsiFinD("ths_adjustment_nvg_ratio_fund",$D10,O$1,O$2,101) -> 28.339223 | ... T10: =[1]!thsiFinD("ths_adjustment_nvg_ratio_fund",$D10,T$1,T$2,101) -> 0 | U10: =[1]!thsiFinD("ths_fund_establishment_date_fund",D10) -> 2022-08-25
B11: 主动 | D11: 017488.OF | E11: 嘉实信息产业A | F11: =[1]!thsiFinD("ths_fund_manager_current_fund",D11) -> 李涛 | G11: 海外算力、应用 | H11: =[1]!thsiFinD("ths_adjustment_nvg_ratio_fund",$D11,H$1,H$2,101) -> 5.6783145 | I11: =[1]!thsiFinD("ths_adjustment_nvg_ratio_fund",$D11,I$1,I$2,101) -> 66.047638 | J11: =[1]!thsiFinD("ths_adjustment_nvg_ratio_fund",$D11,J$1,J$2,101) -> 76.22108 | K11: =[1]!thsiFinD("ths_adjustment_nvg_ratio_fund",$D11,K$1,K$2,101) -> 204.66667 | L11: =[1]!thsiFinD("ths_adjustment_nvg_ratio_fund",$D11,L$1,L$2,101) -> 286.37858 | M11: =[1]!thsiFinD("ths_adjustment_nvg_ratio_fund",$D11,M$1,M$2,101) -> 189.7295 | N11: =[1]!thsiFinD("ths_adjustment_nvg_ratio_fund",$D11,N$1,N$2,101) -> 62.546138 | O11: =[1]!thsiFinD("ths_adjustment_nvg_ratio_fund",$D11,O$1,O$2,101) -> 21.316323 | ... T11: =[1]!thsiFinD("ths_adjustment_nvg_ratio_fund",$D11,T$1,T$2,101) -> 0 | U11: =[1]!thsiFinD("ths_fund_establishment_date_fund",D11) -> 2022-12-16
A12: 931994.CSI | D12: 004320.OF | E12: 前海开源沪港深乐享生活 | F12: =[1]!thsiFinD("ths_fund_manager_current_fund",D12) -> 魏淳,梁策 | G12: 海外算力 | H12: =[1]!thsiFinD("ths_adjustment_nvg_ratio_fund",$D12,H$1,H$2,101) -> 3.6564358 | I12: =[1]!thsiFinD("ths_adjustment_nvg_ratio_fund",$D12,I$1,I$2,101) -> 77.910325 | J12: =[1]!thsiFinD("ths_adjustment_nvg_ratio_fund",$D12,J$1,J$2,101) -> 102.45165 | K12: =[1]!thsiFinD("ths_adjustment_nvg_ratio_fund",$D12,K$1,K$2,101) -> 408.63653 | L12: =[1]!thsiFinD("ths_adjustment_nvg_ratio_fund",$D12,L$1,L$2,101) -> 498.6677 | M12: =[1]!thsiFinD("ths_adjustment_nvg_ratio_fund",$D12,M$1,M$2,101) -> 261.15025 | N12: =[1]!thsiFinD("ths_adjustment_nvg_ratio_fund",$D12,N$1,N$2,101) -> 122.08434 | O12: =[1]!thsiFinD("ths_adjustment_nvg_ratio_fund",$D12,O$1,O$2,101) -> 10.472294 | ... Q12: =[1]!thsiFinD("ths_adjustment_nvg_ratio_fund",$D12,Q$1,Q$2,101) -> -17.071806
B13: 主动 | D13: 000411.OF | E13: 景顺长城优质成长 | F13: =[1]!thsiFinD("ths_fund_manager_current_fund",D13) -> 张仲维 | G13: 海外算力 | H13: =[1]!thsiFinD("ths_adjustment_nvg_ratio_fund",$D13,H$1,H$2,101) -> 5.3633572 | I13: =[1]!thsiFinD("ths_adjustment_nvg_ratio_fund",$D13,I$1,I$2,101) -> 64.546036 | J13: =[1]!thsiFinD("ths_adjustment_nvg_ratio_fund",$D13,J$1,J$2,101) -> 72.486595 | K13: =[1]!thsiFinD("ths_adjustment_nvg_ratio_fund",$D13,K$1,K$2,101) -> 251.09141 | L13: =[1]!thsiFinD("ths_adjustment_nvg_ratio_fund",$D13,L$1,L$2,101) -> 306.2352 | M13: =[1]!thsiFinD("ths_adjustment_nvg_ratio_fund",$D13,M$1,M$2,101) -> 325.54866 | N13: =[1]!thsiFinD("ths_adjustment_nvg_ratio_fund",$D13,N$1,N$2,101) -> 91.527599 | O13: =[1]!thsiFinD("ths_adjustment_nvg_ratio_fund",$D13,O$1,O$2,101) -> 32.145886 | ... T13: =[1]!thsiFinD("ths_adjustment_nvg_ratio_fund",$D13,T$1,T$2,101) -> 39.847991 | U13: =[1]!thsiFinD("ths_fund_establishment_date_fund",D13) -> 2014-01-02
B14: 主动 | D14: 001480.OF | E14: 财通成长优选 | F14: =[1]!thsiFinD("ths_fund_manager_current_fund",D14) -> 金梓才 | G14: 海外算力 | H14: =[1]!thsiFinD("ths_adjustment_nvg_ratio_fund",$D14,H$1,H$2,101) -> 6.8810374 | I14: =[1]!thsiFinD("ths_adjustment_nvg_ratio_fund",$D14,I$1,I$2,101) -> 89.600939 | J14: =[1]!thsiFinD("ths_adjustment_nvg_ratio_fund",$D14,J$1,J$2,101) -> 103.14386 | K14: =[1]!thsiFinD("ths_adjustment_nvg_ratio_fund",$D14,K$1,K$2,101) -> 414.78649 | L14: =[1]!thsiFinD("ths_adjustment_nvg_ratio_fund",$D14,L$1,L$2,101) -> 362.33543 | M14: =[1]!thsiFinD("ths_adjustment_nvg_ratio_fund",$D14,M$1,M$2,101) -> 298.07787 | N14: =[1]!thsiFinD("ths_adjustment_nvg_ratio_fund",$D14,N$1,N$2,101) -> 84.244671 | O14: =[1]!thsiFinD("ths_adjustment_nvg_ratio_fund",$D14,O$1,O$2,101) -> 48.62259 | ... T14: =[1]!thsiFinD("ths_adjustment_nvg_ratio_fund",$D14,T$1,T$2,101) -> 72.928177 | U14: =[1]!thsiFinD("ths_fund_establishment_date_fund",D14) -> 2015-06-29
B15: 主动 | D15: 001323.OF | E15: 东吴移动互联网A | F15: =[1]!thsiFinD("ths_fund_manager_current_fund",D15) -> 刘元海 | G15: 海外算力+应用 | H15: =[1]!thsiFinD("ths_adjustment_nvg_ratio_fund",$D15,H$1,H$2,101) -> 2.6441434 | I15: =[1]!thsiFinD("ths_adjustment_nvg_ratio_fund",$D15,I$1,I$2,101) -> 42.116769 | J15: =[1]!thsiFinD("ths_adjustment_nvg_ratio_fund",$D15,J$1,J$2,101) -> 37.912513 | K15: =[1]!thsiFinD("ths_adjustment_nvg_ratio_fund",$D15,K$1,K$2,101) -> 163.95862 | L15: =[1]!thsiFinD("ths_adjustment_nvg_ratio_fund",$D15,L$1,L$2,101) -> 204.43784 | M15: =[1]!thsiFinD("ths_adjustment_nvg_ratio_fund",$D15,M$1,M$2,101) -> 216.99756 | N15: =[1]!thsiFinD("ths_adjustment_nvg_ratio_fund",$D15,N$1,N$2,101) -> 85.565207 | O15: =[1]!thsiFinD("ths_adjustment_nvg_ratio_fund",$D15,O$1,O$2,101) -> 32.398445 | ... T15: =[1]!thsiFinD("ths_adjustment_nvg_ratio_fund",$D15,T$1,T$2,101) -> 30.051813 | U15: =[1]!thsiFinD("ths_fund_establishment_date_fund",D15) -> 2015-05-27
B16: 主动 | D16: 001513.OF | E16: 易方达信息产业A | F16: =[1]!thsiFinD("ths_fund_manager_current_fund",D16) -> 郑希 | G16: 海外算力 | H16: =[1]!thsiFinD("ths_adjustment_nvg_ratio_fund",$D16,H$1,H$2,101) -> 4.6391753 | I16: =[1]!thsiFinD("ths_adjustment_nvg_ratio_fund",$D16,I$1,I$2,101) -> 62.95041 | J16: =[1]!thsiFinD("ths_adjustment_nvg_ratio_fund",$D16,J$1,J$2,101) -> 68.679186 | K16: =[1]!thsiFinD("ths_adjustment_nvg_ratio_fund",$D16,K$1,K$2,101) -> 273.26767 | L16: =[1]!thsiFinD("ths_adjustment_nvg_ratio_fund",$D16,L$1,L$2,101) -> 329.06895 | M16: =[1]!thsiFinD("ths_adjustment_nvg_ratio_fund",$D16,M$1,M$2,101) -> 259.04384 | N16: =[1]!thsiFinD("ths_adjustment_nvg_ratio_fund",$D16,N$1,N$2,101) -> 108.05117 | O16: =[1]!thsiFinD("ths_adjustment_nvg_ratio_fund",$D16,O$1,O$2,101) -> 24.906015 | ... T16: =[1]!thsiFinD("ths_adjustment_nvg_ratio_fund",$D16,T$1,T$2,101) -> 75.589744 | U16: =[1]!thsiFinD("ths_fund_establishment_date_fund",D16) -> 2016-09-27
D17: 931160.CSI | E17: 中证全指通信设备 | F17: 海外算力--指数 | H17: =[1]!thsiFinD("ths_int_chg_ratio_index",$D17,H$1,H$2,101) -> 7.4140967 | I17: =[1]!thsiFinD("ths_int_chg_ratio_index",$D17,I$1,I$2,101) -> 60.354301 | J17: =[1]!thsiFinD("ths_int_chg_ratio_index",$D17,J$1,J$2,101) -> 66.710083 | K17: =[1]!thsiFinD("ths_int_chg_ratio_index",$D17,K$1,K$2,101) -> 309.12449 | L17: =[1]!thsiFinD("ths_int_chg_ratio_index",$D17,L$1,L$2,101) -> 344.93839 | M17: =[1]!thsiFinD("ths_int_chg_ratio_index",$D17,M$1,M$2,101) -> 344.01633 | N17: =[1]!thsiFinD("ths_int_chg_ratio_index",$D17,N$1,N$2,101) -> 125.72805 | O17: =[1]!thsiFinD("ths_int_chg_ratio_index",$D17,O$1,O$2,101) -> 30.17831 | ... T17: =[1]!thsiFinD("ths_int_chg_ratio_index",$D17,T$1,T$2,101) -> 37.62724
D18: 013840.OF | E18: 银华集成电路A | F18: =[1]!thsiFinD("ths_fund_manager_current_fund",D18) -> 方建 | G18: 自主可控 | H18: =[1]!thsiFinD("ths_adjustment_nvg_ratio_fund",$D18,H$1,H$2,101) -> 0.75852868 | I18: =[1]!thsiFinD("ths_adjustment_nvg_ratio_fund",$D18,I$1,I$2,101) -> 56.497543 | J18: =[1]!thsiFinD("ths_adjustment_nvg_ratio_fund",$D18,J$1,J$2,101) -> 69.38357 | K18: =[1]!thsiFinD("ths_adjustment_nvg_ratio_fund",$D18,K$1,K$2,101) -> 172.88118 | L18: =[1]!thsiFinD("ths_adjustment_nvg_ratio_fund",$D18,L$1,L$2,101) -> 247.54141 | M18: =[1]!thsiFinD("ths_adjustment_nvg_ratio_fund",$D18,M$1,M$2,101) -> 145.8748 | N18: =[1]!thsiFinD("ths_adjustment_nvg_ratio_fund",$D18,N$1,N$2,101) -> 55.655296 | O18: =[1]!thsiFinD("ths_adjustment_nvg_ratio_fund",$D18,O$1,O$2,101) -> 10.956175 | ... Q18: =[1]!thsiFinD("ths_adjustment_nvg_ratio_fund",$D18,Q$1,Q$2,101) -> -13.228204
D19: 017744.OF | E19: 嘉实绿色主题A | F19: =[1]!thsiFinD("ths_fund_manager_current_fund",D19) -> 蔡丞丰 | G19: 自主可控 | H19: =[1]!thsiFinD("ths_adjustment_nvg_ratio_fund",$D19,H$1,H$2,101) -> 2.3760144 | I19: =[1]!thsiFinD("ths_adjustment_nvg_ratio_fund",$D19,I$1,I$2,101) -> 58.225908 | J19: =[1]!thsiFinD("ths_adjustment_nvg_ratio_fund",$D19,J$1,J$2,101) -> 74.360746 | K19: =[1]!thsiFinD("ths_adjustment_nvg_ratio_fund",$D19,K$1,K$2,101) -> 136.43274 | L19: =[1]!thsiFinD("ths_adjustment_nvg_ratio_fund",$D19,L$1,L$2,101) -> 261.97991 | M19: =[1]!thsiFinD("ths_adjustment_nvg_ratio_fund",$D19,M$1,M$2,101) -> 140.54025 | N19: =[1]!thsiFinD("ths_adjustment_nvg_ratio_fund",$D19,N$1,N$2,101) -> 48.715313 | O19: =[1]!thsiFinD("ths_adjustment_nvg_ratio_fund",$D19,O$1,O$2,101) -> 15.390697 | ... Q19: =[1]!thsiFinD("ths_adjustment_nvg_ratio_fund",$D19,Q$1,Q$2,101) -> 0
D20: 008185.OF | E20: 诺安研究优选A | F20: =[1]!thsiFinD("ths_fund_manager_current_fund",D20) -> 邓心怡,周靖翔 | G20: 自主可控 | H20: =[1]!thsiFinD("ths_adjustment_nvg_ratio_fund",$D20,H$1,H$2,101) -> 1.2754327 | I20: =[1]!thsiFinD("ths_adjustment_nvg_ratio_fund",$D20,I$1,I$2,101) -> 47.024247 | J20: =[1]!thsiFinD("ths_adjustment_nvg_ratio_fund",$D20,J$1,J$2,101) -> 44.019001 | K20: =[1]!thsiFinD("ths_adjustment_nvg_ratio_fund",$D20,K$1,K$2,101) -> 171.28525 | L20: =[1]!thsiFinD("ths_adjustment_nvg_ratio_fund",$D20,L$1,L$2,101) -> 129.97357 | M20: =[1]!thsiFinD("ths_adjustment_nvg_ratio_fund",$D20,M$1,M$2,101) -> 80.497925 | N20: =[1]!thsiFinD("ths_adjustment_nvg_ratio_fund",$D20,N$1,N$2,101) -> 87.200216 | O20: =[1]!thsiFinD("ths_adjustment_nvg_ratio_fund",$D20,O$1,O$2,101) -> -23.571208 | ... Q20: =[1]!thsiFinD("ths_adjustment_nvg_ratio_fund",$D20,Q$1,Q$2,101) -> -26.63347
D21: 019437.OF | E21: 华商科创创业精选A | F21: =[1]!thsiFinD("ths_fund_manager_current_fund",D21) -> 刘力 | G21: 自主可控 | H21: =[1]!thsiFinD("ths_adjustment_nvg_ratio_fund",$D21,H$1,H$2,101) -> 0.295733 | I21: =[1]!thsiFinD("ths_adjustment_nvg_ratio_fund",$D21,I$1,I$2,101) -> 45.478421 | J21: =[1]!thsiFinD("ths_adjustment_nvg_ratio_fund",$D21,J$1,J$2,101) -> 56.478343
D22: 162214.OF | E22: 宏利领先小盘 | F22: =[1]!thsiFinD("ths_fund_manager_current_fund",D22) -> 张岩 | G22: 自主可控 | H22: =[1]!thsiFinD("ths_adjustment_nvg_ratio_fund",$D22,H$1,H$2,101) -> 2.8118609 | I22: =[1]!thsiFinD("ths_adjustment_nvg_ratio_fund",$D22,I$1,I$2,101) -> 50.975976 | J22: =[1]!thsiFinD("ths_adjustment_nvg_ratio_fund",$D22,J$1,J$2,101) -> 54.217791 | K22: =[1]!thsiFinD("ths_adjustment_nvg_ratio_fund",$D22,K$1,K$2,101) -> 137.98817 | L22: =[1]!thsiFinD("ths_adjustment_nvg_ratio_fund",$D22,L$1,L$2,101) -> 184.84419 | M22: =[1]!thsiFinD("ths_adjustment_nvg_ratio_fund",$D22,M$1,M$2,101) -> 130.61927 | N22: =[1]!thsiFinD("ths_adjustment_nvg_ratio_fund",$D22,N$1,N$2,101) -> 51.627907 | O22: =[1]!thsiFinD("ths_adjustment_nvg_ratio_fund",$D22,O$1,O$2,101) -> 13.157895 | ... Q22: =[1]!thsiFinD("ths_adjustment_nvg_ratio_fund",$D22,Q$1,Q$2,101) -> -24.067797
D23: 931743.CSI | E23: 中证半导体材料设备 | F23: 自主可控-指数 | H23: =[1]!thsiFinD("ths_int_chg_ratio_index",$D23,H$1,H$2,101) -> 2.7088576 | I23: =[1]!thsiFinD("ths_int_chg_ratio_index",$D23,I$1,I$2,101) -> 52.296382 | J23: =[1]!thsiFinD("ths_int_chg_ratio_index",$D23,J$1,J$2,101) -> 62.207805 | K23: =[1]!thsiFinD("ths_int_chg_ratio_index",$D23,K$1,K$2,101) -> 148.1036 | L23: =[1]!thsiFinD("ths_int_chg_ratio_index",$D23,L$1,L$2,101) -> 204.44343 | M23: =[1]!thsiFinD("ths_int_chg_ratio_index",$D23,M$1,M$2,101) -> 124.23476 | N23: =[1]!thsiFinD("ths_int_chg_ratio_index",$D23,N$1,N$2,101) -> 53.69537 | O23: =[1]!thsiFinD("ths_int_chg_ratio_index",$D23,O$1,O$2,101) -> 9.6843434 | ... T23: =[1]!thsiFinD("ths_int_chg_ratio_index",$D23,T$1,T$2,101) -> 119.05451
